Workbook

Sheet Construccion1 (ch)
A2: Descripción series | B2: 2002 | C2: 2003 | D2: 2004 | E2: 2005 | F2: 2006 | G2: 2007 | H2: 2008 | I2: 2009 | J2: 2010 | K2: 2011 | L2: 2012 | M2: 2013 | N2: 2014 | O2: 2015 | P2: 2016 | Q2: 2017 | R2: 2018 | S2: 2019 | T2: 2020 | U2: 2021 | V2: 2022 | W2: 2023 | X2: 2024
A3: IPV General. | B3: 82.4 | C3: 84.23 | D3: 89.13 | E3: 92.3 | F3: 94.79 | G3: 98.78 | H3: 100 | I3: 102.27 | J3: 108.77 | K3: 118.1 | L3: 126.74 | M3: 137.04 | N3: 148.27 | O3: 160.65 | P3: 165.03 | Q3: 174.68 | R3: 187.58 | S3: 198.33 | T3: 205.27 | U3: 219.6 | V3: 210.37 | W3: 210.99 | X3: 217.31
A4: IPV Casas | B4: 78.1 | C4: 80.96 | D4: 87.8 | E4: 91.02 | F4: 94.34 | G4: 98.51 | H4: 100 | I4: 102.31 | J4: 110.82 | K4: 122.58 | L4: 130.35 | M4: 140.16 | N4: 151.08 | O4: 161.84 | P4: 164.58 | Q4: 173.25 | R4: 189.31 | S4: 201.51 | T4: 207.46 | U4: 225.89 | V4: 212.01 | W4: 213.88 | X4: 221.63
A5: IPV Casas Nuevas | B5: 70.7 | C5: 74.87 | D5: 82.49 | E5: 85.98 | F5: 91.54 | G5: 95.92 | H5: 100 | I5: 102.89 | J5: 104.18 | K5: 118.54 | L5: 129.72 | M5: 135.89 | N5: 143.52 | O5: 157.52 | P5: 160.13 | Q5: 167.25 | R5: 175.71 | S5: 184.43 | T5: 195.66 | U5: 203.85 | V5: 211.14
A6: IPV Casas Usadas | B6: 85.3 | C6: 86.81 | D6: 92.76 | E6: 95.7 | F6: 96.81 | G6: 100.8 | H6: 100 | I6: 101.88 | J6: 115.64 | K6: 125.34 | L6: 131 | M6: 143.26 | N6: 156.33 | O6: 165.12 | P6: 167.95 | Q6: 177.56 | R6: 198.79 | S6: 213.03 | T6: 216.58 | U6: 240.72 | V6: 218.6 | W6: 216.65 | X6: 222.65
A7: IPV Departamentos | B7: 89.96 | C7: 89.88 | D7: 91.13 | E7: 94.21 | F7: 95.43 | G7: 99.15 | H7: 100 | I7: 102.23 | J7: 106.51 | K7: 112.96 | L7: 122.6 | M7: 133.61 | N7: 145.28 | O7: 159.42 | P7: 165.49 | Q7: 176.1 | R7: 186.31 | S7: 195.76 | T7: 203.51 | U7: 214.16 | V7: 209.18 | W7: 208.67 | X7: 213.68
A8: IPV Departamentos Nuevos | B8: 86.38 | C8: 86.95 | D8: 86.67 | E8: 90.8 | F8: 93.12 | G8: 98.09 | H8: 100 | I8: 100.06 | J8: 99.32 | K8: 104.61 | L8: 112.92 | M8: 118.8 | N8: 126.74 | O8: 141.06 | P8: 147.65 | Q8: 158.9 | R8: 166.15 | S8: 172.66 | T8: 181.67 | U8: 187.7 | V8: 194.13 | W8: 192.94 | X8: 199.91
A9: IPV Departamentos Usados | B9: 97.06 | C9: 96.04 | D9: 99.64 | E9: 100.95 | F9: 100.07 | G9: 101.43 | H9: 100 | I9: 106.64 | J9: 124.11 | K9: 133.5 | L9: 146.18 | M9: 165.58 | N9: 183.99 | O9: 197.72 | P9: 202.79 | Q9: 211.68 | R9: 229.43 | S9: 244.88 | T9: 249.79 | U9: 271.66 | V9: 248.43 | W9: 249.23 | X9: 250.41
A10: IPV Nuevas | B10: 77.08 | C10: 79.89 | D10: 84.52 | E10: 88.3 | F10: 92.36 | G10: 97.03 | H10: 100 | I10: 101.35 | J10: 101.39 | K10: 110.5 | L10: 119.97 | M10: 125.94 | N10: 133.71 | O10: 147.98 | P10: 153.18 | Q10: 163.11 | R10: 170.82 | S10: 178.11 | T10: 187.85 | U10: 194.72 | V10: 201.48 | W10: 203.82 | X10: 212.31
A11: IPV Usadas | B11: 88.9 | C11: 89.62 | D11: 94.86 | E11: 97.3 | F11: 97.79 | G11: 100.99 | H11: 100 | I11: 103.32 | J11: 118.2 | K11: 127.82 | L11: 135.66 | M11: 150.22 | N11: 165.02 | O11: 175.39 | P11: 178.96 | Q11: 188.31 | R11: 208.23 | S11: 222.79 | T11: 226.8 | U11: 249.96 | V11: 227.62 | W11: 226.63 | X11: 230.88
A13: El IPV (índice de precio de la vivienda) se elabora sobre la base de registros administrativos innominados del Servicio de Impuestos Internos, correspondientes a transacciones efectivas del valor de viviendas nuevas y usadas

Sheet Construccion2(Ch)
B2: Índice de Precios de Materiales e Insumos de Construcción (IPMIC) | C2: 2019 | D2: 2020 | E2: 2021 | F2: 2022 | G2: 2023 | H2: 2024
B3: Construcción de edificios | C3: 100 | D3: 106.05 | E3: 127.99 | F3: 158.4 | G3: 157.84 | H3: 162.88
B4: Construcción de obras de ingeniería civil | C4: 100 | D4: 106.98 | E4: 129.11 | F4: 159.77 | G4: 160.88 | H4: 166.09
B5: Actividades especializadas de construcción | C5: 100 | D5: 104.79 | E5: 127.87 | F5: 162.08 | G5: 160.14 | H5: 163.77
B6: Madera aserrada, cepillada y astillada | C6: 100 | D6: 106.16 | E6: 127.33 | F6: 155.4 | G6: 154.55 | H6: 160.29
B7: Tableros y madera prensada | C7: 100 | D7: 104.08 | E7: 125.34 | F7: 154.11 | G7: 142.28 | H7: 144.32
B8: Otros productos químicos básicos | C8: 100 | D8: 111.93 | E8: 140.81 | F8: 177.2 | G8: 159.06 | H8: 168.46
B9: Pinturas y barnices | C9: 100 | D9: 106.95 | E9: 122.72 | F9: 159.5 | G9: 159.23 | H9: 166.3
B10: Productos de plástico | C10: 100 | D10: 103.08 | E10: 110.7 | F10: 133.52 | G10: 148.91 | H10: 166.12
B11: Otros productos de vidrio | C11: 100 | D11: 104.67 | E11: 126.39 | F11: 152.63 | G11: 147.28 | H11: 150.69
B12: Cemento, cal y yeso | C12: 100 | D12: 105.81 | E12: 117.49 | F12: 150.51 | G12: 158.72 | H12: 168.82
B13: Hormigón premezclado | C13: 100 | D13: 103.78 | E13: 117.19 | F13: 140.82 | G13: 144.17 | H13: 140.97
... B23: Muebles | C23: 100 | D23: 108.64 | E23: 125.03 | F23: 132.57 | G23: 130.63 | H23: 133.17

Sheet Construccion 3 (ch)
B2: MERCADO NACIONAL | D2: Departamentos | G2: Casas | J2: Viviendas
D3: Stock | E3: Ventas | F3: Meses | G3: Stock | H3: Ventas | I3: Meses | J3: Stock | K3: Ventas | L3: Meses
B4: 2004 | C4: Ene | D4: 37212 | E4: 1750 | F4: 21.3 | G4: 18771 | H4: 1199 | I4: 15.7 | J4: 55983 | K4: 2949 | L4: 19
C5: Feb | D5: 36793 | E5: 1699 | F5: 21.7 | G5: 17857 | H5: 1214 | I5: 14.7 | J5: 54650 | K5: 2913 | L5: 18.8
C6: Mar | D6: 35743 | E6: 2103 | F6: 17 | G6: 17509 | H6: 1820 | I6: 9.6 | J6: 53252 | K6: 3923 | L6: 13.6
C7: Abr | D7: 35796 | E7: 2272 | F7: 15.8 | G7: 16304 | H7: 1967 | I7: 8.3 | J7: 52099 | K7: 4238 | L7: 12.3
C8: May | D8: 38372 | E8: 2651 | F8: 14.5 | G8: 17056 | H8: 1982 | I8: 8.6 | J8: 55428 | K8: 4633 | L8: 12 | N8: Las cifras fueron revisadas a partir de CASEN 2020, en base a la actualización de la metodología de expansión de las cifras nacionales.
C9: Jun | D9: 36053 | E9: 2522 | F9: 14.3 | G9: 19232 | H9: 1882 | I9: 10.2 | J9: 55285 | K9: 4405 | L9: 12.6
C10: Jul | D10: 36993 | E10: 2965 | F10: 12.5 | G10: 18557 | H10: 2592 | I10: 7.2 | J10: 55550 | K10: 5556 | L10: 10 | N10: Stock: unidades de viviendas (departamentos o casas) disponibles para venta en cada momento del tiempo.
C11: Ago | D11: 35279 | E11: 2912 | F11: 12.1 | G11: 16985 | H11: 2654 | I11: 6.4 | J11: 52265 | K11: 5566 | L11: 9.4 | N11: Ventas: promesas de compraventa firmadas en cada momento del tiempo.
C12: Sep | D12: 37220 | E12: 2679 | F12: 13.9 | G12: 17637 | H12: 2160 | I12: 8.2 | J12: 54857 | K12: 4838 | L12: 11.3 | N12: Meses: medida de la velocidad de ventas que se calcula como el cociente entre el stock disponible en un mes concreto y las unidades vendidas en ese mismo mes. Representa el número de meses necesarios para vender todo el stock disponible asumiendo que el ritmo de ventas se mantendrá estable y no habrá ingreso de nuevas unidades.
C13: Oct | D13: 37797 | E13: 2471 | F13: 15.3 | G13: 17097 | H13: 2245 | I13: 7.6 | J13: 54893 | K13: 4716 | L13: 11.6
C14: Nov | D14: 40766 | E14: 1938 | F14: 21 | G14: 15830 | H14: 1973 | I14: 8 | J14: 56596 | K14: 3911 | L14: 14.5
C15: Dic | D15: 34830 | E15: 1735 | F15: 20.1 | G15: 14846 | H15: 1430 | I15: 10.4 | J15: 49676 | K15: 3164 | L15: 15.7
B16: 2005 | C16: Ene | D16: 35568 | E16: 1870 | F16: 19 | G16: 15008 | H16: 1471 | I16: 10.2 | J16: 50576 | K16: 3341 | L16: 15.1
C17: Feb | D17: 38333 | E17: 1968 | F17: 19.5 | G17: 15590 | H17: 1673 | I17: 9.3 | J17: 53922 | K17: 3641 | L17: 14.8
C18: Mar | D18: 38282 | E18: 1969 | F18: 19.4 | G18: 17175 | H18: 2100 | I18: 8.2 | J18: 55456 | K18: 4069 | L18: 13.6
C19: Abr | D19: 40939 | E19: 2546 | F19: 16.1 | G19: 16545 | H19: 1849 | I19: 8.9 | J19: 57483 | K19: 4395 | L19: 13.1
C20: May | D20: 47786 | E20: 2821 | F20: 16.9 | G20: 16436 | H20: 2612 | I20: 6.3 | J20: 64223 | K20: 5433 | L20: 11.8
C21: Jun | D21: 49856 | E21: 2761 | F21: 18.1 | G21: 15267 | H21: 2307 | I21: 6.6 | J21: 65123 | K21: 5068 | L21: 12.8
C22: Jul | D22: 49296 | E22: 3276 | F22: 15 | G22: 15662 | H22: 2545 | I22: 6.2 | J22: 64958 | K22: 5821 | L22: 11.2
C23: Ago | D23: 47640 | E23: 3471 | F23: 13.7 | G23: 14976 | H23: 2452 | I23: 6.1 | J23: 62615 | K23: 5923 | L23: 10.6
C24: Sep | D24: 46886 | E24: 2953 | F24: 15.9 | G24: 14443 | H24: 2092 | I24: 6.9 | J24: 61329 | K24: 5045 | L24: 12.2
C25: Oct | D25: 45234 | E25: 2572 | F25: 17.6 | G25: 15269 | H25: 2860 | I25: 5.3 | J25: 60503 | K25: 5432 | L25: 11.1
C26: Nov | D26: 43665 | E26: 2834 | F26: 15.4 | G26: 14956 | H26: 2265 | I26: 6.6 | J26: 58621 | K26: 5099 | L26: 11.5
C27: Dic | D27: 43100 | E27: 2066 | F27: 20.9 | G27: 14765 | H27: 1556 | I27: 9.5 | J27: 57865 | K27: 3622 | L27: 16
B28: 2006 | C28: Ene | D28: 43176 | E28: 1980 | F28: 21.8 | G28: 14869 | H28: 1941 | I28: 7.7 | J28: 58045 | K28: 3922 | L28: 14.8
C29: Feb | D29: 42279 | E29: 2196 | F29: 19.3 | G29: 14277 | H29: 2075 | I29: 6.9 | J29: 56556 | K29: 4271 | L29: 13.2
C30: Mar | D30: 43343 | E30: 2578 | F30: 16.8 | G30: 14552 | H30: 1894 | I30: 7.7 | J30: 57895 | K30: 4472 | L30: 12.9
C31: Abr | D31: 41578 | E31: 2313 | F31: 18 | G31: 16750 | H31: 2200 | I31: 7.6 | J31: 58329 | K31: 4513 | L31: 12.9
C32: May | D32: 46248 | E32: 2837 | F32: 16.3 | G32: 16305 | H32: 2317 | I32: 7 | J32: 62553 | K32: 5154 | L32: 12.1
C33: Jun | D33: 47092 | E33: 2782 | F33: 16.9 | G33: 16877 | H33: 2063 | I33: 8.2 | J33: 63968 | K33: 4845 | L33: 13.2
C34: Jul | D34: 52255 | E34: 3307 | F34: 15.8 | G34: 19993 | H34: 2269 | I34: 8.8 | J34: 72248 | K34: 5576 | L34: 13
C35: Ago | D35: 54149 | E35: 3644 | F35: 14.9 | G35: 20928 | H35: 2691 | I35: 7.8 | J35: 75076 | K35: 6335 | L35: 11.9
C36: Sep | D36: 52658 | E36: 2699 | F36: 19.5 | G36: 20057 | H36: 2538 | I36: 7.9 | J36: 72715 | K36: 5237 | L36: 13.9
C37: Oct | D37: 51709 | E37: 3147 | F37: 16.4 | G37: 19458 | H37: 2585 | I37: 7.5 | J37: 71167 | K37: 5732 | L37: 12.4
C38: Nov | D38: 50449 | E38: 2766 | F38: 18.2 | G38: 22644 | H38: 2704 | I38: 8.4 | J38: 73094 | K38: 5470 | L38: 13.4
C39: Dic | D39: 49981 | E39: 2071 | F39: 24.1 | G39: 20843 | H39: 1454 | I39: 14.3 | J39: 70824 | K39: 3525 | L39: 20.1
B40: 2007 | C40: Ene | D40: 49086 | E40: 2447 | F40: 20.1 | G40: 18111 | H40: 1843 | I40: 9.8 | J40: 67197 | K40: 4290 | L40: 15.7
C41: Feb | D41: 48067 | E41: 2587 | F41: 18.6 | G41: 17457 | H41: 1707 | I41: 10.2 | J41: 65524 | K41: 4295 | L41: 15.3
C42: Mar | D42: 52477 | E42: 3078 | F42: 17 | G42: 15713 | H42: 2172 | I42: 7.2 | J42: 68190 | K42: 5251 | L42: 13
C43: Abr | D43: 52754 | E43: 2654 | F43: 19.9 | G43: 15586 | H43: 2075 | I43: 7.5 | J43: 68340 | K43: 4729 | L43: 14.5
C44: May | D44: 56426 | E44: 2651 | F44: 21.3 | G44: 17712 | H44: 2296 | I44: 7.7 | J44: 74138 | K44: 4947 | L44: 15
C45: Jun | D45: 58178 | E45: 2716 | F45: 21.4 | G45: 16719 | H45: 1927 | I45: 8.7 | J45: 74897 | K45: 4643 | L45: 16.1
C46: Jul | D46: 61136 | E46: 3155 | F46: 19.4 | G46: 18188 | H46: 1986 | I46: 9.2 | J46: 79324 | K46: 5141 | L46: 15.4
C47: Ago | D47: 66172 | E47: 3412 | F47: 19.4 | G47: 20212 | H47: 2076 | I47: 9.7 | J47: 86384 | K47: 5488 | L47: 15.7
C48: Sep | D48: 64842 | E48: 2369 | F48: 27.4 | G48: 23365 | H48: 1961 | I48: 11.9 | J48: 88207 | K48: 4329 | L48: 20.4
C49: Oct | D49: 64369 | E49: 2908 | F49: 22.1 | G49: 24943 | H49: 3008 | I49: 8.3 | J49: 89312 | K49: 5915 | L49: 15.1
C50: Nov | D50: 63708 | E50: 2534 | F50: 25.1 | G50: 27186 | H50: 2808 | I50: 9.7 | J50: 90894 | K50: 5342 | L50: 17
C51: Dic | D51: 68387 | E51: 2455 | F51: 27.9 | G51: 24992 | H51: 1582 | I51: 15.8 | J51: 93379 | K51: 4037 | L51: 23.1
B52: 2008 | C52: Ene | D52: 66419 | E52: 2592 | F52: 25.6 | G52: 26084 | H52: 2092 | I52: 12.5 | J52: 92503 | K52: 4684 | L52: 19.7
C53: Feb | D53: 64227 | E53: 2902 | F53: 22.1 | G53: 25222 | H53: 1831 | I53: 13.8 | J53: 89449 | K53: 4733 | L53: 18.9
C54: Mar | D54: 60846 | E54: 3050 | F54: 19.9 | G54: 22363 | H54: 2711 | I54: 8.2 | J54: 83209 | K54: 5761 | L54: 14.4
C55: Abr | D55: 63021 | E55: 1974 | F55: 31.9 | G55: 22133 | H55: 1667 | I55: 13.3 | J55: 85154 | K55: 3641 | L55: 23.4
C56: May | D56: 62404 | E56: 2414 | F56: 25.8 | G56: 24829 | H56: 1836 | I56: 13.5 | J56: 87232 | K56: 4250 | L56: 20.5
C57: Jun | D57: 61931 | E57: 2390 | F57: 25.9 | G57: 24454 | H57: 1704 | I57: 14.3 | J57: 86385 | K57: 4094 | L57: 21.1
C58: Jul | D58: 62952 | E58: 2626 | F58: 24 | G58: 23501 | H58: 1609 | I58: 14.6 | J58: 86453 | K58: 4235 | L58: 20.4
C59: Ago | D59: 65524 | E59: 2418 | F59: 27.1 | G59: 23273 | H59: 1384 | I59: 16.8 | J59: 88797 | K59: 3803 | L59: 23.4
C60: Sep | D60: 64500 | E60: 2060 | F60: 31.3 | G60: 23205 | H60: 1328 | I60: 17.5 | J60: 87704 | K60: 3388 | L60: 25.9
C61: Oct | D61: 66925 | E61: 2348 | F61: 28.5 | G61: 23812 | H61: 1338 | I61: 17.8 | J61: 90737 | K61: 3686 | L61: 24.6
C62: Nov | D62: 65050 | E62: 1851 | F62: 35.1 | G62: 24702 | H62: 1099 | I62: 22.5 | J62: 89752 | K62: 2950 | L62: 30.4
C63: Dic | D63: 65429 | E63: 1841 | F63: 35.5 | G63: 24712 | H63: 1188 | I63: 20.8 | J63: 90141 | K63: 3029 | L63: 29.8
B64: 2009 | C64: Ene | D64: 63745 | E64: 2080 | F64: 30.6 | G64: 24856 | H64: 1229 | I64: 20.2 | J64: 88601 | K64: 3309 | L64: 26.8
C65: Feb | D65: 63524 | E65: 2306 | F65: 27.5 | G65: 23885 | H65: 1329 | I65: 18 | J65: 87409 | K65: 3635 | L65: 24
C66: Mar | D66: 62316 | E66: 2871 | F66: 21.7 | G66: 23441 | H66: 1764 | I66: 13.3 | J66: 85757 | K66: 4635 | L66: 18.5
C67: Abr | D67: 62144 | E67: 2693 | F67: 23.1 | G67: 22078 | H67: 1779 | I67: 12.4 | J67: 84222 | K67: 4472 | L67: 18.8
C68: May | D68: 61089 | E68: 3069 | F68: 19.9 | G68: 21613 | H68: 1699 | I68: 12.7 | J68: 82702 | K68: 4768 | L68: 17.3
C69: Jun | D69: 62108 | E69: 3460 | F69: 18 | G69: 21075 | H69: 1615 | I69: 13 | J69: 83183 | K69: 5075 | L69: 16.4
C70: Jul | D70: 56836 | E70: 3189 | F70: 17.8 | G70: 18663 | H70: 1696 | I70: 11 | J70: 75499 | K70: 4885 | L70: 15.5
C71: Ago | D71: 65058 | E71: 3248 | F71: 20 | G71: 18646 | H71: 1595 | I71: 11.7 | J71: 83704 | K71: 4843 | L71: 17.3
C72: Sep | D72: 63985 | E72: 2729 | F72: 23.4 | G72: 18125 | H72: 1499 | I72: 12.1 | J72: 82110 | K72: 4228 | L72: 19.4
C73: Oct | D73: 63103 | E73: 3150 | F73: 20 | G73: 16694 | H73: 1468 | I73: 11.4 | J73: 79797 | K73: 4618 | L73: 17.3
C74: Nov | D74: 61993 | E74: 2930 | F74: 21.2 | G74: 15143 | H74: 1453 | I74: 10.4 | J74: 77136 | K74: 4383 | L74: 17.6
C75: Dic | D75: 59811 | E75: 2410 | F75: 24.8 | G75: 14210 | H75: 1408 | I75: 10.1 | J75: 74021 | K75: 3818 | L75: 19.4
B76: 2010 | C76: Ene | D76: 58395 | E76: 2181 | F76: 26.8 | G76: 14555 | H76: 1290 | I76: 11.3 | J76: 72950 | K76: 3471 | L76: 21
C77: Feb | D77: 58058 | E77: 1891 | F77: 30.7 | G77: 14225 | H77: 1305 | I77: 10.9 | J77: 72283 | K77: 3196 | L77: 22.6
C78: Mar | D78: 56431 | E78: 1423 | F78: 39.7 | G78: 13883 | H78: 1311 | I78: 10.6 | J78: 70314 | K78: 2734 | L78: 25.7
C79: Abr | D79: 56393 | E79: 1810 | F79: 31.2 | G79: 12836 | H79: 1301 | I79: 9.9 | J79: 69229 | K79: 3111 | L79: 22.3
C80: May | D80: 57156 | E80: 1783 | F80: 32.1 | G80: 13199 | H80: 1334 | I80: 9.9 | J80: 70355 | K80: 3117 | L80: 22.6
C81: Jun | D81: 58758 | E81: 2334 | F81: 25.2 | G81: 13228 | H81: 1311 | I81: 10.1 | J81: 71986 | K81: 3645 | L81: 19.7
C82: Jul | D82: 56870 | E82: 2241 | F82: 25.4 | G82: 14090 | H82: 1341 | I82: 10.5 | J82: 70960 | K82: 3582 | L82: 19.8
C83: Ago | D83: 54811 | E83: 2998 | F83: 18.3 | G83: 13189 | H83: 1654 | I83: 8 | J83: 68000 | K83: 4652 | L83: 14.6
C84: Sep | D84: 53495 | E84: 2949 | F84: 18.1 | G84: 13575 | H84: 1386 | I84: 9.8 | J84: 67070 | K84: 4335 | L84: 15.5
C85: Oct | D85: 51923 | E85: 3216 | F85: 16.1 | G85: 13061 | H85: 1575 | I85: 8.3 | J85: 64984 | K85: 4791 | L85: 13.6
C86: Nov | D86: 52578 | E86: 2484 | F86: 21.2 | G86: 13318 | H86: 1639 | I86: 8.1 | J86: 65896 | K86: 4123 | L86: 16
C87: Dic | D87: 55464 | E87: 2431 | F87: 22.8 | G87: 14429 | H87: 1646 | I87: 8.8 | J87: 69893 | K87: 4077 | L87: 17.1
B88: 2011 | C88: Ene | D88: 52847 | E88: 2116 | F88: 25 | G88: 15180 | H88: 1216 | I88: 12.5 | J88: 68027 | K88: 3332 | L88: 20.4
C89: Feb | D89: 52187 | E89: 2401 | F89: 21.7 | G89: 14774 | H89: 1401 | I89: 10.5 | J89: 66961 | K89: 3802 | L89: 17.6
C90: Mar | D90: 51894 | E90: 2572 | F90: 20.2 | G90: 15422 | H90: 1854 | I90: 8.3 | J90: 67316 | K90: 4426 | L90: 15.2
C91: Abr | D91: 52803 | E91: 2679 | F91: 19.7 | G91: 14789 | H91: 1838 | I91: 8 | J91: 67592 | K91: 4517 | L91: 15
C92: May | D92: 53126 | E92: 3104 | F92: 17.1 | G92: 16375 | H92: 1911 | I92: 8.6 | J92: 69501 | K92: 5015 | L92: 13.9
C93: Jun | D93: 54856 | E93: 2617 | F93: 21 | G93: 16422 | H93: 1958 | I93: 8.4 | J93: 71278 | K93: 4575 | L93: 15.6
C94: Jul | D94: 56385 | E94: 2624 | F94: 21.5 | G94: 17973 | H94: 2124 | I94: 8.5 | J94: 74358 | K94: 4748 | L94: 15.7
C95: Ago | D95: 57748 | E95: 2833 | F95: 20.4 | G95: 18175 | H95: 2361 | I95: 7.7 | J95: 75923 | K95: 5194 | L95: 14.6
C96: Sep | D96: 58869 | E96: 2853 | F96: 20.6 | G96: 17948 | H96: 2614 | I96: 6.9 | J96: 76817 | K96: 5467 | L96: 14.1
C97: Oct | D97: 61660 | E97: 3135 | F97: 19.7 | G97: 17123 | H97: 2614 | I97: 6.6 | J97: 78783 | K97: 5749 | L97: 13.7
C98: Nov | D98: 60779 | E98: 3066 | F98: 19.8 | G98: 18917 | H98: 2301 | I98: 8.2 | J98: 79696 | K98: 5367 | L98: 14.8
C99: Dic | D99: 59684 | E99: 2734 | F99: 21.8 | G99: 18312 | H99: 1939 | I99: 9.4 | J99: 77996 | K99: 4673 | L99: 16.7
B100: 2012 | C100: Ene | D100: 54440 | E100: 2527 | F100: 21.5 | G100: 21860 | H100: 1905 | I100: 11.5 | J100: 76300 | K100: 4432 | L100: 17.2
C101: Feb | D101: 57772 | E101: 2567 | F101: 22.5 | G101: 21863 | H101: 1876 | I101: 11.7 | J101: 79635 | K101: 4443 | L101: 17.9
...

Sheet Construccion1 (Mex)
A2: Gasto del producto interno bruto, volumen a precios del año anterior encadenado, series empalmadas, referencia 2018 (miles de millones de pesos encadenados CLP)
A3: Total México | B3: Descripción series | C3: 2002 | D3: 2003 | E3: 2004 | F3: 2005 | G3: 2006 | H3: 2007 | I3: 2008 | J3: 2009 | K3: 2010 | L3: 2011 | M3: 2012 | N3: 2013 | O3: 2014 | P3: 2015 | Q3: 2016 | R3: 2017 | S3: 2018 | T3: 2019 | U3: 2020 | V3: 2021 | W3: 2022 | X3: 2023 | Y3: 2024
B4: Construcción y otras obras | C4: 13963.74 | D4: 15325.32 | E4: 16617.02 | F4: 18525.83 | G4: 19888.48 | H4: 21555.32 | I4: 24178.88 | J4: 22772.09 | K4: 23222.17 | L4: 25594.85 | M4: 28128.62 | N4: 29200.35 | O4: 28398.77 | P4: 29397.74 | Q4: 28739.03 | R4: 27006.44 | S4: 28201.33 | T4: 29664.86 | U4: 26663.74 | V4: 29438.1 | W4: 30850.77 | X4: 30743.33 | Y4: 30637.68
A7: N° de Vivienda
A8: Total México | B8: Descripción series | C8: 2008 | D8: 2009 | E8: 2010 | F8: 2011 | G8: 2012 | H8: 2013 | I8: 2014 | J8: 2015 | K8: 2016 | L8: 2017 | M8: 2018 | N8: 2019 | O8: 2020 | P8: 2021 | Q8: 2022 | R8: 2023 | S8: 2024
B9: Vivienda (número) | C9: 150911 | D9: 140619 | E9: 96036 | F9: 151071 | G9: 117310 | H9: 118796 | I9: 150453 | J9: 179402 | K9: 122967 | L9: 133914 | M9: 150491 | N9: 159182 | O9: 123779 | P9: 146370 | Q9: 117950 | R9: 90589 | S9: 86013
A11: Número de viviendas autorizadas en obras nuevas, total país (CH)
A14: Concepto | B14: 2013 | C14: 2014 | D14: 2015 | E14: 2016 | F14: 2017 | G14: 2018 | H14: 2019 | I14: 2020 | J14: 2021 | K14: 2022 P | L14: 2023 P
A16: PIB de la vivienda | B16: 857.599 | C16: 907.83 | D16: 969.042 | E16: 1,065,073 | F16: 1,156,240 | G16: 1,235,753 | H16: 1,292,515 | I16: 1,180,524 | J16: 1,358,009 | K16: 1,484,766 | L16: 1,596,333
A17: Proporción respecto al total nacional (porcentaje) | B17: 45721 | C17: 45721 | D17: 45721 | E17: 45782 | F17: 45752 | G17: 45752 | H17: 45782 | I17: 45693 | J17: 45752 | K17: 45721 | L17: 45721
A18: PIB de la Vivienda por ámbito económico
A19: Edificación | B19: 536.18 | C19: 570.93 | D19: 618.419 | E19: 694.439 | F19: 780.893 | G19: 847.362 | H19: 887.976 | I19: 755.777 | J19: 905.447 | K19: 1,006,007 | L19: 1,089,415
A20: Adquisición | B20: 62.954 | C20: 64.532 | D20: 68.488 | E20: 76.889 | F20: 70.468 | G20: 72.973 | H20: 75.832 | I20: 83.122 | J20: 94.403 | K20: 100.164 | L20: 112.348
A21: Uso | B21: 253.301 | C21: 265.858 | D21: 276.422 | E21: 287.636 | F21: 297.628 | G21: 308.635 | H21: 324.338 | I21: 337.411 | J21: 353.461 | K21: 373.848 | L21: 390.737
A22: Regulación y fomento | B22: 5.163 | C22: 6.51 | D22: 5.714 | E22: 6.109 | F22: 7.25 | G22: 6.783 | H22: 4.369 | I22: 4.214 | J22: 4.698 | K22: 4.748 | L22: 3.832
A23: Puestos de trabajo (Unidades)1/ | B23: 2,351,170 | C23: 2,329,886 | D23: 2,375,346 | E23: 2,441,326 | F23: 2,467,946 | G23: 2,524,605 | H23: 2,503,717 | I23: 2,340,085 | J23: 2,333,677 | K23: 2,193,530 | L23: 2,185,532
A25: https://www.inegi.org.mx/programas/viviendasat/2018/
A27: Producto Interno Bruto del sector vivienda, Base 2018
A28: Valores corrientes
A29: Millones de pesos y porcentaje
A30: (Mexico)

Sheet Construcción 2. (Mex)
A1: Banco de México
G2: índice de Volumen de la Industria de la Construcción por subsectores: es un indicador real (en cantidades/volumen, no en pesos) que muestra cómo cambia la producción de la construcción y de cada uno de sus subsectores en el tiempo. Se publica por Edificación (236), Obras de ingeniería civil (237) y Trabajos especializados para la construcción (238), y forma parte del Indicador Mensual de la Actividad Industrial (IMAI) del INEGI. Se expresa como un índice con base 2018=100 y se calcula con una metodología tipo Laspeyres (estructura fija del año base). inegi.org.mx Cómo se interpreta Nivel del índice (base 2018=100): si Edificación marca 110, significa que el volumen producido es 10% mayor que en 2018; si marca 90, es 10% menor. inegi.org.mx Variaciones publicadas: se difunden cambios mensuales desestacionalizados (para comparar contra el mes inmediato anterior quitando estacionalidad) y variaciones anuales (respecto al mismo mes del año previo). inegi.org.mx Cobertura y fuentes: el IMAI usa, entre otras, la Encuesta Nacional de Empresas Constructoras (ENEC) para derivar estos índices por subsector; por eso mide volumen real, no valores corrientes. inegi.org.mx Para qué sirve Seguimiento cíclico: permite ver si la construcción acelera o se enfría por tipo de obra (vivienda/edificación, carreteras/infraestructura, instalaciones y acabados). inegi.org.mx Planeación y análisis: es insumo para el PIB industrial, análisis sectoriales y decisiones de política y negocio (por ejemplo, detectar caídas en obra civil versus expansión en edificación).
A3: Producción
A4: Índice de volumen de la industria de la construcción por subsectores
A7: Título | B7: Índice de volumen de la producción industrial, Series originales, Construcción | C7: Índice de volumen de la industria de la construcción por subsectores, Total, Edificación | D7: Índice de volumen de la industria de la construcción por subsectores, Total, Construcción de obras de ingeniería civil u obra pesada
A8: Periodo disponible | B8: Ene 1993 - Ago 2017 | C8: Ene 1993 - Ago 2017 | D8: Ene 1993 - Ago 2017
A9: Periodicidad | B9: Mensual | C9: Mensual | D9: Mensual
A10: Cifra | B10: Indices | C10: Indices | D10: Indices
A11: Unidad | B11: Porcentajes | C11: Porcentajes | D11: Porcentajes
A12: Base | B12: (Base 2008=100) | C12: (Base 2008=100) | D12: (Base 2008=100)
A13: Aviso
A14: Tipo de información | B14: Tasa de crecimiento anual | C14: Tasa de crecimiento anual | D14: Tasa de crecimiento anual
A15: Fecha | B15: SR13813 | C15: SR13850 | D15: SR13851
A16: 36526 | B16: 0.28 | C16: -2.17 | D16: 28.1
A17: 36557 | B17: 4.37 | C17: 2.21 | D17: 32.29
A18: 36586 | B18: 1.4 | C18: -1.43 | D18: 26.9
A19: 36617 | B19: 3.35 | C19: 0.57 | D19: 27.4
A20: 36647 | B20: 5.71 | C20: 2.93 | D20: 27.99
A21: 36678 | B21: 1.04 | C21: -1.75 | D21: 22.41
A22: 36708 | B22: 1.36 | C22: -1.17 | D22: 19.66
A23: 36739 | B23: 3.87 | C23: 0.97 | D23: 22.02
A24: Sep 2000 | B24: -1.2 | C24: -3.58 | D24: 12.6
A25: 36800 | B25: -0.25 | C25: -2.99 | D25: 11.5
A26: 36831 | B26: -3.68 | C26: -6.76 | D26: 5.73
A27: 36861 | B27: -7.08 | C27: -8.83 | D27: -2.02
A28: 36892 | B28: -7.52 | C28: -9.36 | D28: -3.7
A29: 36923 | B29: -11.28 | C29: -12.45 | D29: -10.07
A30: 36951 | B30: -8.64 | C30: -8.66 | D30: -11.58
A31: 36982 | B31: -12.2 | C31: -12.28 | D31: -14.24
A32: 37012 | B32: -11.24 | C32: -10.99 | D32: -14.4
A33: 37043 | B33: -9.8 | C33: -10.19 | D33: -12.26
A34: 37073 | B34: -4.98 | C34: -6.07 | D34: -4.53
A35: 37104 | B35: -5.62 | C35: -6.91 | D35: -3.84
A36: Sep 2001 | B36: -5.57 | C36: -7.59 | D36: 0.25
A37: 37165 | B37: -7.4 | C37: -9.38 | D37: 1.73
A38: 37196 | B38: -5.45 | C38: -7.62 | D38: 6.96
A39: 37226 | B39: -2.98 | C39: -6.07 | D39: 16.82
A40: 37257 | B40: -5.54 | C40: -9.15 | D40: 17.59
A41: 37288 | B41: -3.16 | C41: -6.94 | D41: 26.57
A42: 37316 | B42: -8.59 | C42: -14.28 | D42: 25.01
A43: 37347 | B43: 8 | C43: 0.71 | D43: 53.05
A44: 37377 | B44: 1.67 | C44: -5.37 | D44: 44.84
A45: 37408 | B45: -1.76 | C45: -7.9 | D45: 40.15
A46: 37438 | B46: -4.78 | C46: -10.53 | D46: 34.24
A47: 37469 | B47: -5.41 | C47: -10.65 | D47: 31.98
A48: Sep 2002 | B48: -3.18 | C48: -8.56 | D48: 32.29
A49: 37530 | B49: 1.78 | C49: -4.2 | D49: 34.56
A50: 37561 | B50: 0.13 | C50: -5.56 | D50: 25.32
A51: 37591 | B51: -1.09 | C51: -5.48 | D51: 18.19
A52: 37622 | B52: 4.84 | C52: 1.92 | D52: 20.44
A53: 37653 | B53: 9.76 | C53: 7.19 | D53: 21.17
A54: 37681 | B54: 13.55 | C54: 11.26 | D54: 20.49
A55: 37712 | B55: 4.49 | C55: 3.75 | D55: 6.63
A56: 37742 | B56: 2.34 | C56: 3.38 | D56: -0.57
A57: 37773 | B57: 4.55 | C57: 5.47 | D57: 0.47
A58: 37803 | B58: 2.79 | C58: 5.27 | D58: -4.62
A59: 37834 | B59: -1.79 | C59: 0.2 | D59: -8.28
A60: Sep 2003 | B60: -4.06 | C60: -2.32 | D60: -10.27
A61: 37895 | B61: 1.39 | C61: 2.9 | D61: -5.37
A62: 37926 | B62: -2.8 | C62: -2.23 | D62: -5.97
A63: 37956 | B63: 2.35 | C63: 1.32 | D63: 1.76
A64: 37987 | B64: 9.39 | C64: 14.63 | D64: -6.51
A65: 38018 | B65: 0.77 | C65: 0.75 | D65: 0.09
A66: 38047 | B66: 11 | C66: 15.11 | D66: -4.46
A67: 38078 | B67: 8.92 | C67: 11.62 | D67: -2.86
A68: 38108 | B68: 8.67 | C68: 10.86 | D68: 1.72
A69: 38139 | B69: 8.89 | C69: 10.28 | D69: 1.38
A70: 38169 | B70: 4.87 | C70: 3.95 | D70: 5.47
A71: 38200 | B71: 2.05 | C71: -2.34 | D71: 16.79
A72: Sep 2004 | B72: 6.39 | C72: 2.96 | D72: 13.89
A73: 38261 | B73: 5.56 | C73: 2.75 | D73: 15.9
A74: 38292 | B74: 11.32 | C74: 10.79 | D74: 9.51
A75: 38322 | B75: 7.2 | C75: 5.73 | D75: 9.97
A76: 38353 | B76: 2.64 | C76: -2.39 | D76: 24.33
A77: 38384 | B77: 2.5 | C77: 0.25 | D77: 12.33
A78: 38412 | B78: -0.33 | C78: -2.2 | D78: 9.93
A79: 38443 | B79: 4.84 | C79: 1.69 | D79: 15.89
A80: 38473 | B80: 4.06 | C80: 0.72 | D80: 16.35
A81: 38504 | B81: 1.92 | C81: 0.59 | D81: 9.94
A82: 38534 | B82: 2.3 | C82: 1.6 | D82: 10.02
A83: 38565 | B83: 3.6 | C83: 3.96 | D83: 3.74
A84: Sep 2005 | B84: 2.2 | C84: 1.98 | D84: 8.24
A85: 38626 | B85: 3.74 | C85: 3.72 | D85: 6.59
A86: 38657 | B86: 6.84 | C86: 9.13 | D86: 3.81
A87: 38687 | B87: 8.69 | C87: 9.93 | D87: 9.58
A88: 38718 | B88: 2.75 | C88: 0.97 | D88: 8.46
A89: 38749 | B89: 5.16 | C89: 2.7 | D89: 15.44
A90: 38777 | B90: 9.92 | C90: 11.47 | D90: 5.05
A91: 38808 | B91: 5.56 | C91: 7.39 | D91: 3.76
A92: 38838 | B92: 9.41 | C92: 12.13 | D92: -0.32
A93: 38869 | B93: 7.97 | C93: 7.02 | D93: 13.72
A94: 38899 | B94: 10.9 | C94: 13.13 | D94: 3.34
A95: 38930 | B95: 12.5 | C95: 17.78 | D95: -1.81
A96: Sep 2006 | B96: 11.54 | C96: 17.48 | D96: -3.88
A97: 38991 | B97: 12.59 | C97: 17.39 | D97: 0.25
A98: 39022 | B98: 8.52 | C98: 12.05 | D98: 0.14
A99: 39052 | B99: 7.28 | C99: 11.23 | D99: -3.38
A100: 39083 | B100: 4.93 | C100: 5.79 | D100: 2.72
A101: 39114 | B101: 7.72 | C101: 9.29 | D101: 2.3
A102: 39142 | B102: 4.04 | C102: 3.67 | D102: 3.07
...

Sheet Salud1(ch)
A2: Ingresos SECTOR PRIVADO (MM$) / % del PIB / N° de Camas Hospitalarias
A3: Año | B3: INGRESOS SECTOR PRIVADO (MM$) | C3: gasto en salud % PIB | D3: camas hospitalarias
A4: 2014 | D4: 38171
A5: 2015 | D5: 38171
A6: 2016 | D6: 37552
A7: 2017 | D7: 38362
A8: 2018 | B8: 8445174 | C8: 9.1 | D8: 38959
A9: 2019 | B9: 8871520 | C9: 9.3 | D9: 38184
A10: 2020 | B10: 8487716 | C10: 9.7 | D10: 38899
A11: 2021 | B11: 10788356 | C11: 9.7 | D11: 38495
A12: 2022 | B12: 12929688 | C12: 10 | D12: 38167
A13: 2023 | B13: 13878518 | C13: 10.2 | D13: 37430
A14: 2024 | B14: 16894843 | C14: 10.5 | D14: 37397

Sheet Salud2(ch)
B1: Chile - Natalidad | E1: Año | F1: Nacimientos registrados | G1: Nota / fuente
A2: Fecha | B2: Tasa Natalidad | C2: Índice de Fecund. | E2: 2011 | F2: 247 358 nacidos vivos. Instituto Nacional de Estadísticas+2La Tercera+2 | G2: Anuario Estadísticas Vitales 2011.
A3: 2023 | B3: 0.00896 | C3: 1.17 | E3: 2015 | F3: 244 670 nacimientos. ADN Radio+2La Nación+2 | G3: Notificado por INE.
A4: 2022 | B4: 0.00967 | C4: 1.26 | E4: 2016 | F4: 231 749 nacimientos. La Nación+1 | G4: Según Anuario 2016.
A5: 2021 | B5: 0.00907 | C5: 1.18 | E5: 2017 | F5: 219 186 nacimientos. Instituto Nacional de Estadísticas | G5: Según Anuario 2017.
A6: 2020 | B6: 0.0101 | C6: 1.31 | E6: 2022 | F6: 189 303 nacimientos. Instituto Nacional de Estadísticas+1 | G6: Estadísticas Vitales 2022.
A7: 2019 | B7: 0.01094 | C7: 1.43 | E7: 2023 (provisionales) | F7: 174 067 nacimientos. Duna+2Instituto Nacional de Estadísticas+2 | G7: Datos provisionales.
A8: 2018 | B8: 0.0117 | C8: 1.54 | E8: 2024 (provisionales) | F8: 154 441 nacimientos. Cooperativa.cl+1 | G8: Boletín Demográfico Anual Provisional.
A9: 2017 | B9: 0.01176 | C9: 1.56
A10: 2016 | B10: 0.01269 | C10: 1.69
A11: 2015 | B11: 0.01315 | C11: 1.74
A12: 2014 | B12: 0.01347 | C12: 1.77
A13: 2013 | B13: 0.01362 | C13: 1.79
A14: 2012 | B14: 0.01378 | C14: 1.8
A15: 2011 | B15: 0.01402 | C15: 1.82

Sheet Salud3(ch)
A1: Chile
A2: 2017 [ Enero - Diciembre ] | E2: CONTROLES SEGÚN PROBLEMA DE SALUD
A3: TIPO DE CONTROL | B3: PROFESIONAL | C3: TOTAL | F3: POR EDAD | AN3: BENEFICIARIOS
F4: 0 - 4 | H4: 45905 | J4: 45944 | L4: 15 - 19 | N4: 20 - 24 | P4: 25 - 29 | R4: 30 - 34 | T4: 35 - 39 | V4: 40 - 44 | X4: 45 - 49 | Z4: 50 - 54 | AB4: 55 - 59 | AD4: 60 - 64 | AF4: 65 - 69 | AH4: 70 - 74 | AJ4: 75 - 79 | AL4: 80 y mas
C5: Ambos Sexos | D5: Hombres | E5: Mujeres | F5: Hombres | G5: Mujeres | H5: Hombres | I5: Mujeres | J5: Hombres | K5: Mujeres | L5: Hombres | M5: Mujeres | N5: Hombres | O5: Mujeres | P5: Hombres | Q5: Mujeres | R5: Hombres | S5: Mujeres | T5: Hombres | U5: Mujeres | V5: Hombres | W5: Mujeres | X5: Hombres | Y5: Mujeres | Z5: Hombres | AA5: Mujeres | AB5: Hombres | AC5: Mujeres | AD5: Hombres | AE5: Mujeres | AF5: Hombres | AG5: Mujeres | AH5: Hombres | AI5: Mujeres | AJ5: Hombres | AK5: Mujeres | AL5: Hombres | AM5: Mujeres
A6: Acumulado Pais
A7: DE SALUD CARDIOVASCULAR | B7: MÉDICO | C7: 2793983 | D7: 1006415 | E7: 1787568 | F7: 0 | G7: 0 | H7: 0 | I7: 0 | J7: 0 | K7: 1 | L7: 2219 | M7: 3486 | N7: 2855 | O7: 6490 | P7: 5543 | Q7: 12306 | R7: 9356 | S7: 20623 | T7: 17271 | U7: 36776 | V7: 31427 | W7: 66695 | X7: 54203 | Y7: 118671 | Z7: 93470 | AA7: 194462 | AB7: 120306 | AC7: 228535 | AD7: 138335 | AE7: 247051 | AF7: 149354 | AG7: 243055 | AH7: 148034 | AI7: 226020 | AJ7: 114488 | AK7: 176401 | AL7: 119526 | AM7: 206936 | AN7: 2757706
B8: ENFERMERA /O | C8: 1305552 | D8: 469444 | E8: 836108 | F8: 0 | G8: 0 | H8: 0 | I8: 0 | J8: 0 | K8: 0 | L8: 514 | M8: 726 | N8: 1048 | O8: 1866 | P8: 2050 | Q8: 3771 | R8: 3434 | S8: 6999 | T8: 6654 | U8: 13974 | V8: 12542 | W8: 26894 | X8: 22692 | Y8: 50016 | Z8: 39772 | AA8: 84126 | AB8: 52680 | AC8: 102913 | AD8: 61825 | AE8: 113664 | AF8: 71197 | AG8: 120082 | AH8: 74931 | AI8: 115611 | AJ8: 58263 | AK8: 91033 | AL8: 61854 | AM8: 104496 | AN8: 1289563
B9: NUTRICIONISTA | C9: 1082967 | D9: 366667 | E9: 716308 | F9: 0 | G9: 0 | H9: 0 | I9: 0 | J9: 0 | K9: 0 | L9: 1006 | M9: 1999 | N9: 1467 | O9: 3806 | P9: 2550 | Q9: 6473 | R9: 4079 | S9: 9942 | T9: 7357 | U9: 17007 | V9: 12623 | W9: 29629 | X9: 21490 | Y9: 51986 | Z9: 34801 | AA9: 82324 | AB9: 44202 | AC9: 94568 | AD9: 49314 | AE9: 98116 | AF9: 53606 | AG9: 96451 | AH9: 54157 | AI9: 88751 | AJ9: 40435 | AK9: 65781 | AL9: 39571 | AM9: 69479 | AN9: 1066882
B10: TÉCNICO PARAMÉDICO | C10: 112456 | D10: 42378 | E10: 70078 | F10: 0 | G10: 0 | H10: 0 | I10: 0 | J10: 0 | K10: 0 | L10: 197 | M10: 272 | N10: 228 | O10: 352 | P10: 339 | Q10: 576 | R10: 522 | S10: 1072 | T10: 993 | U10: 1753 | V10: 1519 | W10: 3207 | X10: 2472 | Y10: 5129 | Z10: 3940 | AA10: 7646 | AB10: 4807 | AC10: 9054 | AD10: 5343 | AE10: 9639 | AF10: 6142 | AG10: 9662 | AH10: 6249 | AI10: 8046 | AJ10: 4660 | AK10: 6036 | AL10: 4962 | AM10: 7639 | AN10: 109255
A11: DE TUBERCULOSIS | B11: MÉDICO | C11: 8984 | D11: 5120 | E11: 3864 | F11: 114 | G11: 95 | H11: 131 | I11: 135 | J11: 121 | K11: 131 | L11: 197 | M11: 167 | N11: 342 | O11: 267 | P11: 483 | Q11: 333 | R11: 480 | S11: 297 | T11: 346 | U11: 253 | V11: 373 | W11: 227 | X11: 387 | Y11: 223 | Z11: 469 | AA11: 221 | AB11: 434 | AC11: 300 | AD11: 325 | AE11: 275 | AF11: 246 | AG11: 284 | AH11: 212 | AI11: 273 | AJ11: 246 | AK11: 150 | AL11: 214 | AM11: 233 | AN11: 8626
B12: ENFERMERA /O | C12: 6742 | D12: 3793 | E12: 2949 | F12: 136 | G12: 109 | H12: 93 | I12: 97 | J12: 159 | K12: 129 | L12: 147 | M12: 125 | N12: 285 | O12: 302 | P12: 342 | Q12: 244 | R12: 260 | S12: 246 | T12: 230 | U12: 141 | V12: 236 | W12: 184 | X12: 290 | Y12: 175 | Z12: 272 | AA12: 143 | AB12: 282 | AC12: 176 | AD12: 298 | AE12: 191 | AF12: 209 | AG12: 175 | AH12: 197 | AI12: 220 | AJ12: 144 | AK12: 134 | AL12: 213 | AM12: 158 | AN12: 6419
A13: SEGUIMIENTO AUTOVALENTE CON RIESGO | B13: MÉDICO | C13: 1731 | D13: 641 | E13: 1090 | F13: 0 | G13: 0 | H13: 0 | I13: 0 | J13: 0 | K13: 0 | L13: 0 | M13: 0 | N13: 0 | O13: 0 | P13: 0 | Q13: 0 | R13: 0 | S13: 0 | T13: 0 | U13: 0 | V13: 0 | W13: 0 | X13: 0 | Y13: 0 | Z13: 0 | AA13: 0 | AB13: 0 | AC13: 0 | AD13: 0 | AE13: 0 | AF13: 153 | AG13: 288 | AH13: 197 | AI13: 270 | AJ13: 148 | AK13: 259 | AL13: 143 | AM13: 273 | AN13: 1678
B14: ENFERMERA /O | C14: 23666 | D14: 8489 | E14: 15177 | F14: 0 | G14: 0 | H14: 0 | I14: 0 | J14: 0 | K14: 0 | L14: 0 | M14: 0 | N14: 0 | O14: 0 | P14: 0 | Q14: 0 | R14: 0 | S14: 0 | T14: 0 | U14: 0 | V14: 0 | W14: 0 | X14: 0 | Y14: 0 | Z14: 0 | AA14: 0 | AB14: 0 | AC14: 0 | AD14: 0 | AE14: 0 | AF14: 2154 | AG14: 4151 | AH14: 2599 | AI14: 4591 | AJ14: 2091 | AK14: 3443 | AL14: 1642 | AM14: 2981 | AN14: 23382
A15: SEGUIMIENTO RIESGO DEPENDENCIA | B15: MÉDICO | C15: 778 | D15: 279 | E15: 499 | F15: 0 | G15: 0 | H15: 0 | I15: 0 | J15: 0 | K15: 0 | L15: 0 | M15: 0 | N15: 0 | O15: 0 | P15: 0 | Q15: 0 | R15: 0 | S15: 0 | T15: 0 | U15: 0 | V15: 0 | W15: 0 | X15: 0 | Y15: 0 | Z15: 0 | AA15: 0 | AB15: 0 | AC15: 0 | AD15: 0 | AE15: 0 | AF15: 48 | AG15: 80 | AH15: 52 | AI15: 93 | AJ15: 58 | AK15: 111 | AL15: 121 | AM15: 215 | AN15: 774
B16: ENFERMERA /O | C16: 14077 | D16: 4680 | E16: 9397 | F16: 0 | G16: 0 | H16: 0 | I16: 0 | J16: 0 | K16: 0 | L16: 0 | M16: 0 | N16: 0 | O16: 0 | P16: 0 | Q16: 0 | R16: 0 | S16: 0 | T16: 0 | U16: 0 | V16: 0 | W16: 0 | X16: 0 | Y16: 0 | Z16: 0 | AA16: 0 | AB16: 0 | AC16: 0 | AD16: 0 | AE16: 0 | AF16: 555 | AG16: 1128 | AH16: 971 | AI16: 1736 | AJ16: 1111 | AK16: 2308 | AL16: 2038 | AM16: 4217 | AN16: 13840
A17: DE INFECCIÓN TRANSMISIÓN SEXUAL | B17: MÉDICO | C17: 4522 | D17: 1501 | E17: 3021 | F17: 34 | G17: 37 | H17: 40 | I17: 30 | J17: 24 | K17: 23 | L17: 72 | M17: 156 | N17: 178 | O17: 219 | P17: 94 | Q17: 182 | R17: 71 | S17: 155 | T17: 49 | U17: 127 | V17: 56 | W17: 150 | X17: 76 | Y17: 208 | Z17: 113 | AA17: 226 | AB17: 102 | AC17: 299 | AD17: 139 | AE17: 275 | AF17: 120 | AG17: 293 | AH17: 114 | AI17: 284 | AJ17: 114 | AK17: 180 | AL17: 105 | AM17: 177 | AN17: 4219
B18: ENFERMERA /O | C18: 616 | D18: 282 | E18: 334 | F18: 16 | G18: 8 | H18: 10 | I18: 7 | J18: 0 | K18: 1 | L18: 7 | M18: 13 | N18: 21 | O18: 16 | P18: 15 | Q18: 17 | R18: 9 | S18: 17 | T18: 11 | U18: 12 | V18: 5 | W18: 8 | X18: 12 | Y18: 17 | Z18: 18 | AA18: 25 | AB18: 23 | AC18: 31 | AD18: 17 | AE18: 26 | AF18: 28 | AG18: 29 | AH18: 27 | AI18: 42 | AJ18: 31 | AK18: 25 | AL18: 32 | AM18: 40 | AN18: 542
B19: MATRONA /ÓN | C19: 7057 | D19: 1905 | E19: 5152 | F19: 10 | G19: 8 | H19: 3 | I19: 13 | J19: 8 | K19: 36 | L19: 254 | M19: 709 | N19: 429 | O19: 922 | P19: 303 | Q19: 736 | R19: 152 | S19: 595 | T19: 130 | U19: 544 | V19: 109 | W19: 445 | X19: 95 | Y19: 318 | Z19: 115 | AA19: 226 | AB19: 98 | AC19: 180 | AD19: 50 | AE19: 129 | AF19: 55 | AG19: 86 | AH19: 32 | AI19: 85 | AJ19: 20 | AK19: 55 | AL19: 42 | AM19: 65 | AN19: 6731
A20: OTROS PROBLEMAS DE SALUD | B20: MÉDICO | C20: 640824 | D20: 176686 | E20: 464139 | F20: 6878 | G20: 5802 | H20: 5501 | I20: 4649 | J20: 5599 | K20: 4826 | L20: 4518 | M20: 7499 | N20: 3506 | O20: 9073 | P20: 3827 | Q20: 12640 | R20: 4105 | S20: 14314 | T20: 4773 | U20: 17634 | V20: 6079 | W20: 22940 | X20: 8806 | Y20: 31977 | Z20: 12617 | AA20: 44548 | AB20: 15921 | AC20: 52706 | AD20: 17778 | AE20: 54716 | AF20: 19533 | AG20: 53322 | AH20: 20193 | AI20: 48061 | AJ20: 17306 | AK20: 36449 | AL20: 19748 | AM20: 42985 | AN20: 627792
B21: ENFERMERA /O | C21: 85890 | D21: 31033 | E21: 54858 | F21: 1407 | G21: 1313 | H21: 747 | I21: 660 | J21: 508 | K21: 460 | L21: 454 | M21: 615 | N21: 379 | O21: 671 | P21: 431 | Q21: 955 | R21: 512 | S21: 1144 | T21: 551 | U21: 1660 | V21: 943 | W21: 2172 | X21: 1406 | Y21: 3407 | Z21: 2292 | AA21: 4759 | AB21: 2742 | AC21: 5459 | AD21: 3041 | AE21: 6294 | AF21: 3916 | AG21: 6977 | AH21: 4420 | AI21: 6789 | AJ21: 3598 | AK21: 5147 | AL21: 3689 | AM21: 6375 | AN21: 84606
B22: MATRONA /ÓN | C22: 14220 | D22: 2131 | E22: 12089 | F22: 693 | G22: 729 | H22: 61 | I22: 129 | J22: 78 | K22: 179 | L22: 40 | M22: 659 | N22: 65 | O22: 784 | P22: 76 | Q22: 894 | R22: 47 | S22: 790 | T22: 59 | U22: 700 | V22: 35 | W22: 916 | X22: 107 | Y22: 900 | Z22: 201 | AA22: 1131 | AB22: 208 | AC22: 1156 | AD22: 49 | AE22: 1047 | AF22: 179 | AG22: 823 | AH22: 85 | AI22: 695 | AJ22: 105 | AK22: 307 | AL22: 42 | AM22: 250 | AN22: 14043
B23: NUTRICIONISTA | C23: 152533 | D23: 54902 | E23: 97632 | F23: 28910 | G23: 28301 | H23: 6933 | I23: 7340 | J23: 2989 | K23: 3654 | L23: 1373 | M23: 5087 | N23: 875 | O23: 5337 | P23: 999 | Q23: 6201 | R23: 889 | S23: 5227 | T23: 865 | U23: 4479 | V23: 878 | W23: 4018 | X23: 1009 | Y23: 4401 | Z23: 1232 | AA23: 4873 | AB23: 1439 | AC23: 4474 | AD23: 1276 | AE23: 3782 | AF23: 1396 | AG23: 3439 | AH23: 1479 | AI23: 2862 | AJ23: 1100 | AK23: 1920 | AL23: 1261 | AM23: 2245 | AN23: 146638
B24: TÉCNICO PARAMÉDICO | C24: 60240 | D24: 25645 | E24: 34598 | F24: 1935 | G24: 1901 | H24: 1026 | I24: 1240 | J24: 1087 | K24: 1099 | L24: 798 | M24: 1126 | N24: 794 | O24: 1110 | P24: 1024 | Q24: 1586 | R24: 1012 | S24: 1771 | T24: 1129 | U24: 1737 | V24: 1331 | W24: 2144 | X24: 1596 | Y24: 2554 | Z24: 1915 | AA24: 2815 | AB24: 1881 | AC24: 2866 | AD24: 1876 | AE24: 2891 | AF24: 2124 | AG24: 2593 | AH24: 2113 | AI24: 2452 | AJ24: 1881 | AK24: 2148 | AL24: 2123 | AM24: 2565 | AN24: 58945
A25: NIÑOS CON NECESIDADES ESPECIALES | B25: MÉDICO | C25: 790 | D25: 428 | E25: 362 | F25: 320 | G25: 248 | H25: 54 | I25: 59 | J25: 28 | K25: 38 | L25: 21 | M25: 11 | N25: 5 | O25: 6 | P25: 0 | Q25: 0 | R25: 0 | S25: 0 | T25: 0 | U25: 18 | V25: 0 | W25: 0 | X25: 0 | Y25: 0 | Z25: 0 | AA25: 0 | AB25: 0 | AC25: 0 | AD25: 0 | AE25: 0 | AF25: 0 | AG25: 0 | AH25: 0 | AI25: 0 | AJ25: 0 | AK25: 0 | AL25: 0 | AM25: 0 | AN25: 757
B26: ENFERMERA /O | C26: 1860 | D26: 1001 | E26: 859 | F26: 802 | G26: 699 | H26: 134 | I26: 106 | J26: 36 | K26: 30 | L26: 22 | M26: 13 | N26: 7 | O26: 11 | P26: 0 | Q26: 0 | R26: 0 | S26: 0 | T26: 0 | U26: 18 | V26: 0 | W26: 0 | X26: 0 | Y26: 0 | Z26: 0 | AA26: 0 | AB26: 0 | AC26: 0 | AD26: 0 | AE26: 0 | AF26: 0 | AG26: 0 | AH26: 0 | AI26: 0 | AJ26: 0 | AK26: 0 | AL26: 0 | AM26: 0 | AN26: 1711
B27: MATRONA /ÓN | C27: 128 | D27: 54 | E27: 74 | F27: 38 | G27: 32 | H27: 3 | I27: 4 | J27: 8 | K27: 13 | L27: 5 | M27: 11 | N27: 0 | O27: 14 | P27: 0 | Q27: 0 | R27: 0 | S27: 0 | T27: 0 | U27: 18 | V27: 0 | W27: 0 | X27: 0 | Y27: 0 | Z27: 1 | AA27: 0 | AB27: 0 | AC27: 0 | AD27: 0 | AE27: 0 | AF27: 0 | AG27: 0 | AH27: 0 | AI27: 0 | AJ27: 0 | AK27: 0 | AL27: 0 | AM27: 0 | AN27: 121
B28: NUTRICIONISTA | C28: 1145 | D28: 562 | E28: 583 | F28: 432 | G28: 474 | H28: 81 | I28: 51 | J28: 25 | K28: 24 | L28: 22 | M28: 23 | N28: 2 | O28: 11 | P28: 0 | Q28: 0 | R28: 0 | S28: 0 | T28: 0 | U28: 18 | V28: 0 | W28: 0 | X28: 0 | Y28: 0 | Z28: 0 | AA28: 0 | AB28: 0 | AC28: 0 | AD28: 0 | AE28: 0 | AF28: 0 | AG28: 0 | AH28: 0 | AI28: 0 | AJ28: 0 | AK28: 0 | AL28: 0 | AM28: 0 | AN28: 1057
B29: TÉCNICO PARAMÉDICO | C29: 114 | D29: 64 | E29: 50 | F29: 21 | G29: 13 | H29: 15 | I29: 5 | J29: 16 | K29: 7 | L29: 6 | M29: 3 | N29: 6 | O29: 4 | P29: 0 | Q29: 0 | R29: 0 | S29: 0 | T29: 0 | U29: 18 | V29: 0 | W29: 0 | X29: 0 | Y29: 0 | Z29: 0 | AA29: 0 | AB29: 0 | AC29: 0 | AD29: 0 | AE29: 0 | AF29: 0 | AG29: 0 | AH29: 0 | AI29: 0 | AJ29: 0 | AK29: 0 | AL29: 0 | AM29: 0 | AN29: 91
A30: Servicio: Arica
A31: DE SALUD CARDIOVASCULAR | B31: MÉDICO | C31: 17290 | D31: 6361 | E31: 10929 | F31: 0 | G31: 0 | H31: 0 | I31: 0 | J31: 0 | K31: 0 | L31: 5 | M31: 11 | N31: 21 | O31: 24 | P31: 37 | Q31: 44 | R31: 39 | S31: 76 | T31: 85 | U31: 161 | V31: 122 | W31: 308 | X31: 261 | Y31: 507 | Z31: 451 | AA31: 1060 | AB31: 641 | AC31: 1249 | AD31: 841 | AE31: 1448 | AF31: 909 | AG31: 1653 | AH31: 1222 | AI31: 1727 | AJ31: 917 | AK31: 1255 | AL31: 810 | AM31: 1406 | AN31: 17288
B32: ENFERMERA /O | C32: 17428 | D32: 6887 | E32: 10541 | F32: 0 | G32: 0 | H32: 0 | I32: 0 | J32: 0 | K32: 0 | L32: 6 | M32: 4 | N32: 9 | O32: 30 | P32: 40 | Q32: 40 | R32: 46 | S32: 81 | T32: 84 | U32: 168 | V32: 182 | W32: 320 | X32: 319 | Y32: 527 | Z32: 530 | AA32: 1002 | AB32: 753 | AC32: 1247 | AD32: 925 | AE32: 1405 | AF32: 976 | AG32: 1559 | AH32: 1268 | AI32: 1499 | AJ32: 839 | AK32: 1172 | AL32: 910 | AM32: 1487 | AN32: 17425
B33: NUTRICIONISTA | C33: 9958 | D33: 3578 | E33: 6380 | F33: 0 | G33: 0 | H33: 0 | I33: 0 | J33: 0 | K33: 0 | L33: 4 | M33: 7 | N33: 8 | O33: 13 | P33: 19 | Q33: 26 | R33: 34 | S33: 48 | T33: 56 | U33: 101 | V33: 88 | W33: 211 | X33: 183 | Y33: 297 | Z33: 252 | AA33: 597 | AB33: 351 | AC33: 756 | AD33: 455 | AE33: 868 | AF33: 526 | AG33: 966 | AH33: 658 | AI33: 964 | AJ33: 474 | AK33: 698 | AL33: 470 | AM33: 828 | AN33: 9957
B34: TÉCNICO PARAMÉDICO | C34: 333 | D34: 149 | E34: 184 | F34: 0 | G34: 0 | H34: 0 | I34: 0 | J34: 0 | K34: 0 | L34: 0 | M34: 0 | N34: 0 | O34: 0 | P34: 4 | Q34: 3 | R34: 1 | S34: 3 | T34: 1 | U34: 5 | V34: 0 | W34: 6 | X34: 9 | Y34: 5 | Z34: 36 | AA34: 25 | AB34: 24 | AC34: 7 | AD34: 9 | AE34: 10 | AF34: 12 | AG34: 34 | AH34: 27 | AI34: 37 | AJ34: 14 | AK34: 18 | AL34: 12 | AM34: 31 | AN34: 327
A35: DE TUBERCULOSIS | B35: MÉDICO | C35: 289 | D35: 160 | E35: 129 | F35: 0 | G35: 0 | H35: 0 | I35: 0 | J35: 1 | K35: 0 | L35: 0 | M35: 4 | N35: 7 | O35: 13 | P35: 20 | Q35: 8 | R35: 11 | S35: 5 | T35: 6 | U35: 3 | V35: 19 | W35: 3 | X35: 11 | Y35: 8 | Z35: 13 | AA35: 15 | AB35: 16 | AC35: 7 | AD35: 21 | AE35: 2 | AF35: 1 | AG35: 25 | AH35: 9 | AI35: 26 | AJ35: 15 | AK35: 5 | AL35: 10 | AM35: 5 | AN35: 289
B36: ENFERMERA /O | C36: 151 | D36: 96 | E36: 55 | F36: 0 | G36: 0 | H36: 1 | I36: 1 | J36: 3 | K36: 0 | L36: 3 | M36: 4 | N36: 13 | O36: 11 | P36: 8 | Q36: 2 | R36: 9 | S36: 6 | T36: 0 | U36: 3 | V36: 13 | W36: 3 | X36: 4 | Y36: 2 | Z36: 4 | AA36: 4 | AB36: 19 | AC36: 3 | AD36: 3 | AE36: 0 | AF36: 0 | AG36: 2 | AH36: 9 | AI36: 12 | AJ36: 6 | AK36: 0 | AL36: 1 | AM36: 2 | AN36: 151
A37: SEGUIMIENTO AUTOVALENTE CON RIESGO | B37: MÉDICO | C37: 120 | D37: 46 | E37: 74 | F37: 0 | G37: 0 | H37: 0 | I37: 0 | J37: 0 | K37: 0 | L37: 0 | M37: 0 | N37: 0 | O37: 0 | P37: 0 | Q37: 0 | R37: 0 | S37: 0 | T37: 0 | U37: 0 | V37: 0 | W37: 0 | X37: 0 | Y37: 0 | Z37: 0 | AA37: 0 | AB37: 0 | AC37: 0 | AD37: 0 | AE37: 0 | AF37: 6 | AG37: 9 | AH37: 13 | AI37: 16 | AJ37: 12 | AK37: 24 | AL37: 15 | AM37: 25 | AN37: 120
B38: ENFERMERA /O | C38: 318 | D38: 99 | E38: 219 | F38: 0 | G38: 0 | H38: 0 | I38: 0 | J38: 0 | K38: 0 | L38: 0 | M38: 0 | N38: 0 | O38: 0 | P38: 0 | Q38: 0 | R38: 0 | S38: 0 | T38: 0 | U38: 0 | V38: 0 | W38: 0 | X38: 0 | Y38: 0 | Z38: 0 | AA38: 0 | AB38: 0 | AC38: 0 | AD38: 0 | AE38: 0 | AF38: 10 | AG38: 68 | AH38: 44 | AI38: 59 | AJ38: 30 | AK38: 69 | AL38: 15 | AM38: 23 | AN38: 317
A39: SEGUIMIENTO RIESGO DEPENDENCIA | B39: MÉDICO | C39: 108 | D39: 41 | E39: 67 | F39: 0 | G39: 0 | H39: 0 | I39: 0 | J39: 0 | K39: 0 | L39: 0 | M39: 0 | N39: 0 | O39: 0 | P39: 0 | Q39: 0 | R39: 0 | S39: 0 | T39: 0 | U39: 0 | V39: 0 | W39: 0 | X39: 0 | Y39: 0 | Z39: 0 | AA39: 0 | AB39: 0 | AC39: 0 | AD39: 0 | AE39: 0 | AF39: 5 | AG39: 10 | AH39: 9 | AI39: 14 | AJ39: 7 | AK39: 15 | AL39: 20 | AM39: 28 | AN39: 108
B40: ENFERMERA /O | C40: 229 | D40: 70 | E40: 159 | F40: 0 | G40: 0 | H40: 0 | I40: 0 | J40: 0 | K40: 0 | L40: 0 | M40: 0 | N40: 0 | O40: 0 | P40: 0 | Q40: 0 | R40: 0 | S40: 0 | T40: 0 | U40: 0 | V40: 0 | W40: 0 | X40: 0 | Y40: 0 | Z40: 0 | AA40: 0 | AB40: 0 | AC40: 0 | AD40: 0 | AE40: 0 | AF40: 8 | AG40: 16 | AH40: 15 | AI40: 40 | AJ40: 18 | AK40: 42 | AL40: 29 | AM40: 61 | AN40: 225
A41: DE INFECCIÓN TRANSMISIÓN SEXUAL | B41: MÉDICO | C41: 5 | D41: 2 | E41: 3 | F41: 0 | G41: 0 | H41: 0 | I41: 0 | J41: 0 | K41: 0 | L41: 0 | M41: 0 | N41: 0 | O41: 0 | P41: 0 | Q41: 0 | R41: 0 | S41: 1 | T41: 0 | U41: 0 | V41: 0 | W41: 0 | X41: 0 | Y41: 0 | Z41: 0 | AA41: 0 | AB41: 0 | AC41: 1 | AD41: 2 | AE41: 0 | AF41: 0 | AG41: 0 | AH41: 0 | AI41: 1 | AJ41: 0 | AK41: 0 | AL41: 0 | AM41: 0 | AN41: 5
B42: ENFERMERA /O | C42: 0 | D42: 0 | E42: 0 | F42: 0 | G42: 0 | H42: 0 | I42: 0 | J42: 0 | K42: 0 | L42: 0 | M42: 0 | N42: 0 | O42: 0 | P42: 0 | Q42: 0 | R42: 0 | S42: 0 | T42: 0 | U42: 0 | V42: 0 | W42: 0 | X42: 0 | Y42: 0 | Z42: 0 | AA42: 0 | AB42: 0 | AC42: 0 | AD42: 0 | AE42: 0 | AF42: 0 | AG42: 0 | AH42: 0 | AI42: 0 | AJ42: 0 | AK42: 0 | AL42: 0 | AM42: 0 | AN42: 0
B43: MATRONA /ÓN | C43: 1 | D43: 0 | E43: 1 | F43: 0 | G43: 0 | H43: 0 | I43: 0 | J43: 0 | K43: 0 | L43: 0 | M43: 0 | N43: 0 | O43: 0 | P43: 0 | Q43: 0 | R43: 0 | S43: 0 | T43: 0 | U43: 0 | V43: 0 | W43: 0 | X43: 0 | Y43: 1 | Z43: 0 | AA43: 0 | AB43: 0 | AC43: 0 | AD43: 0 | AE43: 0 | AF43: 0 | AG43: 0 | AH43: 0 | AI43: 0 | AJ43: 0 | AK43: 0 | AL43: 0 | AM43: 0 | AN43: 1
A44: OTROS PROBLEMAS DE SALUD | B44: MÉDICO | C44: 17259 | D44: 5070 | E44: 12189 | F44: 2 | G44: 10 | H44: 225 | I44: 284 | J44: 397 | K44: 369 | L44: 335 | M44: 418 | N44: 277 | O44: 374 | P44: 199 | Q44: 450 | R44: 219 | S44: 474 | T44: 173 | U44: 547 | V44: 146 | W44: 507 | X44: 189 | Y44: 753 | Z44: 304 | AA44: 1092 | AB44: 401 | AC44: 1290 | AD44: 533 | AE44: 1407 | AF44: 455 | AG44: 1270 | AH44: 490 | AI44: 1236 | AJ44: 381 | AK44: 806 | AL44: 344 | AM44: 902 | AN44: 17255
B45: ENFERMERA /O | C45: 3358 | D45: 1331 | E45: 2027 | F45: 0 | G45: 1 | H45: 76 | I45: 109 | J45: 163 | K45: 174 | L45: 154 | M45: 159 | N45: 107 | O45: 125 | P45: 73 | Q45: 128 | R45: 88 | S45: 152 | T45: 59 | U45: 136 | V45: 42 | W45: 72 | X45: 55 | Y45: 102 | Z45: 64 | AA45: 227 | AB45: 105 | AC45: 213 | AD45: 139 | AE45: 169 | AF45: 97 | AG45: 100 | AH45: 62 | AI45: 82 | AJ45: 38 | AK45: 48 | AL45: 9 | AM45: 30 | AN45: 3358
B46: MATRONA /ÓN | C46: 14 | D46: 4 | E46: 10 | F46: 2 | G46: 0 | H46: 0 | I46: 0 | J46: 0 | K46: 0 | L46: 0 | M46: 0 | N46: 0 | O46: 0 | P46: 0 | Q46: 1 | R46: 0 | S46: 1 | T46: 0 | U46: 1 | V46: 0 | W46: 1 | X46: 0 | Y46: 0 | Z46: 0 | AA46: 0 | AB46: 0 | AC46: 0 | AD46: 0 | AE46: 0 | AF46: 0 | AG46: 0 | AH46: 0 | AI46: 0 | AJ46: 1 | AK46: 2 | AL46: 1 | AM46: 4 | AN46: 13
B47: NUTRICIONISTA | C47: 8733 | D47: 3628 | E47: 5105 | F47: 2237 | G47: 2095 | H47: 460 | I47: 505 | J47: 274 | K47: 303 | L47: 108 | M47: 455 | N47: 36 | O47: 187 | P47: 40 | Q47: 199 | R47: 35 | S47: 170 | T47: 29 | U47: 139 | V47: 34 | W47: 165 | X47: 24 | Y47: 154 | Z47: 33 | AA47: 170 | AB47: 43 | AC47: 126 | AD47: 39 | AE47: 95 | AF47: 53 | AG47: 115 | AH47: 76 | AI47: 85 | AJ47: 52 | AK47: 54 | AL47: 55 | AM47: 88 | AN47: 8733
B48: TÉCNICO PARAMÉDICO | C48: 0 | D48: 0 | E48: 0 | F48: 0 | G48: 0 | H48: 0 | I48: 0 | J48: 0 | K48: 0 | L48: 0 | M48: 0 | N48: 0 | O48: 0 | P48: 0 | Q48: 0 | R48: 0 | S48: 0 | T48: 0 | U48: 0 | V48: 0 | W48: 0 | X48: 0 | Y48: 0 | Z48: 0 | AA48: 0 | AB48: 0 | AC48: 0 | AD48: 0 | AE48: 0 | AF48: 0 | AG48: 0 | AH48: 0 | AI48: 0 | AJ48: 0 | AK48: 0 | AL48: 0 | AM48: 0 | AN48: 0
A49: NIÑOS CON NECESIDADES ESPECIALES | B49: MÉDICO | C49: 51 | D49: 32 | E49: 19 | F49: 32 | G49: 19 | H49: 0 | I49: 0 | J49: 0 | K49: 0 | L49: 0 | M49: 0 | N49: 0 | O49: 0 | P49: 0 | Q49: 0 | R49: 0 | S49: 0 | T49: 0 | U49: 0 | V49: 0 | W49: 0 | X49: 0 | Y49: 0 | Z49: 0 | AA49: 0 | AB49: 0 | AC49: 0 | AD49: 0 | AE49: 0 | AF49: 0 | AG49: 0 | AH49: 0 | AI49: 0 | AJ49: 0 | AK49: 0 | AL49: 0 | AM49: 0 | AN49: 51
B50: ENFERMERA /O | C50: 138 | D50: 79 | E50: 59 | F50: 73 | G50: 55 | H50: 6 | I50: 4 | J50: 0 | K50: 0 | L50: 0 | M50: 0 | N50: 0 | O50: 0 | P50: 0 | Q50: 0 | R50: 0 | S50: 0 | T50: 0 | U50: 0 | V50: 0 | W50: 0 | X50: 0 | Y50: 0 | Z50: 0 | AA50: 0 | AB50: 0 | AC50: 0 | AD50: 0 | AE50: 0 | AF50: 0 | AG50: 0 | AH50: 0 | AI50: 0 | AJ50: 0 | AK50: 0 | AL50: 0 | AM50: 0 | AN50: 131
B51: MATRONA /ÓN | C51: 0 | D51: 0 | E51: 0 | F51: 0 | G51: 0 | H51: 0 | I51: 0 | J51: 0 | K51: 0 | L51: 0 | M51: 0 | N51: 0 | O51: 0 | P51: 0 | Q51: 0 | R51: 0 | S51: 0 | T51: 0 | U51: 0 | V51: 0 | W51: 0 | X51: 0 | Y51: 0 | Z51: 0 | AA51: 0 | AB51: 0 | AC51: 0 | AD51: 0 | AE51: 0 | AF51: 0 | AG51: 0 | AH51: 0 | AI51: 0 | AJ51: 0 | AK51: 0 | AL51: 0 | AM51: 0 | AN51: 0
B52: NUTRICIONISTA | C52: 35 | D52: 17 | E52: 18 | F52: 17 | G52: 18 | H52: 0 | I52: 0 | J52: 0 | K52: 0 | L52: 0 | M52: 0 | N52: 0 | O52: 0 | P52: 0 | Q52: 0 | R52: 0 | S52: 0 | T52: 0 | U52: 0 | V52: 0 | W52: 0 | X52: 0 | Y52: 0 | Z52: 0 | AA52: 0 | AB52: 0 | AC52: 0 | AD52: 0 | AE52: 0 | AF52: 0 | AG52: 0 | AH52: 0 | AI52: 0 | AJ52: 0 | AK52: 0 | AL52: 0 | AM52: 0 | AN52: 35
B53: TÉCNICO PARAMÉDICO | C53: 0 | D53: 0 | E53: 0 | F53: 0 | G53: 0 | H53: 0 | I53: 0 | J53: 0 | K53: 0 | L53: 0 | M53: 0 | N53: 0 | O53: 0 | P53: 0 | Q53: 0 | R53: 0 | S53: 0 | T53: 0 | U53: 0 | V53: 0 | W53: 0 | X53: 0 | Y53: 0 | Z53: 0 | AA53: 0 | AB53: 0 | AC53: 0 | AD53: 0 | AE53: 0 | AF53: 0 | AG53: 0 | AH53: 0 | AI53: 0 | AJ53: 0 | AK53: 0 | AL53: 0 | AM53: 0 | AN53: 0
A54: Servicio: Iquique
A55: DE SALUD CARDIOVASCULAR | B55: MÉDICO | C55: 56278 | D55: 20241 | E55: 36037 | F55: 0 | G55: 0 | H55: 0 | I55: 0 | J55: 0 | K55: 0 | L55: 37 | M55: 55 | N55: 46 | O55: 159 | P55: 103 | Q55: 254 | R55: 184 | S55: 400 | T55: 363 | U55: 774 | V55: 578 | W55: 1260 | X55: 970 | Y55: 2276 | Z55: 1808 | AA55: 3842 | AB55: 2590 | AC55: 4621 | AD55: 3196 | AE55: 5542 | AF55: 3243 | AG55: 5373 | AH55: 3000 | AI55: 4650 | AJ55: 1944 | AK55: 3147 | AL55: 2179 | AM55: 3684 | AN55: 55435
B56: ENFERMERA /O | C56: 15978 | D56: 6262 | E56: 9716 | F56: 0 | G56: 0 | H56: 0 | I56: 0 | J56: 0 | K56: 0 | L56: 8 | M56: 14 | N56: 11 | O56: 30 | P56: 34 | Q56: 64 | R56: 43 | S56: 124 | T56: 103 | U56: 220 | V56: 181 | W56: 336 | X56: 330 | Y56: 586 | Z56: 521 | AA56: 987 | AB56: 791 | AC56: 1179 | AD56: 839 | AE56: 1358 | AF56: 958 | AG56: 1405 | AH56: 986 | AI56: 1386 | AJ56: 653 | AK56: 1002 | AL56: 804 | AM56: 1025 | AN56: 15379
B57: NUTRICIONISTA | C57: 11824 | D57: 4455 | E57: 7369 | F57: 0 | G57: 0 | H57: 0 | I57: 0 | J57: 0 | K57: 0 | L57: 15 | M57: 10 | N57: 14 | O57: 35 | P57: 26 | Q57: 75 | R57: 71 | S57: 147 | T57: 136 | U57: 244 | V57: 209 | W57: 370 | X57: 308 | Y57: 621 | Z57: 423 | AA57: 838 | AB57: 546 | AC57: 1007 | AD57: 604 | AE57: 1067 | AF57: 613 | AG57: 920 | AH57: 589 | AI57: 815 | AJ57: 415 | AK57: 606 | AL57: 486 | AM57: 614 | AN57: 10334
B58: TÉCNICO PARAMÉDICO | C58: 101 | D58: 68 | E58: 33 | F58: 0 | G58: 0 | H58: 0 | I58: 0 | J58: 0 | K58: 0 | L58: 1 | M58: 0 | N58: 0 | O58: 0 | P58: 0 | Q58: 0 | R58: 0 | S58: 2 | T58: 4 | U58: 2 | V58: 0 | W58: 0 | X58: 5 | Y58: 0 | Z58: 0 | AA58: 1 | AB58: 0 | AC58: 1 | AD58: 3 | AE58: 7 | AF58: 15 | AG58: 0 | AH58: 9 | AI58: 5 | AJ58: 20 | AK58: 1 | AL58: 11 | AM58: 14 | AN58: 96
A59: DE TUBERCULOSIS | B59: MÉDICO | C59: 387 | D59: 196 | E59: 191 | F59: 0 | G59: 2 | H59: 0 | I59: 1 | J59: 6 | K59: 20 | L59: 17 | M59: 12 | N59: 14 | O59: 21 | P59: 13 | Q59: 18 | R59: 18 | S59: 22 | T59: 5 | U59: 20 | V59: 19 | W59: 19 | X59: 14 | Y59: 8 | Z59: 13 | AA59: 2 | AB59: 5 | AC59: 7 | AD59: 21 | AE59: 7 | AF59: 12 | AG59: 4 | AH59: 7 | AI59: 16 | AJ59: 18 | AK59: 2 | AL59: 14 | AM59: 10 | AN59: 353
B60: ENFERMERA /O | C60: 618 | D60: 347 | E60: 271 | F60: 3 | G60: 3 | H60: 0 | I60: 1 | J60: 17 | K60: 19 | L60: 9 | M60: 9 | N60: 33 | O60: 29 | P60: 31 | Q60: 32 | R60: 17 | S60: 26 | T60: 7 | U60: 28 | V60: 26 | W60: 42 | X60: 23 | Y60: 16 | Z60: 11 | AA60: 9 | AB60: 10 | AC60: 14 | AD60: 45 | AE60: 2 | AF60: 16 | AG60: 3 | AH60: 38 | AI60: 35 | AJ60: 14 | AK60: 1 | AL60: 47 | AM60: 2 | AN60: 571
A61: SEGUIMIENTO AUTOVALENTE CON RIESGO | B61: MÉDICO | C61: 54 | D61: 17 | E61: 37 | F61: 0 | G61: 0 | H61: 0 | I61: 0 | J61: 0 | K61: 0 | L61: 0 | M61: 0 | N61: 0 | O61: 0 | P61: 0 | Q61: 0 | R61: 0 | S61: 0 | T61: 0 | U61: 0 | V61: 0 | W61: 0 | X61: 0 | Y61: 0 | Z61: 0 | AA61: 0 | AB61: 0 | AC61: 0 | AD61: 0 | AE61: 0 | AF61: 4 | AG61: 10 | AH61: 6 | AI61: 8 | AJ61: 2 | AK61: 11 | AL61: 5 | AM61: 8 | AN61: 54
B62: ENFERMERA /O | C62: 976 | D62: 340 | E62: 636 | F62: 0 | G62: 0 | H62: 0 | I62: 0 | J62: 0 | K62: 0 | L62: 0 | M62: 0 | N62: 0 | O62: 0 | P62: 0 | Q62: 0 | R62: 0 | S62: 0 | T62: 0 | U62: 0 | V62: 0 | W62: 0 | X62: 0 | Y62: 0 | Z62: 0 | AA62: 0 | AB62: 0 | AC62: 0 | AD62: 0 | AE62: 0 | AF62: 78 | AG62: 155 | AH62: 108 | AI62: 190 | AJ62: 74 | AK62: 142 | AL62: 80 | AM62: 149 | AN62: 964
A63: SEGUIMIENTO RIESGO DEPENDENCIA | B63: MÉDICO | C63: 22 | D63: 6 | E63: 16 | F63: 0 | G63: 0 | H63: 0 | I63: 0 | J63: 0 | K63: 0 | L63: 0 | M63: 0 | N63: 0 | O63: 0 | P63: 0 | Q63: 0 | R63: 0 | S63: 0 | T63: 0 | U63: 0 | V63: 0 | W63: 0 | X63: 0 | Y63: 0 | Z63: 0 | AA63: 0 | AB63: 0 | AC63: 0 | AD63: 0 | AE63: 0 | AF63: 4 | AG63: 2 | AH63: 1 | AI63: 2 | AJ63: 1 | AK63: 4 | AL63: 0 | AM63: 8 | AN63: 22
B64: ENFERMERA /O | C64: 447 | D64: 163 | E64: 284 | F64: 0 | G64: 0 | H64: 0 | I64: 0 | J64: 0 | K64: 0 | L64: 0 | M64: 0 | N64: 0 | O64: 0 | P64: 0 | Q64: 0 | R64: 0 | S64: 0 | T64: 0 | U64: 0 | V64: 0 | W64: 0 | X64: 0 | Y64: 0 | Z64: 0 | AA64: 0 | AB64: 0 | AC64: 0 | AD64: 0 | AE64: 0 | AF64: 29 | AG64: 29 | AH64: 34 | AI64: 66 | AJ64: 49 | AK64: 57 | AL64: 51 | AM64: 132 | AN64: 443
A65: DE INFECCIÓN TRANSMISIÓN SEXUAL | B65: MÉDICO | C65: 93 | D65: 35 | E65: 58 | F65: 0 | G65: 0 | H65: 0 | I65: 0 | J65: 0 | K65: 0 | L65: 1 | M65: 2 | N65: 0 | O65: 2 | P65: 0 | Q65: 0 | R65: 0 | S65: 5 | T65: 0 | U65: 0 | V65: 0 | W65: 3 | X65: 3 | Y65: 6 | Z65: 2 | AA65: 2 | AB65: 8 | AC65: 10 | AD65: 7 | AE65: 9 | AF65: 5 | AG65: 9 | AH65: 4 | AI65: 7 | AJ65: 0 | AK65: 2 | AL65: 5 | AM65: 1 | AN65: 92
B66: ENFERMERA /O | C66: 58 | D66: 19 | E66: 39 | F66: 0 | G66: 0 | H66: 0 | I66: 0 | J66: 0 | K66: 1 | L66: 0 | M66: 0 | N66: 0 | O66: 2 | P66: 0 | Q66: 1 | R66: 0 | S66: 0 | T66: 0 | U66: 2 | V66: 0 | W66: 1 | X66: 0 | Y66: 0 | Z66: 0 | AA66: 0 | AB66: 4 | AC66: 6 | AD66: 4 | AE66: 9 | AF66: 4 | AG66: 6 | AH66: 3 | AI66: 4 | AJ66: 2 | AK66: 4 | AL66: 2 | AM66: 3 | AN66: 58
B67: MATRONA /ÓN | C67: 0 | D67: 0 | E67: 0 | F67: 0 | G67: 0 | H67: 0 | I67: 0 | J67: 0 | K67: 0 | L67: 0 | M67: 0 | N67: 0 | O67: 0 | P67: 0 | Q67: 0 | R67: 0 | S67: 0 | T67: 0 | U67: 0 | V67: 0 | W67: 0 | X67: 0 | Y67: 0 | Z67: 0 | AA67: 0 | AB67: 0 | AC67: 0 | AD67: 0 | AE67: 0 | AF67: 0 | AG67: 0 | AH67: 0 | AI67: 0 | AJ67: 0 | AK67: 0 | AL67: 0 | AM67: 0 | AN67: 0
A68: OTROS PROBLEMAS DE SALUD | B68: MÉDICO | C68: 22600 | D68: 5319 | E68: 17281 | F68: 90 | G68: 93 | H68: 88 | I68: 88 | J68: 72 | K68: 91 | L68: 71 | M68: 164 | N68: 52 | O68: 267 | P68: 92 | Q68: 398 | R68: 114 | S68: 434 | T68: 100 | U68: 470 | V68: 171 | W68: 586 | X68: 160 | Y68: 847 | Z68: 257 | AA68: 1251 | AB68: 499 | AC68: 1950 | AD68: 663 | AE68: 2453 | AF68: 776 | AG68: 2496 | AH68: 732 | AI68: 2188 | AJ68: 598 | AK68: 1615 | AL68: 784 | AM68: 1890 | AN68: 20606
B69: ENFERMERA /O | C69: 2816 | D69: 828 | E69: 1988 | F69: 182 | G69: 247 | H69: 21 | I69: 36 | J69: 0 | K69: 1 | L69: 6 | M69: 22 | N69: 3 | O69: 27 | P69: 9 | Q69: 57 | R69: 11 | S69: 62 | T69: 17 | U69: 98 | V69: 20 | W69: 76 | X69: 41 | Y69: 125 | Z69: 54 | AA69: 186 | AB69: 82 | AC69: 220 | AD69: 63 | AE69: 186 | AF69: 83 | AG69: 203 | AH69: 90 | AI69: 181 | AJ69: 68 | AK69: 123 | AL69: 78 | AM69: 138 | AN69: 2425
B70: MATRONA /ÓN | C70: 673 | D70: 189 | E70: 484 | F70: 173 | G70: 288 | H70: 0 | I70: 0 | J70: 0 | K70: 2 | L70: 0 | M70: 31 | N70: 0 | O70: 33 | P70: 0 | Q70: 23 | R70: 0 | S70: 28 | T70: 0 | U70: 13 | V70: 0 | W70: 11 | X70: 0 | Y70: 11 | Z70: 0 | AA70: 7 | AB70: 0 | AC70: 3 | AD70: 0 | AE70: 2 | AF70: 1 | AG70: 2 | AH70: 0 | AI70: 1 | AJ70: 4 | AK70: 1 | AL70: 11 | AM70: 28 | AN70: 591
B71: NUTRICIONISTA | C71: 5724 | D71: 2405 | E71: 3319 | F71: 1595 | G71: 1625 | H71: 266 | I71: 255 | J71: 30 | K71: 35 | L71: 32 | M71: 77 | N71: 16 | O71: 86 | P71: 23 | Q71: 127 | R71: 14 | S71: 106 | T71: 21 | U71: 111 | V71: 33 | W71: 97 | X71: 44 | Y71: 88 | Z71: 42 | AA71: 109 | AB71: 54 | AC71: 103 | AD71: 36 | AE71: 105 | AF71: 42 | AG71: 87 | AH71: 57 | AI71: 107 | AJ71: 48 | AK71: 82 | AL71: 52 | AM71: 119 | AN71: 4936
B72: TÉCNICO PARAMÉDICO | C72: 2106 | D72: 968 | E72: 1138 | F72: 38 | G72: 52 | H72: 36 | I72: 55 | J72: 30 | K72: 47 | L72: 35 | M72: 28 | N72: 30 | O72: 26 | P72: 41 | Q72: 66 | R72: 59 | S72: 138 | T72: 60 | U72: 55 | V72: 69 | W72: 56 | X72: 82 | Y72: 79 | Z72: 60 | AA72: 67 | AB72: 58 | AC72: 65 | AD72: 82 | AE72: 57 | AF72: 55 | AG72: 84 | AH72: 89 | AI72: 92 | AJ72: 82 | AK72: 52 | AL72: 62 | AM72: 119 | AN72: 1897
A73: NIÑOS CON NECESIDADES ESPECIALES | B73: MÉDICO | C73: 7 | D73: 6 | E73: 1 | F73: 6 | G73: 1 | H73: 0 | I73: 0 | J73: 0 | K73: 0 | L73: 0 | M73: 0 | N73: 0 | O73: 0 | P73: 0 | Q73: 0 | R73: 0 | S73: 0 | T73: 0 | U73: 0 | V73: 0 | W73: 0 | X73: 0 | Y73: 0 | Z73: 0 | AA73: 0 | AB73: 0 | AC73: 0 | AD73: 0 | AE73: 0 | AF73: 0 | AG73: 0 | AH73: 0 | AI73: 0 | AJ73: 0 | AK73: 0 | AL73: 0 | AM73: 0 | AN73: 7
B74: ENFERMERA /O | C74: 90 | D74: 45 | E74: 45 | F74: 43 | G74: 43 | H74: 1 | I74: 2 | J74: 0 | K74: 0 | L74: 1 | M74: 0 | N74: 0 | O74: 0 | P74: 0 | Q74: 0 | R74: 0 | S74: 0 | T74: 0 | U74: 0 | V74: 0 | W74: 0 | X74: 0 | Y74: 0 | Z74: 0 | AA74: 0 | AB74: 0 | AC74: 0 | AD74: 0 | AE74: 0 | AF74: 0 | AG74: 0 | AH74: 0 | AI74: 0 | AJ74: 0 | AK74: 0 | AL74: 0 | AM74: 0 | AN74: 72
B75: MATRONA /ÓN | C75: 33 | D75: 18 | E75: 15 | F75: 17 | G75: 13 | H75: 1 | I75: 2 | J75: 0 | K75: 0 | L75: 0 | M75: 0 | N75: 0 | O75: 0 | P75: 0 | Q75: 0 | R75: 0 | S75: 0 | T75: 0 | U75: 0 | V75: 0 | W75: 0 | X75: 0 | Y75: 0 | Z75: 0 | AA75: 0 | AB75: 0 | AC75: 0 | AD75: 0 | AE75: 0 | AF75: 0 | AG75: 0 | AH75: 0 | AI75: 0 | AJ75: 0 | AK75: 0 | AL75: 0 | AM75: 0 | AN75: 33
B76: NUTRICIONISTA | C76: 70 | D76: 33 | E76: 37 | F76: 23 | G76: 28 | H76: 7 | I76: 3 | J76: 1 | K76: 1 | L76: 2 | M76: 4 | N76: 0 | O76: 1 | P76: 0 | Q76: 0 | R76: 0 | S76: 0 | T76: 0 | U76: 0 | V76: 0 | W76: 0 | X76: 0 | Y76: 0 | Z76: 0 | AA76: 0 | AB76: 0 | AC76: 0 | AD76: 0 | AE76: 0 | AF76: 0 | AG76: 0 | AH76: 0 | AI76: 0 | AJ76: 0 | AK76: 0 | AL76: 0 | AM76: 0 | AN76: 48
B77: TÉCNICO PARAMÉDICO | C77: 0 | D77: 0 | E77: 0 | F77: 0 | G77: 0 | H77: 0 | I77: 0 | J77: 0 | K77: 0 | L77: 0 | M77: 0 | N77: 0 | O77: 0 | P77: 0 | Q77: 0 | R77: 0 | S77: 0 | T77: 0 | U77: 0 | V77: 0 | W77: 0 | X77: 0 | Y77: 0 | Z77: 0 | AA77: 0 | AB77: 0 | AC77: 0 | AD77: 0 | AE77: 0 | AF77: 0 | AG77: 0 | AH77: 0 | AI77: 0 | AJ77: 0 | AK77: 0 | AL77: 0 | AM77: 0 | AN77: 0
A78: Servicio: Antofagasta
A79: DE SALUD CARDIOVASCULAR | B79: MÉDICO | C79: 80461 | D79: 26550 | E79: 53911 | F79: 0 | G79: 0 | H79: 0 | I79: 0 | J79: 0 | K79: 0 | L79: 44 | M79: 109 | N79: 38 | O79: 144 | P79: 94 | Q79: 265 | R79: 152 | S79: 482 | T79: 351 | U79: 897 | V79: 647 | W79: 1742 | X79: 1205 | Y79: 3135 | Z79: 2501 | AA79: 5668 | AB79: 3301 | AC79: 7457 | AD79: 4233 | AE79: 8071 | AF79: 4178 | AG79: 7559 | AH79: 3848 | AI79: 6837 | AJ79: 2978 | AK79: 5415 | AL79: 2980 | AM79: 6130 | AN79: 74086
B80: ENFERMERA /O | C80: 20991 | D80: 7089 | E80: 13902 | F80: 0 | G80: 0 | H80: 0 | I80: 0 | J80: 0 | K80: 0 | L80: 10 | M80: 19 | N80: 3 | O80: 16 | P80: 29 | Q80: 53 | R80: 42 | S80: 111 | T80: 87 | U80: 211 | V80: 155 | W80: 410 | X80: 300 | Y80: 878 | Z80: 611 | AA80: 1393 | AB80: 811 | AC80: 1745 | AD80: 1064 | AE80: 1911 | AF80: 1149 | AG80: 2088 | AH80: 1070 | AI80: 2061 | AJ80: 923 | AK80: 1497 | AL80: 835 | AM80: 1509 | AN80: 20270
B81: NUTRICIONISTA | C81: 17669 | D81: 5366 | E81: 12303 | F81: 0 | G81: 0 | H81: 0 | I81: 0 | J81: 0 | K81: 0 | L81: 16 | M81: 34 | N81: 19 | O81: 79 | P81: 32 | Q81: 122 | R81: 43 | S81: 223 | T81: 111 | U81: 354 | V81: 179 | W81: 564 | X81: 284 | Y81: 888 | Z81: 546 | AA81: 1593 | AB81: 701 | AC81: 1644 | AD81: 852 | AE81: 1709 | AF81: 854 | AG81: 1671 | AH81: 750 | AI81: 1461 | AJ81: 494 | AK81: 1013 | AL81: 485 | AM81: 948 | AN81: 16716
B82: TÉCNICO PARAMÉDICO | C82: 34 | D82: 13 | E82: 21 | F82: 0 | G82: 0 | H82: 0 | I82: 0 | J82: 0 | K82: 0 | L82: 0 | M82: 0 | N82: 0 | O82: 0 | P82: 0 | Q82: 0 | R82: 0 | S82: 1 | T82: 0 | U82: 0 | V82: 1 | W82: 1 | X82: 0 | Y82: 0 | Z82: 0 | AA82: 1 | AB82: 0 | AC82: 2 | AD82: 2 | AE82: 1 | AF82: 1 | AG82: 3 | AH82: 3 | AI82: 5 | AJ82: 2 | AK82: 5 | AL82: 4 | AM82: 2 | AN82: 34
A83: DE TUBERCULOSIS | B83: MÉDICO | C83: 801 | D83: 445 | E83: 356 | F83: 23 | G83: 5 | H83: 13 | I83: 24 | J83: 11 | K83: 12 | L83: 26 | M83: 16 | N83: 59 | O83: 28 | P83: 57 | Q83: 31 | R83: 43 | S83: 30 | T83: 35 | U83: 25 | V83: 37 | W83: 27 | X83: 29 | Y83: 5 | Z83: 30 | AA83: 10 | AB83: 16 | AC83: 10 | AD83: 20 | AE83: 28 | AF83: 13 | AG83: 32 | AH83: 11 | AI83: 50 | AJ83: 16 | AK83: 10 | AL83: 6 | AM83: 13 | AN83: 755
B84: ENFERMERA /O | C84: 357 | D84: 205 | E84: 152 | F84: 2 | G84: 4 | H84: 0 | I84: 1 | J84: 0 | K84: 2 | L84: 9 | M84: 3 | N84: 17 | O84: 7 | P84: 17 | Q84: 10 | R84: 14 | S84: 13 | T84: 9 | U84: 4 | V84: 5 | W84: 7 | X84: 15 | Y84: 2 | Z84: 14 | AA84: 5 | AB84: 5 | AC84: 7 | AD84: 5 | AE84: 3 | AF84: 28 | AG84: 24 | AH84: 32 | AI84: 32 | AJ84: 22 | AK84: 14 | AL84: 11 | AM84: 14 | AN84: 353
A85: SEGUIMIENTO AUTOVALENTE CON RIESGO | B85: MÉDICO | C85: 15 | D85: 5 | E85: 10 | F85: 0 | G85: 0 | H85: 0 | I85: 0 | J85: 0 | K85: 0 | L85: 0 | M85: 0 | N85: 0 | O85: 0 | P85: 0 | Q85: 0 | R85: 0 | S85: 0 | T85: 0 | U85: 0 | V85: 0 | W85: 0 | X85: 0 | Y85: 0 | Z85: 0 | AA85: 0 | AB85: 0 | AC85: 0 | AD85: 0 | AE85: 0 | AF85: 0 | AG85: 1 | AH85: 0 | AI85: 0 | AJ85: 0 | AK85: 3 | AL85: 5 | AM85: 6 | AN85: 12
B86: ENFERMERA /O | C86: 1737 | D86: 620 | E86: 1117 | F86: 0 | G86: 0 | H86: 0 | I86: 0 | J86: 0 | K86: 0 | L86: 0 | M86: 0 | N86: 0 | O86: 0 | P86: 0 | Q86: 0 | R86: 0 | S86: 0 | T86: 0 | U86: 0 | V86: 0 | W86: 0 | X86: 0 | Y86: 0 | Z86: 0 | AA86: 0 | AB86: 0 | AC86: 0 | AD86: 0 | AE86: 0 | AF86: 147 | AG86: 292 | AH86: 191 | AI86: 333 | AJ86: 155 | AK86: 253 | AL86: 127 | AM86: 239 | AN86: 1747
A87: SEGUIMIENTO RIESGO DEPENDENCIA | B87: MÉDICO | C87: 0 | D87: 0 | E87: 0 | F87: 0 | G87: 0 | H87: 0 | I87: 0 | J87: 0 | K87: 0 | L87: 0 | M87: 0 | N87: 0 | O87: 0 | P87: 0 | Q87: 0 | R87: 0 | S87: 0 | T87: 0 | U87: 0 | V87: 0 | W87: 0 | X87: 0 | Y87: 0 | Z87: 0 | AA87: 0 | AB87: 0 | AC87: 0 | AD87: 0 | AE87: 0 | AF87: 0 | AG87: 0 | AH87: 0 | AI87: 0 | AJ87: 0 | AK87: 0 | AL87: 0 | AM87: 0 | AN87: 0
B88: ENFERMERA /O | C88: 1224 | D88: 262 | E88: 962 | F88: 0 | G88: 0 | H88: 0 | I88: 0 | J88: 0 | K88: 0 | L88: 0 | M88: 0 | N88: 0 | O88: 0 | P88: 0 | Q88: 0 | R88: 0 | S88: 0 | T88: 0 | U88: 0 | V88: 0 | W88: 0 | X88: 0 | Y88: 0 | Z88: 0 | AA88: 0 | AB88: 0 | AC88: 0 | AD88: 0 | AE88: 0 | AF88: 32 | AG88: 95 | AH88: 47 | AI88: 149 | AJ88: 51 | AK88: 388 | AL88: 132 | AM88: 330 | AN88: 1150
A89: DE INFECCIÓN TRANSMISIÓN SEXUAL | B89: MÉDICO | C89: 16 | D89: 8 | E89: 8 | F89: 0 | G89: 0 | H89: 0 | I89: 1 | J89: 0 | K89: 0 | L89: 1 | M89: 1 | N89: 1 | O89: 2 | P89: 3 | Q89: 2 | R89: 1 | S89: 1 | T89: 0 | U89: 0 | V89: 0 | W89: 0 | X89: 0 | Y89: 0 | Z89: 0 | AA89: 0 | AB89: 1 | AC89: 0 | AD89: 0 | AE89: 0 | AF89: 0 | AG89: 1 | AH89: 0 | AI89: 0 | AJ89: 1 | AK89: 0 | AL89: 0 | AM89: 0 | AN89: 13
B90: ENFERMERA /O | C90: 6 | D90: 0 | E90: 6 | F90: 0 | G90: 0 | H90: 0 | I90: 0 | J90: 0 | K90: 0 | L90: 0 | M90: 2 | N90: 0 | O90: 3 | P90: 0 | Q90: 0 | R90: 0 | S90: 0 | T90: 0 | U90: 1 | V90: 0 | W90: 0 | X90: 0 | Y90: 0 | Z90: 0 | AA90: 0 | AB90: 0 | AC90: 0 | AD90: 0 | AE90: 0 | AF90: 0 | AG90: 0 | AH90: 0 | AI90: 0 | AJ90: 0 | AK90: 0 | AL90: 0 | AM90: 0 | AN90: 6
B91: MATRONA /ÓN | C91: 402 | D91: 90 | E91: 312 | F91: 0 | G91: 0 | H91: 0 | I91: 0 | J91: 0 | K91: 1 | L91: 17 | M91: 67 | N91: 25 | O91: 57 | P91: 22 | Q91: 45 | R91: 7 | S91: 58 | T91: 2 | U91: 20 | V91: 7 | W91: 29 | X91: 2 | Y91: 14 | Z91: 2 | AA91: 5 | AB91: 4 | AC91: 0 | AD91: 1 | AE91: 8 | AF91: 1 | AG91: 1 | AH91: 0 | AI91: 6 | AJ91: 0 | AK91: 0 | AL91: 0 | AM91: 1 | AN91: 402
A92: OTROS PROBLEMAS DE SALUD | B92: MÉDICO | C92: 38489 | D92: 10305 | E92: 28184 | F92: 104 | G92: 55 | H92: 52 | I92: 60 | J92: 76 | K92: 96 | L92: 77 | M92: 199 | N92: 82 | O92: 303 | P92: 89 | Q92: 357 | R92: 108 | S92: 449 | T92: 159 | U92: 694 | V92: 175 | W92: 825 | X92: 452 | Y92: 1459 | Z92: 823 | AA92: 2325 | AB92: 1086 | AC92: 3055 | AD92: 1090 | AE92: 3666 | AF92: 1606 | AG92: 3671 | AH92: 1456 | AI92: 3935 | AJ92: 1412 | AK92: 2968 | AL92: 1458 | AM92: 4067 | AN92: 37023
B93: ENFERMERA /O | C93: 5474 | D93: 2349 | E93: 3125 | F93: 6 | G93: 7 | H93: 3 | I93: 3 | J93: 1 | K93: 1 | L93: 2 | M93: 14 | N93: 2 | O93: 18 | P93: 9 | Q93: 37 | R93: 11 | S93: 41 | T93: 17 | U93: 46 | V93: 18 | W93: 89 | X93: 184 | Y93: 170 | Z93: 348 | AA93: 249 | AB93: 382 | AC93: 290 | AD93: 156 | AE93: 386 | AF93: 434 | AG93: 404 | AH93: 298 | AI93: 713 | AJ93: 270 | AK93: 305 | AL93: 208 | AM93: 352 | AN93: 5347
B94: MATRONA /ÓN | C94: 1198 | D94: 673 | E94: 525 | F94: 20 | G94: 24 | H94: 1 | I94: 3 | J94: 0 | K94: 2 | L94: 0 | M94: 33 | N94: 4 | O94: 59 | P94: 1 | Q94: 53 | R94: 0 | S94: 61 | T94: 2 | U94: 9 | V94: 0 | W94: 38 | X94: 78 | Y94: 9 | Z94: 150 | AA94: 11 | AB94: 152 | AC94: 17 | AD94: 3 | AE94: 13 | AF94: 135 | AG94: 13 | AH94: 47 | AI94: 160 | AJ94: 72 | AK94: 12 | AL94: 8 | AM94: 8 | AN94: 1198
B95: NUTRICIONISTA | C95: 15532 | D95: 6006 | E95: 9526 | F95: 3778 | G95: 3569 | H95: 526 | I95: 589 | J95: 185 | K95: 245 | L95: 143 | M95: 538 | N95: 152 | O95: 616 | P95: 163 | Q95: 587 | R95: 143 | S95: 470 | T95: 102 | U95: 342 | V95: 56 | W95: 324 | X95: 79 | Y95: 293 | Z95: 83 | AA95: 359 | AB95: 122 | AC95: 371 | AD95: 71 | AE95: 327 | AF95: 111 | AG95: 326 | AH95: 105 | AI95: 214 | AJ95: 81 | AK95: 154 | AL95: 106 | AM95: 202 | AN95: 15165
B96: TÉCNICO PARAMÉDICO | C96: 1557 | D96: 999 | E96: 558 | F96: 31 | G96: 29 | H96: 35 | I96: 52 | J96: 10 | K96: 17 | L96: 21 | M96: 21 | N96: 19 | O96: 22 | P96: 23 | Q96: 28 | R96: 25 | S96: 31 | T96: 25 | U96: 26 | V96: 18 | W96: 20 | X96: 97 | Y96: 39 | Z96: 165 | AA96: 27 | AB96: 164 | AC96: 19 | AD96: 38 | AE96: 56 | AF96: 133 | AG96: 16 | AH96: 85 | AI96: 138 | AJ96: 47 | AK96: 4 | AL96: 63 | AM96: 13 | AN96: 1496
A97: NIÑOS CON NECESIDADES ESPECIALES | B97: MÉDICO | C97: 377 | D97: 189 | E97: 188 | F97: 127 | G97: 107 | H97: 33 | I97: 39 | J97: 17 | K97: 31 | L97: 12 | M97: 10 | N97: 0 | O97: 1 | P97: 0 | Q97: 0 | R97: 0 | S97: 0 | T97: 0 | U97: 0 | V97: 0 | W97: 0 | X97: 0 | Y97: 0 | Z97: 0 | AA97: 0 | AB97: 0 | AC97: 0 | AD97: 0 | AE97: 0 | AF97: 0 | AG97: 0 | AH97: 0 | AI97: 0 | AJ97: 0 | AK97: 0 | AL97: 0 | AM97: 0 | AN97: 371
B98: ENFERMERA /O | C98: 92 | D98: 64 | E98: 28 | F98: 55 | G98: 23 | H98: 5 | I98: 1 | J98: 0 | K98: 2 | L98: 2 | M98: 2 | N98: 2 | O98: 0 | P98: 0 | Q98: 0 | R98: 0 | S98: 0 | T98: 0 | U98: 0 | V98: 0 | W98: 0 | X98: 0 | Y98: 0 | Z98: 0 | AA98: 0 | AB98: 0 | AC98: 0 | AD98: 0 | AE98: 0 | AF98: 0 | AG98: 0 | AH98: 0 | AI98: 0 | AJ98: 0 | AK98: 0 | AL98: 0 | AM98: 0 | AN98: 87
B99: MATRONA /ÓN | C99: 3 | D99: 0 | E99: 3 | F99: 0 | G99: 3 | H99: 0 | I99: 0 | J99: 0 | K99: 0 | L99: 0 | M99: 0 | N99: 0 | O99: 0 | P99: 0 | Q99: 0 | R99: 0 | S99: 0 | T99: 0 | U99: 0 | V99: 0 | W99: 0 | X99: 0 | Y99: 0 | Z99: 0 | AA99: 0 | AB99: 0 | AC99: 0 | AD99: 0 | AE99: 0 | AF99: 0 | AG99: 0 | AH99: 0 | AI99: 0 | AJ99: 0 | AK99: 0 | AL99: 0 | AM99: 0 | AN99: 3
B100: NUTRICIONISTA | C100: 78 | D100: 40 | E100: 38 | F100: 34 | G100: 32 | H100: 2 | I100: 2 | J100: 2 | K100: 3 | L100: 1 | M100: 1 | N100: 1 | O100: 0 | P100: 0 | Q100: 0 | R100: 0 | S100: 0 | T100: 0 | U100: 0 | V100: 0 | W100: 0 | X100: 0 | Y100: 0 | Z100: 0 | AA100: 0 | AB100: 0 | AC100: 0 | AD100: 0 | AE100: 0 | AF100: 0 | AG100: 0 | AH100: 0 | AI100: 0 | AJ100: 0 | AK100: 0 | AL100: 0 | AM100: 0 | AN100: 66
...

Sheet Controles según problema de sal
A1: 2018 [ Enero - Diciembre ] | E1: CONTROLES SEGÚN PROBLEMA DE SALUD
A2: TIPO DE CONTROL | B2: PROFESIONAL | C2: TOTAL | F2: POR EDAD | AN2: BENEFICIARIOS
F3: 0 - 4 | H3: 45905 | J3: 45944 | L3: 15 - 19 | N3: 20 - 24 | P3: 25 - 29 | R3: 30 - 34 | T3: 35 - 39 | V3: 40 - 44 | X3: 45 - 49 | Z3: 50 - 54 | AB3: 55 - 59 | AD3: 60 - 64 | AF3: 65 - 69 | AH3: 70 - 74 | AJ3: 75 - 79 | AL3: 80 y mas
C4: Ambos Sexos | D4: Hombres | E4: Mujeres | F4: Hombres | G4: Mujeres | H4: Hombres | I4: Mujeres | J4: Hombres | K4: Mujeres | L4: Hombres | M4: Mujeres | N4: Hombres | O4: Mujeres | P4: Hombres | Q4: Mujeres | R4: Hombres | S4: Mujeres | T4: Hombres | U4: Mujeres | V4: Hombres | W4: Mujeres | X4: Hombres | Y4: Mujeres | Z4: Hombres | AA4: Mujeres | AB4: Hombres | AC4: Mujeres | AD4: Hombres | AE4: Mujeres | AF4: Hombres | AG4: Mujeres | AH4: Hombres | AI4: Mujeres | AJ4: Hombres | AK4: Mujeres | AL4: Hombres | AM4: Mujeres
A5: Acumulado Pais
A6: DE SALUD CARDIOVASCULAR | B6: MÉDICO | C6: 2900511 | D6: 1050710 | E6: 1849815 | F6: 0 | G6: 0 | H6: 0 | I6: 0 | J6: 0 | K6: 0 | L6: 1968 | M6: 3082 | N6: 2754 | O6: 6079 | P6: 5586 | Q6: 12319 | R6: 9340 | S6: 20733 | T6: 17184 | U6: 36752 | V6: 30585 | W6: 66181 | X6: 53624 | Y6: 116524 | Z6: 92911 | AA6: 194785 | AB6: 126974 | AC6: 239999 | AD6: 146278 | AE6: 256955 | AF6: 157480 | AG6: 253533 | AH6: 157647 | AI6: 238296 | AJ6: 122664 | AK6: 187835 | AL6: 126033 | AM6: 217273 | AN6: 2870098
B7: ENFERMERA /O | C7: 1322084 | D7: 478473 | E7: 843611 | F7: 0 | G7: 0 | H7: 0 | I7: 0 | J7: 0 | K7: 0 | L7: 490 | M7: 701 | N7: 980 | O7: 1592 | P7: 1926 | Q7: 3758 | R7: 3429 | S7: 6787 | T7: 6297 | U7: 13456 | V7: 11978 | W7: 26034 | X7: 21445 | Y7: 48279 | Z7: 38590 | AA7: 82504 | AB7: 53340 | AC7: 103725 | AD7: 63352 | AE7: 115049 | AF7: 74461 | AG7: 122516 | AH7: 77172 | AI7: 117861 | AJ7: 61285 | AK7: 93115 | AL7: 63728 | AM7: 108234 | AN7: 1309557
B8: NUTRICIONISTA | C8: 1111789 | D8: 379451 | E8: 732338 | F8: 0 | G8: 0 | H8: 0 | I8: 0 | J8: 0 | K8: 0 | L8: 834 | M8: 1682 | N8: 1288 | O8: 3385 | P8: 2388 | Q8: 6139 | R8: 3886 | S8: 9441 | T8: 6988 | U8: 16578 | V8: 11953 | W8: 28331 | X8: 20562 | Y8: 49780 | Z8: 34300 | AA8: 82024 | AB8: 45888 | AC8: 97679 | AD8: 52135 | AE8: 102073 | AF8: 56889 | AG8: 99888 | AH8: 57413 | AI8: 92312 | AJ8: 43529 | AK8: 69745 | AL8: 41396 | AM8: 73282 | AN8: 1099332
B9: TÉCNICO PARAMÉDICO | C9: 92806 | D9: 34235 | E9: 58571 | F9: 0 | G9: 0 | H9: 0 | I9: 0 | J9: 0 | K9: 0 | L9: 134 | M9: 167 | N9: 121 | O9: 263 | P9: 278 | Q9: 484 | R9: 380 | S9: 865 | T9: 670 | U9: 1366 | V9: 1055 | W9: 2373 | X9: 1912 | Y9: 4004 | Z9: 3105 | AA9: 6364 | AB9: 3912 | AC9: 7619 | AD9: 4303 | AE9: 8142 | AF9: 4990 | AG9: 7904 | AH9: 5121 | AI9: 7180 | AJ9: 3889 | AK9: 5303 | AL9: 4365 | AM9: 6537 | AN9: 92097
A10: DE TUBERCULOSIS | B10: MÉDICO | C10: 11070 | D10: 6218 | E10: 4852 | F10: 137 | G10: 139 | H10: 155 | I10: 140 | J10: 130 | K10: 106 | L10: 215 | M10: 211 | N10: 453 | O10: 364 | P10: 638 | Q10: 436 | R10: 498 | S10: 417 | T10: 553 | U10: 302 | V10: 460 | W10: 315 | X10: 414 | Y10: 310 | Z10: 494 | AA10: 350 | AB10: 453 | AC10: 417 | AD10: 540 | AE10: 365 | AF10: 329 | AG10: 321 | AH10: 266 | AI10: 251 | AJ10: 249 | AK10: 178 | AL10: 234 | AM10: 230 | AN10: 10594
B11: ENFERMERA /O | C11: 9612 | D11: 5416 | E11: 4196 | F11: 218 | G11: 220 | H11: 152 | I11: 148 | J11: 142 | K11: 105 | L11: 359 | M11: 178 | N11: 425 | O11: 406 | P11: 631 | Q11: 352 | R11: 394 | S11: 583 | T11: 705 | U11: 295 | V11: 329 | W11: 222 | X11: 250 | Y11: 247 | Z11: 366 | AA11: 299 | AB11: 362 | AC11: 219 | AD11: 469 | AE11: 212 | AF11: 183 | AG11: 261 | AH11: 143 | AI11: 191 | AJ11: 125 | AK11: 114 | AL11: 163 | AM11: 144 | AN11: 9200
A12: SEGUIMIENTO AUTOVALENTE CON RIESGO | B12: MÉDICO | C12: 2183 | D12: 887 | E12: 1296 | F12: 0 | G12: 0 | H12: 0 | I12: 0 | J12: 0 | K12: 0 | L12: 0 | M12: 0 | N12: 0 | O12: 0 | P12: 0 | Q12: 0 | R12: 0 | S12: 0 | T12: 0 | U12: 0 | V12: 0 | W12: 0 | X12: 0 | Y12: 0 | Z12: 0 | AA12: 0 | AB12: 0 | AC12: 0 | AD12: 0 | AE12: 0 | AF12: 212 | AG12: 323 | AH12: 216 | AI12: 282 | AJ12: 229 | AK12: 265 | AL12: 230 | AM12: 426 | AN12: 2179
B13: ENFERMERA /O | C13: 23215 | D13: 8542 | E13: 14673 | F13: 0 | G13: 0 | H13: 0 | I13: 0 | J13: 0 | K13: 0 | L13: 0 | M13: 0 | N13: 0 | O13: 0 | P13: 0 | Q13: 0 | R13: 0 | S13: 0 | T13: 0 | U13: 0 | V13: 0 | W13: 0 | X13: 0 | Y13: 0 | Z13: 0 | AA13: 0 | AB13: 0 | AC13: 0 | AD13: 0 | AE13: 0 | AF13: 2202 | AG13: 4086 | AH13: 2688 | AI13: 4359 | AJ13: 2082 | AK13: 3290 | AL13: 1570 | AM13: 2938 | AN13: 22890
A14: SEGUIMIENTO RIESGO DEPENDENCIA | B14: MÉDICO | C14: 719 | D14: 264 | E14: 455 | F14: 0 | G14: 0 | H14: 0 | I14: 0 | J14: 0 | K14: 0 | L14: 0 | M14: 0 | N14: 0 | O14: 0 | P14: 0 | Q14: 0 | R14: 0 | S14: 0 | T14: 0 | U14: 0 | V14: 0 | W14: 0 | X14: 0 | Y14: 0 | Z14: 0 | AA14: 0 | AB14: 0 | AC14: 0 | AD14: 0 | AE14: 0 | AF14: 38 | AG14: 62 | AH14: 42 | AI14: 84 | AJ14: 64 | AK14: 110 | AL14: 120 | AM14: 199 | AN14: 712
B15: ENFERMERA /O | C15: 14359 | D15: 4990 | E15: 9369 | F15: 0 | G15: 0 | H15: 0 | I15: 0 | J15: 0 | K15: 0 | L15: 0 | M15: 0 | N15: 0 | O15: 0 | P15: 0 | Q15: 0 | R15: 0 | S15: 0 | T15: 0 | U15: 0 | V15: 0 | W15: 0 | X15: 0 | Y15: 0 | Z15: 0 | AA15: 0 | AB15: 0 | AC15: 0 | AD15: 0 | AE15: 0 | AF15: 635 | AG15: 1204 | AH15: 948 | AI15: 1750 | AJ15: 1202 | AK15: 2020 | AL15: 2205 | AM15: 4395 | AN15: 14194
A16: DE INFECCIÓN TRANSMISIÓN SEXUAL | B16: MÉDICO | C16: 2966 | D16: 1031 | E16: 1935 | F16: 11 | G16: 16 | H16: 20 | I16: 8 | J16: 30 | K16: 14 | L16: 54 | M16: 85 | N16: 125 | O16: 136 | P16: 82 | Q16: 143 | R16: 81 | S16: 96 | T16: 42 | U16: 76 | V16: 47 | W16: 99 | X16: 48 | Y16: 102 | Z16: 63 | AA16: 141 | AB16: 55 | AC16: 188 | AD16: 94 | AE16: 221 | AF16: 61 | AG16: 214 | AH16: 67 | AI16: 162 | AJ16: 78 | AK16: 113 | AL16: 73 | AM16: 121 | AN16: 2940
B17: ENFERMERA /O | C17: 516 | D17: 198 | E17: 318 | F17: 6 | G17: 6 | H17: 3 | I17: 12 | J17: 4 | K17: 5 | L17: 12 | M17: 8 | N17: 25 | O17: 19 | P17: 14 | Q17: 22 | R17: 18 | S17: 26 | T17: 18 | U17: 32 | V17: 21 | W17: 26 | X17: 7 | Y17: 31 | Z17: 12 | AA17: 24 | AB17: 7 | AC17: 26 | AD17: 10 | AE17: 13 | AF17: 8 | AG17: 15 | AH17: 14 | AI17: 16 | AJ17: 10 | AK17: 22 | AL17: 9 | AM17: 15 | AN17: 515
B18: MATRONA /ÓN | C18: 6111 | D18: 1514 | E18: 4602 | F18: 5 | G18: 6 | H18: 12 | I18: 5 | J18: 6 | K18: 25 | L18: 256 | M18: 646 | N18: 352 | O18: 952 | P18: 235 | Q18: 765 | R18: 152 | S18: 521 | T18: 117 | U18: 511 | V18: 85 | W18: 290 | X18: 73 | Y18: 317 | Z18: 72 | AA18: 203 | AB18: 58 | AC18: 146 | AD18: 28 | AE18: 81 | AF18: 17 | AG18: 30 | AH18: 22 | AI18: 50 | AJ18: 15 | AK18: 18 | AL18: 9 | AM18: 36 | AN18: 6043
A19: OTROS PROBLEMAS DE SALUD | B19: MÉDICO | C19: 702395 | D19: 189546 | E19: 512849 | F19: 7284 | G19: 6285 | H19: 5629 | I19: 4447 | J19: 5336 | K19: 4714 | L19: 4753 | M19: 7486 | N19: 3569 | O19: 9871 | P19: 3932 | Q19: 14177 | R19: 4288 | S19: 15942 | T19: 4891 | U19: 19518 | V19: 6157 | W19: 25114 | X19: 8782 | Y19: 34001 | Z19: 12752 | AA19: 48059 | AB19: 17384 | AC19: 59067 | AD19: 19228 | AE19: 61711 | AF19: 21424 | AG19: 59362 | AH19: 22769 | AI19: 54103 | AJ19: 19184 | AK19: 41319 | AL19: 22184 | AM19: 47853 | AN19: 690884
B20: ENFERMERA /O | C20: 80633 | D20: 28517 | E20: 52116 | F20: 1647 | G20: 1524 | H20: 626 | I20: 589 | J20: 340 | K20: 321 | L20: 368 | M20: 501 | N20: 351 | O20: 633 | P20: 416 | Q20: 936 | R20: 518 | S20: 1175 | T20: 577 | U20: 1570 | V20: 687 | W20: 1950 | X20: 1092 | Y20: 3053 | Z20: 1751 | AA20: 4596 | AB20: 2682 | AC20: 5158 | AD20: 2933 | AE20: 5939 | AF20: 3420 | AG20: 6490 | AH20: 4055 | AI20: 6277 | AJ20: 3149 | AK20: 4987 | AL20: 3904 | AM20: 6417 | AN20: 78691
B21: MATRONA /ÓN | C21: 13505 | D21: 1261 | E21: 12244 | F21: 620 | G21: 741 | H21: 38 | I21: 73 | J21: 57 | K21: 191 | L21: 32 | M21: 653 | N21: 29 | O21: 857 | P21: 35 | Q21: 1105 | R21: 28 | S21: 910 | T21: 34 | U21: 897 | V21: 35 | W21: 874 | X21: 40 | Y21: 942 | Z21: 45 | AA21: 1049 | AB21: 51 | AC21: 1112 | AD21: 61 | AE21: 1093 | AF21: 49 | AG21: 801 | AH21: 42 | AI21: 566 | AJ21: 25 | AK21: 330 | AL21: 40 | AM21: 212 | AN21: 13399
B22: NUTRICIONISTA | C22: 139925 | D22: 49069 | E22: 90856 | F22: 23914 | G22: 23005 | H22: 6517 | I22: 6740 | J22: 2658 | K22: 3224 | L22: 1053 | M22: 4204 | N22: 579 | O22: 4752 | P22: 701 | Q22: 5568 | R22: 716 | S22: 4808 | T22: 680 | U22: 4295 | V22: 747 | W22: 3723 | X22: 878 | Y22: 4162 | Z22: 1271 | AA22: 5107 | AB22: 1474 | AC22: 4868 | AD22: 1536 | AE22: 4307 | AF22: 1773 | AG22: 3775 | AH22: 1808 | AI22: 3269 | AJ22: 1325 | AK22: 2344 | AL22: 1439 | AM22: 2704 | AN22: 137375
B23: TÉCNICO PARAMÉDICO | C23: 61052 | D23: 25947 | E23: 35105 | F23: 1516 | G23: 1485 | H23: 991 | I23: 1059 | J23: 950 | K23: 1019 | L23: 660 | M23: 1307 | N23: 748 | O23: 1365 | P23: 940 | Q23: 1761 | R23: 977 | S23: 1798 | T23: 1014 | U23: 1888 | V23: 1170 | W23: 2253 | X23: 1549 | Y23: 2497 | Z23: 1973 | AA23: 3031 | AB23: 2100 | AC23: 2763 | AD23: 1998 | AE23: 2839 | AF23: 2259 | AG23: 2676 | AH23: 2493 | AI23: 2410 | AJ23: 2027 | AK23: 2241 | AL23: 2582 | AM23: 2713 | AN23: 60226
A24: NIÑOS CON NECESIDADES ESPECIALES | B24: MÉDICO | C24: 1211 | D24: 734 | E24: 477 | F24: 444 | G24: 299 | H24: 176 | I24: 96 | J24: 77 | K24: 41 | L24: 29 | M24: 24 | N24: 8 | O24: 17 | P24: 0 | Q24: 0 | R24: 0 | S24: 0 | T24: 0 | U24: 15 | V24: 0 | W24: 0 | X24: 0 | Y24: 0 | Z24: 0 | AA24: 0 | AB24: 0 | AC24: 0 | AD24: 0 | AE24: 0 | AF24: 0 | AG24: 0 | AH24: 0 | AI24: 0 | AJ24: 0 | AK24: 0 | AL24: 0 | AM24: 0 | AN24: 1039
B25: ENFERMERA /O | C25: 2878 | D25: 1576 | E25: 1302 | F25: 1259 | G25: 1086 | H25: 245 | I25: 147 | J25: 53 | K25: 33 | L25: 9 | M25: 19 | N25: 10 | O25: 17 | P25: 0 | Q25: 0 | R25: 0 | S25: 0 | T25: 0 | U25: 15 | V25: 0 | W25: 0 | X25: 0 | Y25: 0 | Z25: 0 | AA25: 0 | AB25: 0 | AC25: 0 | AD25: 0 | AE25: 0 | AF25: 0 | AG25: 0 | AH25: 0 | AI25: 0 | AJ25: 0 | AK25: 0 | AL25: 0 | AM25: 0 | AN25: 2698
B26: MATRONA /ÓN | C26: 179 | D26: 43 | E26: 137 | F26: 25 | G26: 20 | H26: 0 | I26: 0 | J26: 7 | K26: 12 | L26: 3 | M26: 42 | N26: 8 | O26: 63 | P26: 0 | Q26: 0 | R26: 0 | S26: 0 | T26: 0 | U26: 15 | V26: 0 | W26: 0 | X26: 0 | Y26: 0 | Z26: 0 | AA26: 0 | AB26: 0 | AC26: 0 | AD26: 0 | AE26: 0 | AF26: 0 | AG26: 0 | AH26: 0 | AI26: 0 | AJ26: 0 | AK26: 0 | AL26: 0 | AM26: 0 | AN26: 175
B27: NUTRICIONISTA | C27: 1936 | D27: 988 | E27: 948 | F27: 763 | G27: 715 | H27: 136 | I27: 104 | J27: 44 | K27: 49 | L27: 35 | M27: 50 | N27: 10 | O27: 30 | P27: 0 | Q27: 0 | R27: 0 | S27: 0 | T27: 0 | U27: 15 | V27: 0 | W27: 0 | X27: 0 | Y27: 0 | Z27: 0 | AA27: 0 | AB27: 0 | AC27: 0 | AD27: 0 | AE27: 0 | AF27: 0 | AG27: 0 | AH27: 0 | AI27: 0 | AJ27: 0 | AK27: 0 | AL27: 0 | AM27: 0 | AN27: 1849
B28: TÉCNICO PARAMÉDICO | C28: 87 | D28: 52 | E28: 35 | F28: 25 | G28: 13 | H28: 16 | I28: 6 | J28: 6 | K28: 4 | L28: 4 | M28: 4 | N28: 1 | O28: 8 | P28: 0 | Q28: 0 | R28: 0 | S28: 0 | T28: 0 | U28: 15 | V28: 0 | W28: 0 | X28: 0 | Y28: 0 | Z28: 0 | AA28: 0 | AB28: 0 | AC28: 0 | AD28: 0 | AE28: 0 | AF28: 0 | AG28: 0 | AH28: 0 | AI28: 0 | AJ28: 0 | AK28: 0 | AL28: 0 | AM28: 0 | AN28: 85
A29: Servicio: Arica
A30: DE SALUD CARDIOVASCULAR | B30: MÉDICO | C30: 19907 | D30: 7288 | E30: 12619 | F30: 0 | G30: 0 | H30: 0 | I30: 0 | J30: 0 | K30: 0 | L30: 10 | M30: 16 | N30: 18 | O30: 36 | P30: 37 | Q30: 31 | R30: 51 | S30: 104 | T30: 81 | U30: 218 | V30: 132 | W30: 360 | X30: 288 | Y30: 646 | Z30: 534 | AA30: 1116 | AB30: 757 | AC30: 1518 | AD30: 920 | AE30: 1622 | AF30: 1148 | AG30: 1939 | AH30: 1346 | AI30: 1958 | AJ30: 1024 | AK30: 1443 | AL30: 942 | AM30: 1612 | AN30: 19841
B31: ENFERMERA /O | C31: 17302 | D31: 6826 | E31: 10476 | F31: 0 | G31: 0 | H31: 0 | I31: 0 | J31: 0 | K31: 0 | L31: 4 | M31: 7 | N31: 14 | O31: 26 | P31: 38 | Q31: 35 | R31: 78 | S31: 111 | T31: 91 | U31: 192 | V31: 169 | W31: 321 | X31: 313 | Y31: 536 | Z31: 530 | AA31: 932 | AB31: 757 | AC31: 1237 | AD31: 880 | AE31: 1286 | AF31: 1038 | AG31: 1567 | AH31: 1147 | AI31: 1513 | AJ31: 840 | AK31: 1123 | AL31: 927 | AM31: 1590 | AN31: 17298
B32: NUTRICIONISTA | C32: 9923 | D32: 3632 | E32: 6291 | F32: 0 | G32: 0 | H32: 0 | I32: 0 | J32: 0 | K32: 0 | L32: 4 | M32: 9 | N32: 9 | O32: 17 | P32: 29 | Q32: 20 | R32: 34 | S32: 57 | T32: 48 | U32: 102 | V32: 86 | W32: 170 | X32: 148 | Y32: 319 | Z32: 265 | AA32: 564 | AB32: 340 | AC32: 746 | AD32: 426 | AE32: 823 | AF32: 550 | AG32: 919 | AH32: 696 | AI32: 1017 | AJ32: 528 | AK32: 732 | AL32: 469 | AM32: 796 | AN32: 9923
B33: TÉCNICO PARAMÉDICO | C33: 303 | D33: 146 | E33: 157 | F33: 0 | G33: 0 | H33: 0 | I33: 0 | J33: 0 | K33: 0 | L33: 0 | M33: 0 | N33: 0 | O33: 0 | P33: 2 | Q33: 0 | R33: 3 | S33: 0 | T33: 1 | U33: 1 | V33: 1 | W33: 9 | X33: 18 | Y33: 7 | Z33: 18 | AA33: 18 | AB33: 35 | AC33: 6 | AD33: 10 | AE33: 8 | AF33: 2 | AG33: 22 | AH33: 22 | AI33: 53 | AJ33: 33 | AK33: 18 | AL33: 1 | AM33: 15 | AN33: 287
A34: DE TUBERCULOSIS | B34: MÉDICO | C34: 402 | D34: 207 | E34: 195 | F34: 9 | G34: 3 | H34: 0 | I34: 0 | J34: 6 | K34: 0 | L34: 0 | M34: 9 | N34: 28 | O34: 13 | P34: 16 | Q34: 20 | R34: 21 | S34: 37 | T34: 18 | U34: 10 | V34: 23 | W34: 14 | X34: 11 | Y34: 12 | Z34: 13 | AA34: 8 | AB34: 17 | AC34: 9 | AD34: 12 | AE34: 24 | AF34: 12 | AG34: 14 | AH34: 6 | AI34: 3 | AJ34: 10 | AK34: 10 | AL34: 5 | AM34: 9 | AN34: 397
B35: ENFERMERA /O | C35: 243 | D35: 141 | E35: 102 | F35: 7 | G35: 0 | H35: 5 | I35: 2 | J35: 2 | K35: 5 | L35: 0 | M35: 3 | N35: 17 | O35: 5 | P35: 11 | Q35: 6 | R35: 12 | S35: 16 | T35: 10 | U35: 3 | V35: 10 | W35: 6 | X35: 13 | Y35: 11 | Z35: 10 | AA35: 11 | AB35: 21 | AC35: 2 | AD35: 9 | AE35: 16 | AF35: 7 | AG35: 4 | AH35: 3 | AI35: 2 | AJ35: 2 | AK35: 4 | AL35: 2 | AM35: 6 | AN35: 243
A36: SEGUIMIENTO AUTOVALENTE CON RIESGO | B36: MÉDICO | C36: 382 | D36: 130 | E36: 252 | F36: 0 | G36: 0 | H36: 0 | I36: 0 | J36: 0 | K36: 0 | L36: 0 | M36: 0 | N36: 0 | O36: 0 | P36: 0 | Q36: 0 | R36: 0 | S36: 0 | T36: 0 | U36: 0 | V36: 0 | W36: 0 | X36: 0 | Y36: 0 | Z36: 0 | AA36: 0 | AB36: 0 | AC36: 0 | AD36: 0 | AE36: 0 | AF36: 19 | AG36: 45 | AH36: 27 | AI36: 76 | AJ36: 33 | AK36: 45 | AL36: 51 | AM36: 86 | AN36: 382
B37: ENFERMERA /O | C37: 223 | D37: 69 | E37: 154 | F37: 0 | G37: 0 | H37: 0 | I37: 0 | J37: 0 | K37: 0 | L37: 0 | M37: 0 | N37: 0 | O37: 0 | P37: 0 | Q37: 0 | R37: 0 | S37: 0 | T37: 0 | U37: 0 | V37: 0 | W37: 0 | X37: 0 | Y37: 0 | Z37: 0 | AA37: 0 | AB37: 0 | AC37: 0 | AD37: 0 | AE37: 0 | AF37: 4 | AG37: 43 | AH37: 29 | AI37: 48 | AJ37: 17 | AK37: 38 | AL37: 19 | AM37: 25 | AN37: 223
A38: SEGUIMIENTO RIESGO DEPENDENCIA | B38: MÉDICO | C38: 101 | D38: 28 | E38: 73 | F38: 0 | G38: 0 | H38: 0 | I38: 0 | J38: 0 | K38: 0 | L38: 0 | M38: 0 | N38: 0 | O38: 0 | P38: 0 | Q38: 0 | R38: 0 | S38: 0 | T38: 0 | U38: 0 | V38: 0 | W38: 0 | X38: 0 | Y38: 0 | Z38: 0 | AA38: 0 | AB38: 0 | AC38: 0 | AD38: 0 | AE38: 0 | AF38: 4 | AG38: 5 | AH38: 3 | AI38: 13 | AJ38: 3 | AK38: 22 | AL38: 18 | AM38: 33 | AN38: 101
B39: ENFERMERA /O | C39: 184 | D39: 69 | E39: 115 | F39: 0 | G39: 0 | H39: 0 | I39: 0 | J39: 0 | K39: 0 | L39: 0 | M39: 0 | N39: 0 | O39: 0 | P39: 0 | Q39: 0 | R39: 0 | S39: 0 | T39: 0 | U39: 0 | V39: 0 | W39: 0 | X39: 0 | Y39: 0 | Z39: 0 | AA39: 0 | AB39: 0 | AC39: 0 | AD39: 0 | AE39: 0 | AF39: 6 | AG39: 17 | AH39: 7 | AI39: 29 | AJ39: 21 | AK39: 23 | AL39: 35 | AM39: 46 | AN39: 184
A40: DE INFECCIÓN TRANSMISIÓN SEXUAL | B40: MÉDICO | C40: 3 | D40: 0 | E40: 3 | F40: 0 | G40: 0 | H40: 0 | I40: 0 | J40: 0 | K40: 0 | L40: 0 | M40: 0 | N40: 0 | O40: 0 | P40: 0 | Q40: 0 | R40: 0 | S40: 0 | T40: 0 | U40: 0 | V40: 0 | W40: 0 | X40: 0 | Y40: 0 | Z40: 0 | AA40: 0 | AB40: 0 | AC40: 0 | AD40: 0 | AE40: 0 | AF40: 0 | AG40: 1 | AH40: 0 | AI40: 1 | AJ40: 0 | AK40: 0 | AL40: 0 | AM40: 1 | AN40: 3
B41: ENFERMERA /O | C41: 0 | D41: 0 | E41: 0 | F41: 0 | G41: 0 | H41: 0 | I41: 0 | J41: 0 | K41: 0 | L41: 0 | M41: 0 | N41: 0 | O41: 0 | P41: 0 | Q41: 0 | R41: 0 | S41: 0 | T41: 0 | U41: 0 | V41: 0 | W41: 0 | X41: 0 | Y41: 0 | Z41: 0 | AA41: 0 | AB41: 0 | AC41: 0 | AD41: 0 | AE41: 0 | AF41: 0 | AG41: 0 | AH41: 0 | AI41: 0 | AJ41: 0 | AK41: 0 | AL41: 0 | AM41: 0 | AN41: 0
B42: MATRONA /ÓN | C42: 1 | D42: 0 | E42: 1 | F42: 0 | G42: 0 | H42: 0 | I42: 0 | J42: 0 | K42: 0 | L42: 0 | M42: 0 | N42: 0 | O42: 0 | P42: 0 | Q42: 1 | R42: 0 | S42: 0 | T42: 0 | U42: 0 | V42: 0 | W42: 0 | X42: 0 | Y42: 0 | Z42: 0 | AA42: 0 | AB42: 0 | AC42: 0 | AD42: 0 | AE42: 0 | AF42: 0 | AG42: 0 | AH42: 0 | AI42: 0 | AJ42: 0 | AK42: 0 | AL42: 0 | AM42: 0 | AN42: 1
A43: OTROS PROBLEMAS DE SALUD | B43: MÉDICO | C43: 18344 | D43: 5486 | E43: 12858 | F43: 21 | G43: 25 | H43: 157 | I43: 175 | J43: 328 | K43: 305 | L43: 308 | M43: 418 | N43: 213 | O43: 443 | P43: 211 | Q43: 448 | R43: 218 | S43: 425 | T43: 204 | U43: 498 | V43: 152 | W43: 492 | X43: 251 | Y43: 731 | Z43: 326 | AA43: 1124 | AB43: 451 | AC43: 1416 | AD43: 661 | AE43: 1419 | AF43: 551 | AG43: 1486 | AH43: 577 | AI43: 1426 | AJ43: 458 | AK43: 968 | AL43: 399 | AM43: 1059 | AN43: 18306
B44: ENFERMERA /O | C44: 1618 | D44: 662 | E44: 956 | F44: 2 | G44: 2 | H44: 33 | I44: 52 | J44: 68 | K44: 67 | L44: 81 | M44: 84 | N44: 52 | O44: 77 | P44: 41 | Q44: 64 | R44: 38 | S44: 59 | T44: 37 | U44: 74 | V44: 31 | W44: 42 | X44: 48 | Y44: 69 | Z44: 41 | AA44: 84 | AB44: 46 | AC44: 112 | AD44: 60 | AE44: 42 | AF44: 38 | AG44: 35 | AH44: 22 | AI44: 36 | AJ44: 17 | AK44: 28 | AL44: 7 | AM44: 29 | AN44: 1605
B45: MATRONA /ÓN | C45: 107 | D45: 5 | E45: 102 | F45: 0 | G45: 0 | H45: 0 | I45: 0 | J45: 4 | K45: 0 | L45: 1 | M45: 12 | N45: 0 | O45: 22 | P45: 0 | Q45: 11 | R45: 0 | S45: 10 | T45: 0 | U45: 15 | V45: 0 | W45: 13 | X45: 0 | Y45: 5 | Z45: 0 | AA45: 3 | AB45: 0 | AC45: 3 | AD45: 0 | AE45: 4 | AF45: 0 | AG45: 3 | AH45: 0 | AI45: 1 | AJ45: 0 | AK45: 0 | AL45: 0 | AM45: 0 | AN45: 107
B46: NUTRICIONISTA | C46: 8764 | D46: 3624 | E46: 5140 | F46: 2079 | G46: 1963 | H46: 586 | I46: 588 | J46: 240 | K46: 254 | L46: 119 | M46: 382 | N46: 51 | O46: 222 | P46: 32 | Q46: 214 | R46: 38 | S46: 204 | T46: 40 | U46: 194 | V46: 28 | W46: 142 | X46: 32 | Y46: 137 | Z46: 42 | AA46: 175 | AB46: 60 | AC46: 193 | AD46: 72 | AE46: 156 | AF46: 64 | AG46: 108 | AH46: 52 | AI46: 78 | AJ46: 49 | AK46: 56 | AL46: 40 | AM46: 74 | AN46: 8759
B47: TÉCNICO PARAMÉDICO | C47: 51 | D47: 19 | E47: 32 | F47: 1 | G47: 0 | H47: 0 | I47: 0 | J47: 0 | K47: 0 | L47: 0 | M47: 0 | N47: 0 | O47: 0 | P47: 0 | Q47: 8 | R47: 1 | S47: 10 | T47: 0 | U47: 0 | V47: 1 | W47: 1 | X47: 5 | Y47: 2 | Z47: 4 | AA47: 3 | AB47: 6 | AC47: 0 | AD47: 1 | AE47: 3 | AF47: 0 | AG47: 0 | AH47: 0 | AI47: 0 | AJ47: 0 | AK47: 2 | AL47: 0 | AM47: 3 | AN47: 42
A48: NIÑOS CON NECESIDADES ESPECIALES | B48: MÉDICO | C48: 16 | D48: 9 | E48: 7 | F48: 7 | G48: 6 | H48: 1 | I48: 1 | J48: 1 | K48: 0 | L48: 0 | M48: 0 | N48: 0 | O48: 0 | P48: 0 | Q48: 0 | R48: 0 | S48: 0 | T48: 0 | U48: 0 | V48: 0 | W48: 0 | X48: 0 | Y48: 0 | Z48: 0 | AA48: 0 | AB48: 0 | AC48: 0 | AD48: 0 | AE48: 0 | AF48: 0 | AG48: 0 | AH48: 0 | AI48: 0 | AJ48: 0 | AK48: 0 | AL48: 0 | AM48: 0 | AN48: 15
B49: ENFERMERA /O | C49: 223 | D49: 112 | E49: 111 | F49: 106 | G49: 107 | H49: 6 | I49: 4 | J49: 0 | K49: 0 | L49: 0 | M49: 0 | N49: 0 | O49: 0 | P49: 0 | Q49: 0 | R49: 0 | S49: 0 | T49: 0 | U49: 0 | V49: 0 | W49: 0 | X49: 0 | Y49: 0 | Z49: 0 | AA49: 0 | AB49: 0 | AC49: 0 | AD49: 0 | AE49: 0 | AF49: 0 | AG49: 0 | AH49: 0 | AI49: 0 | AJ49: 0 | AK49: 0 | AL49: 0 | AM49: 0 | AN49: 223
B50: MATRONA /ÓN | C50: 0 | D50: 0 | E50: 0 | F50: 0 | G50: 0 | H50: 0 | I50: 0 | J50: 0 | K50: 0 | L50: 0 | M50: 0 | N50: 0 | O50: 0 | P50: 0 | Q50: 0 | R50: 0 | S50: 0 | T50: 0 | U50: 0 | V50: 0 | W50: 0 | X50: 0 | Y50: 0 | Z50: 0 | AA50: 0 | AB50: 0 | AC50: 0 | AD50: 0 | AE50: 0 | AF50: 0 | AG50: 0 | AH50: 0 | AI50: 0 | AJ50: 0 | AK50: 0 | AL50: 0 | AM50: 0 | AN50: 0
B51: NUTRICIONISTA | C51: 16 | D51: 10 | E51: 6 | F51: 9 | G51: 6 | H51: 1 | I51: 0 | J51: 0 | K51: 0 | L51: 0 | M51: 0 | N51: 0 | O51: 0 | P51: 0 | Q51: 0 | R51: 0 | S51: 0 | T51: 0 | U51: 0 | V51: 0 | W51: 0 | X51: 0 | Y51: 0 | Z51: 0 | AA51: 0 | AB51: 0 | AC51: 0 | AD51: 0 | AE51: 0 | AF51: 0 | AG51: 0 | AH51: 0 | AI51: 0 | AJ51: 0 | AK51: 0 | AL51: 0 | AM51: 0 | AN51: 16
B52: TÉCNICO PARAMÉDICO | C52: 0 | D52: 0 | E52: 0 | F52: 0 | G52: 0 | H52: 0 | I52: 0 | J52: 0 | K52: 0 | L52: 0 | M52: 0 | N52: 0 | O52: 0 | P52: 0 | Q52: 0 | R52: 0 | S52: 0 | T52: 0 | U52: 0 | V52: 0 | W52: 0 | X52: 0 | Y52: 0 | Z52: 0 | AA52: 0 | AB52: 0 | AC52: 0 | AD52: 0 | AE52: 0 | AF52: 0 | AG52: 0 | AH52: 0 | AI52: 0 | AJ52: 0 | AK52: 0 | AL52: 0 | AM52: 0 | AN52: 0
A53: Servicio: Iquique
A54: DE SALUD CARDIOVASCULAR | B54: MÉDICO | C54: 60379 | D54: 21836 | E54: 38557 | F54: 0 | G54: 0 | H54: 0 | I54: 0 | J54: 0 | K54: 0 | L54: 32 | M54: 53 | N54: 34 | O54: 163 | P54: 92 | Q54: 230 | R54: 196 | S54: 394 | T54: 353 | U54: 756 | V54: 594 | W54: 1244 | X54: 1108 | Y54: 2132 | Z54: 1802 | AA54: 3943 | AB54: 2819 | AC54: 5104 | AD54: 3455 | AE54: 6073 | AF54: 3691 | AG54: 6180 | AH54: 3558 | AI54: 5254 | AJ54: 2271 | AK54: 3661 | AL54: 2172 | AM54: 3871 | AN54: 59715
B55: ENFERMERA /O | C55: 12883 | D55: 4825 | E55: 8058 | F55: 0 | G55: 0 | H55: 0 | I55: 0 | J55: 0 | K55: 0 | L55: 5 | M55: 6 | N55: 6 | O55: 16 | P55: 16 | Q55: 45 | R55: 40 | S55: 72 | T55: 94 | U55: 145 | V55: 133 | W55: 265 | X55: 253 | Y55: 480 | Z55: 354 | AA55: 849 | AB55: 533 | AC55: 1005 | AD55: 679 | AE55: 1211 | AF55: 790 | AG55: 1209 | AH55: 841 | AI55: 1106 | AJ55: 553 | AK55: 811 | AL55: 528 | AM55: 838 | AN55: 12584
B56: NUTRICIONISTA | C56: 10401 | D56: 3884 | E56: 6517 | F56: 0 | G56: 0 | H56: 0 | I56: 0 | J56: 0 | K56: 0 | L56: 4 | M56: 8 | N56: 17 | O56: 25 | P56: 25 | Q56: 59 | R56: 59 | S56: 106 | T56: 139 | U56: 199 | V56: 138 | W56: 263 | X56: 239 | Y56: 442 | Z56: 314 | AA56: 797 | AB56: 541 | AC56: 918 | AD56: 570 | AE56: 915 | AF56: 511 | AG56: 913 | AH56: 580 | AI56: 774 | AJ56: 392 | AK56: 558 | AL56: 355 | AM56: 540 | AN56: 9827
B57: TÉCNICO PARAMÉDICO | C57: 165 | D57: 56 | E57: 109 | F57: 0 | G57: 0 | H57: 0 | I57: 0 | J57: 0 | K57: 0 | L57: 0 | M57: 0 | N57: 0 | O57: 0 | P57: 0 | Q57: 0 | R57: 0 | S57: 0 | T57: 0 | U57: 0 | V57: 0 | W57: 3 | X57: 4 | Y57: 0 | Z57: 0 | AA57: 2 | AB57: 8 | AC57: 15 | AD57: 1 | AE57: 26 | AF57: 19 | AG57: 18 | AH57: 20 | AI57: 24 | AJ57: 0 | AK57: 2 | AL57: 4 | AM57: 19 | AN57: 163
A58: DE TUBERCULOSIS | B58: MÉDICO | C58: 639 | D58: 337 | E58: 302 | F58: 1 | G58: 3 | H58: 2 | I58: 2 | J58: 7 | K58: 7 | L58: 19 | M58: 8 | N58: 18 | O58: 34 | P58: 39 | Q58: 24 | R58: 34 | S58: 37 | T58: 47 | U58: 33 | V58: 23 | W58: 23 | X58: 25 | Y58: 12 | Z58: 21 | AA58: 17 | AB58: 11 | AC58: 26 | AD58: 32 | AE58: 30 | AF58: 16 | AG58: 10 | AH58: 12 | AI58: 15 | AJ58: 7 | AK58: 7 | AL58: 23 | AM58: 14 | AN58: 512
B59: ENFERMERA /O | C59: 2176 | D59: 1010 | E59: 1166 | F59: 13 | G59: 7 | H59: 0 | I59: 0 | J59: 13 | K59: 12 | L59: 18 | M59: 21 | N59: 108 | O59: 240 | P59: 188 | Q59: 121 | R59: 56 | S59: 311 | T59: 249 | U59: 166 | V59: 21 | W59: 64 | X59: 31 | Y59: 74 | Z59: 29 | AA59: 75 | AB59: 77 | AC59: 11 | AD59: 147 | AE59: 13 | AF59: 11 | AG59: 3 | AH59: 2 | AI59: 40 | AJ59: 0 | AK59: 6 | AL59: 47 | AM59: 2 | AN59: 1995
A60: SEGUIMIENTO AUTOVALENTE CON RIESGO | B60: MÉDICO | C60: 55 | D60: 24 | E60: 31 | F60: 0 | G60: 0 | H60: 0 | I60: 0 | J60: 0 | K60: 0 | L60: 0 | M60: 0 | N60: 0 | O60: 0 | P60: 0 | Q60: 0 | R60: 0 | S60: 0 | T60: 0 | U60: 0 | V60: 0 | W60: 0 | X60: 0 | Y60: 0 | Z60: 0 | AA60: 0 | AB60: 0 | AC60: 0 | AD60: 0 | AE60: 0 | AF60: 7 | AG60: 6 | AH60: 6 | AI60: 6 | AJ60: 4 | AK60: 12 | AL60: 7 | AM60: 7 | AN60: 55
B61: ENFERMERA /O | C61: 473 | D61: 177 | E61: 296 | F61: 0 | G61: 0 | H61: 0 | I61: 0 | J61: 0 | K61: 0 | L61: 0 | M61: 0 | N61: 0 | O61: 0 | P61: 0 | Q61: 0 | R61: 0 | S61: 0 | T61: 0 | U61: 0 | V61: 0 | W61: 0 | X61: 0 | Y61: 0 | Z61: 0 | AA61: 0 | AB61: 0 | AC61: 0 | AD61: 0 | AE61: 0 | AF61: 51 | AG61: 80 | AH61: 56 | AI61: 91 | AJ61: 35 | AK61: 62 | AL61: 35 | AM61: 63 | AN61: 456
A62: SEGUIMIENTO RIESGO DEPENDENCIA | B62: MÉDICO | C62: 30 | D62: 11 | E62: 19 | F62: 0 | G62: 0 | H62: 0 | I62: 0 | J62: 0 | K62: 0 | L62: 0 | M62: 0 | N62: 0 | O62: 0 | P62: 0 | Q62: 0 | R62: 0 | S62: 0 | T62: 0 | U62: 0 | V62: 0 | W62: 0 | X62: 0 | Y62: 0 | Z62: 0 | AA62: 0 | AB62: 0 | AC62: 0 | AD62: 0 | AE62: 0 | AF62: 2 | AG62: 2 | AH62: 2 | AI62: 5 | AJ62: 4 | AK62: 4 | AL62: 3 | AM62: 8 | AN62: 30
B63: ENFERMERA /O | C63: 300 | D63: 97 | E63: 203 | F63: 0 | G63: 0 | H63: 0 | I63: 0 | J63: 0 | K63: 0 | L63: 0 | M63: 0 | N63: 0 | O63: 0 | P63: 0 | Q63: 0 | R63: 0 | S63: 0 | T63: 0 | U63: 0 | V63: 0 | W63: 0 | X63: 0 | Y63: 0 | Z63: 0 | AA63: 0 | AB63: 0 | AC63: 0 | AD63: 0 | AE63: 0 | AF63: 21 | AG63: 30 | AH63: 17 | AI63: 34 | AJ63: 23 | AK63: 34 | AL63: 36 | AM63: 105 | AN63: 283
A64: DE INFECCIÓN TRANSMISIÓN SEXUAL | B64: MÉDICO | C64: 2 | D64: 1 | E64: 1 | F64: 1 | G64: 1 | H64: 0 | I64: 0 | J64: 0 | K64: 0 | L64: 0 | M64: 0 | N64: 0 | O64: 0 | P64: 0 | Q64: 0 | R64: 0 | S64: 0 | T64: 0 | U64: 0 | V64: 0 | W64: 0 | X64: 0 | Y64: 0 | Z64: 0 | AA64: 0 | AB64: 0 | AC64: 0 | AD64: 0 | AE64: 0 | AF64: 0 | AG64: 0 | AH64: 0 | AI64: 0 | AJ64: 0 | AK64: 0 | AL64: 0 | AM64: 0 | AN64: 2
B65: ENFERMERA /O | C65: 93 | D65: 10 | E65: 83 | F65: 0 | G65: 2 | H65: 1 | I65: 6 | J65: 2 | K65: 4 | L65: 0 | M65: 3 | N65: 0 | O65: 2 | P65: 0 | Q65: 4 | R65: 0 | S65: 4 | T65: 0 | U65: 3 | V65: 1 | W65: 7 | X65: 1 | Y65: 11 | Z65: 0 | AA65: 7 | AB65: 2 | AC65: 9 | AD65: 1 | AE65: 4 | AF65: 0 | AG65: 2 | AH65: 2 | AI65: 7 | AJ65: 0 | AK65: 5 | AL65: 0 | AM65: 3 | AN65: 92
B66: MATRONA /ÓN | C66: 0 | D66: 0 | E66: 0 | F66: 0 | G66: 0 | H66: 0 | I66: 0 | J66: 0 | K66: 0 | L66: 0 | M66: 0 | N66: 0 | O66: 0 | P66: 0 | Q66: 0 | R66: 0 | S66: 0 | T66: 0 | U66: 0 | V66: 0 | W66: 0 | X66: 0 | Y66: 0 | Z66: 0 | AA66: 0 | AB66: 0 | AC66: 0 | AD66: 0 | AE66: 0 | AF66: 0 | AG66: 0 | AH66: 0 | AI66: 0 | AJ66: 0 | AK66: 0 | AL66: 0 | AM66: 0 | AN66: 0
A67: OTROS PROBLEMAS DE SALUD | B67: MÉDICO | C67: 26562 | D67: 6552 | E67: 20010 | F67: 183 | G67: 148 | H67: 109 | I67: 99 | J67: 78 | K67: 96 | L67: 105 | M67: 221 | N67: 61 | O67: 315 | P67: 122 | Q67: 513 | R67: 147 | S67: 483 | T67: 133 | U67: 561 | V67: 192 | W67: 692 | X67: 214 | Y67: 965 | Z67: 285 | AA67: 1303 | AB67: 531 | AC67: 2214 | AD67: 736 | AE67: 2688 | AF67: 916 | AG67: 2985 | AH67: 986 | AI67: 2585 | AJ67: 846 | AK67: 1966 | AL67: 908 | AM67: 2176 | AN67: 24157
B68: ENFERMERA /O | C68: 3492 | D68: 1234 | E68: 2258 | F68: 605 | G68: 576 | H68: 99 | I68: 95 | J68: 2 | K68: 1 | L68: 8 | M68: 24 | N68: 2 | O68: 24 | P68: 11 | Q68: 65 | R68: 17 | S68: 58 | T68: 12 | U68: 74 | V68: 16 | W68: 83 | X68: 28 | Y68: 107 | Z68: 36 | AA68: 177 | AB68: 58 | AC68: 206 | AD68: 52 | AE68: 202 | AF68: 82 | AG68: 156 | AH68: 65 | AI68: 162 | AJ68: 64 | AK68: 115 | AL68: 77 | AM68: 133 | AN68: 2861
B69: MATRONA /ÓN | C69: 912 | D69: 358 | E69: 554 | F69: 334 | G69: 403 | H69: 14 | I69: 12 | J69: 0 | K69: 3 | L69: 0 | M69: 12 | N69: 1 | O69: 21 | P69: 0 | Q69: 23 | R69: 0 | S69: 9 | T69: 0 | U69: 7 | V69: 2 | W69: 14 | X69: 1 | Y69: 9 | Z69: 0 | AA69: 10 | AB69: 2 | AC69: 10 | AD69: 2 | AE69: 5 | AF69: 1 | AG69: 7 | AH69: 1 | AI69: 5 | AJ69: 0 | AK69: 3 | AL69: 0 | AM69: 1 | AN69: 874
B70: NUTRICIONISTA | C70: 4682 | D70: 1824 | E70: 2858 | F70: 917 | G70: 855 | H70: 196 | I70: 183 | J70: 44 | K70: 49 | L70: 27 | M70: 83 | N70: 14 | O70: 134 | P70: 41 | Q70: 116 | R70: 36 | S70: 121 | T70: 39 | U70: 132 | V70: 43 | W70: 107 | X70: 42 | Y70: 160 | Z70: 58 | AA70: 147 | AB70: 87 | AC70: 199 | AD70: 71 | AE70: 166 | AF70: 61 | AG70: 136 | AH70: 65 | AI70: 106 | AJ70: 39 | AK70: 85 | AL70: 44 | AM70: 79 | AN70: 4363
B71: TÉCNICO PARAMÉDICO | C71: 1800 | D71: 793 | E71: 1007 | F71: 50 | G71: 45 | H71: 33 | I71: 66 | J71: 37 | K71: 46 | L71: 17 | M71: 28 | N71: 20 | O71: 29 | P71: 52 | Q71: 155 | R71: 47 | S71: 54 | T71: 51 | U71: 81 | V71: 50 | W71: 59 | X71: 54 | Y71: 57 | Z71: 47 | AA71: 44 | AB71: 53 | AC71: 65 | AD71: 52 | AE71: 39 | AF71: 52 | AG71: 77 | AH71: 69 | AI71: 59 | AJ71: 28 | AK71: 27 | AL71: 81 | AM71: 76 | AN71: 1792
A72: NIÑOS CON NECESIDADES ESPECIALES | B72: MÉDICO | C72: 16 | D72: 9 | E72: 7 | F72: 9 | G72: 7 | H72: 0 | I72: 0 | J72: 0 | K72: 0 | L72: 0 | M72: 0 | N72: 0 | O72: 0 | P72: 0 | Q72: 0 | R72: 0 | S72: 0 | T72: 0 | U72: 0 | V72: 0 | W72: 0 | X72: 0 | Y72: 0 | Z72: 0 | AA72: 0 | AB72: 0 | AC72: 0 | AD72: 0 | AE72: 0 | AF72: 0 | AG72: 0 | AH72: 0 | AI72: 0 | AJ72: 0 | AK72: 0 | AL72: 0 | AM72: 0 | AN72: 10
B73: ENFERMERA /O | C73: 77 | D73: 45 | E73: 32 | F73: 43 | G73: 29 | H73: 2 | I73: 3 | J73: 0 | K73: 0 | L73: 0 | M73: 0 | N73: 0 | O73: 0 | P73: 0 | Q73: 0 | R73: 0 | S73: 0 | T73: 0 | U73: 0 | V73: 0 | W73: 0 | X73: 0 | Y73: 0 | Z73: 0 | AA73: 0 | AB73: 0 | AC73: 0 | AD73: 0 | AE73: 0 | AF73: 0 | AG73: 0 | AH73: 0 | AI73: 0 | AJ73: 0 | AK73: 0 | AL73: 0 | AM73: 0 | AN73: 63
B74: MATRONA /ÓN | C74: 3 | D74: 0 | E74: 3 | F74: 0 | G74: 3 | H74: 0 | I74: 0 | J74: 0 | K74: 0 | L74: 0 | M74: 0 | N74: 0 | O74: 0 | P74: 0 | Q74: 0 | R74: 0 | S74: 0 | T74: 0 | U74: 0 | V74: 0 | W74: 0 | X74: 0 | Y74: 0 | Z74: 0 | AA74: 0 | AB74: 0 | AC74: 0 | AD74: 0 | AE74: 0 | AF74: 0 | AG74: 0 | AH74: 0 | AI74: 0 | AJ74: 0 | AK74: 0 | AL74: 0 | AM74: 0 | AN74: 3
B75: NUTRICIONISTA | C75: 45 | D75: 27 | E75: 18 | F75: 24 | G75: 13 | H75: 1 | I75: 2 | J75: 0 | K75: 1 | L75: 2 | M75: 2 | N75: 0 | O75: 0 | P75: 0 | Q75: 0 | R75: 0 | S75: 0 | T75: 0 | U75: 0 | V75: 0 | W75: 0 | X75: 0 | Y75: 0 | Z75: 0 | AA75: 0 | AB75: 0 | AC75: 0 | AD75: 0 | AE75: 0 | AF75: 0 | AG75: 0 | AH75: 0 | AI75: 0 | AJ75: 0 | AK75: 0 | AL75: 0 | AM75: 0 | AN75: 41
B76: TÉCNICO PARAMÉDICO | C76: 0 | D76: 0 | E76: 0 | F76: 0 | G76: 0 | H76: 0 | I76: 0 | J76: 0 | K76: 0 | L76: 0 | M76: 0 | N76: 0 | O76: 0 | P76: 0 | Q76: 0 | R76: 0 | S76: 0 | T76: 0 | U76: 0 | V76: 0 | W76: 0 | X76: 0 | Y76: 0 | Z76: 0 | AA76: 0 | AB76: 0 | AC76: 0 | AD76: 0 | AE76: 0 | AF76: 0 | AG76: 0 | AH76: 0 | AI76: 0 | AJ76: 0 | AK76: 0 | AL76: 0 | AM76: 0 | AN76: 0
A77: Servicio: Antofagasta
A78: DE SALUD CARDIOVASCULAR | B78: MÉDICO | C78: 89251 | D78: 30164 | E78: 59087 | F78: 0 | G78: 0 | H78: 0 | I78: 0 | J78: 0 | K78: 0 | L78: 43 | M78: 158 | N78: 122 | O78: 235 | P78: 236 | Q78: 404 | R78: 258 | S78: 642 | T78: 439 | U78: 1073 | V78: 792 | W78: 1958 | X78: 1411 | Y78: 3501 | Z78: 2683 | AA78: 6142 | AB78: 3828 | AC78: 8249 | AD78: 4839 | AE78: 8613 | AF78: 4659 | AG78: 8317 | AH78: 4321 | AI78: 7475 | AJ78: 3225 | AK78: 5768 | AL78: 3308 | AM78: 6550 | AN78: 81117
B79: ENFERMERA /O | C79: 26042 | D79: 9201 | E79: 16841 | F79: 0 | G79: 0 | H79: 0 | I79: 0 | J79: 0 | K79: 0 | L79: 8 | M79: 7 | N79: 18 | O79: 23 | P79: 23 | Q79: 90 | R79: 58 | S79: 150 | T79: 106 | U79: 277 | V79: 183 | W79: 513 | X79: 340 | Y79: 822 | Z79: 711 | AA79: 1483 | AB79: 948 | AC79: 1901 | AD79: 1176 | AE79: 2065 | AF79: 1577 | AG79: 2652 | AH79: 1578 | AI79: 2556 | AJ79: 1197 | AK79: 2031 | AL79: 1278 | AM79: 2271 | AN79: 24623
B80: NUTRICIONISTA | C80: 19276 | D80: 5844 | E80: 13432 | F80: 0 | G80: 0 | H80: 0 | I80: 0 | J80: 0 | K80: 0 | L80: 23 | M80: 53 | N80: 16 | O80: 87 | P80: 24 | Q80: 171 | R80: 53 | S80: 227 | T80: 108 | U80: 386 | V80: 204 | W80: 561 | X80: 318 | Y80: 939 | Z80: 568 | AA80: 1660 | AB80: 756 | AC80: 1898 | AD80: 854 | AE80: 1895 | AF80: 903 | AG80: 1722 | AH80: 895 | AI80: 1582 | AJ80: 583 | AK80: 1152 | AL80: 539 | AM80: 1099 | AN80: 18238
B81: TÉCNICO PARAMÉDICO | C81: 72 | D81: 21 | E81: 51 | F81: 0 | G81: 0 | H81: 0 | I81: 0 | J81: 0 | K81: 0 | L81: 0 | M81: 0 | N81: 0 | O81: 0 | P81: 1 | Q81: 2 | R81: 1 | S81: 0 | T81: 0 | U81: 2 | V81: 0 | W81: 0 | X81: 0 | Y81: 1 | Z81: 1 | AA81: 3 | AB81: 2 | AC81: 0 | AD81: 1 | AE81: 4 | AF81: 3 | AG81: 5 | AH81: 2 | AI81: 6 | AJ81: 3 | AK81: 13 | AL81: 7 | AM81: 15 | AN81: 64
A82: DE TUBERCULOSIS | B82: MÉDICO | C82: 753 | D82: 428 | E82: 325 | F82: 13 | G82: 8 | H82: 22 | I82: 9 | J82: 7 | K82: 7 | L82: 12 | M82: 13 | N82: 37 | O82: 30 | P82: 38 | Q82: 32 | R82: 17 | S82: 21 | T82: 37 | U82: 17 | V82: 26 | W82: 27 | X82: 37 | Y82: 19 | Z82: 19 | AA82: 27 | AB82: 31 | AC82: 25 | AD82: 46 | AE82: 22 | AF82: 21 | AG82: 25 | AH82: 21 | AI82: 29 | AJ82: 24 | AK82: 6 | AL82: 20 | AM82: 8 | AN82: 746
B83: ENFERMERA /O | C83: 253 | D83: 150 | E83: 103 | F83: 5 | G83: 4 | H83: 3 | I83: 2 | J83: 4 | K83: 2 | L83: 4 | M83: 5 | N83: 13 | O83: 7 | P83: 15 | Q83: 6 | R83: 11 | S83: 16 | T83: 11 | U83: 2 | V83: 14 | W83: 14 | X83: 12 | Y83: 7 | Z83: 12 | AA83: 8 | AB83: 18 | AC83: 5 | AD83: 10 | AE83: 3 | AF83: 2 | AG83: 6 | AH83: 8 | AI83: 12 | AJ83: 3 | AK83: 4 | AL83: 5 | AM83: 0 | AN83: 249
A84: SEGUIMIENTO AUTOVALENTE CON RIESGO | B84: MÉDICO | C84: 40 | D84: 27 | E84: 13 | F84: 0 | G84: 0 | H84: 0 | I84: 0 | J84: 0 | K84: 0 | L84: 0 | M84: 0 | N84: 0 | O84: 0 | P84: 0 | Q84: 0 | R84: 0 | S84: 0 | T84: 0 | U84: 0 | V84: 0 | W84: 0 | X84: 0 | Y84: 0 | Z84: 0 | AA84: 0 | AB84: 0 | AC84: 0 | AD84: 0 | AE84: 0 | AF84: 16 | AG84: 1 | AH84: 3 | AI84: 2 | AJ84: 4 | AK84: 3 | AL84: 4 | AM84: 7 | AN84: 40
B85: ENFERMERA /O | C85: 1818 | D85: 663 | E85: 1155 | F85: 0 | G85: 0 | H85: 0 | I85: 0 | J85: 0 | K85: 0 | L85: 0 | M85: 0 | N85: 0 | O85: 0 | P85: 0 | Q85: 0 | R85: 0 | S85: 0 | T85: 0 | U85: 0 | V85: 0 | W85: 0 | X85: 0 | Y85: 0 | Z85: 0 | AA85: 0 | AB85: 0 | AC85: 0 | AD85: 0 | AE85: 0 | AF85: 190 | AG85: 325 | AH85: 183 | AI85: 343 | AJ85: 161 | AK85: 265 | AL85: 129 | AM85: 222 | AN85: 1782
A86: SEGUIMIENTO RIESGO DEPENDENCIA | B86: MÉDICO | C86: 10 | D86: 3 | E86: 7 | F86: 0 | G86: 0 | H86: 0 | I86: 0 | J86: 0 | K86: 0 | L86: 0 | M86: 0 | N86: 0 | O86: 0 | P86: 0 | Q86: 0 | R86: 0 | S86: 0 | T86: 0 | U86: 0 | V86: 0 | W86: 0 | X86: 0 | Y86: 0 | Z86: 0 | AA86: 0 | AB86: 0 | AC86: 0 | AD86: 0 | AE86: 0 | AF86: 1 | AG86: 0 | AH86: 1 | AI86: 0 | AJ86: 0 | AK86: 1 | AL86: 1 | AM86: 6 | AN86: 10
B87: ENFERMERA /O | C87: 1089 | D87: 344 | E87: 745 | F87: 0 | G87: 0 | H87: 0 | I87: 0 | J87: 0 | K87: 0 | L87: 0 | M87: 0 | N87: 0 | O87: 0 | P87: 0 | Q87: 0 | R87: 0 | S87: 0 | T87: 0 | U87: 0 | V87: 0 | W87: 0 | X87: 0 | Y87: 0 | Z87: 0 | AA87: 0 | AB87: 0 | AC87: 0 | AD87: 0 | AE87: 0 | AF87: 48 | AG87: 84 | AH87: 59 | AI87: 150 | AJ87: 73 | AK87: 147 | AL87: 164 | AM87: 364 | AN87: 1068
A88: DE INFECCIÓN TRANSMISIÓN SEXUAL | B88: MÉDICO | C88: 29 | D88: 17 | E88: 12 | F88: 0 | G88: 0 | H88: 1 | I88: 0 | J88: 1 | K88: 1 | L88: 3 | M88: 3 | N88: 3 | O88: 1 | P88: 2 | Q88: 2 | R88: 3 | S88: 2 | T88: 0 | U88: 1 | V88: 1 | W88: 1 | X88: 0 | Y88: 1 | Z88: 1 | AA88: 0 | AB88: 1 | AC88: 0 | AD88: 0 | AE88: 0 | AF88: 0 | AG88: 0 | AH88: 0 | AI88: 0 | AJ88: 0 | AK88: 0 | AL88: 1 | AM88: 0 | AN88: 24
B89: ENFERMERA /O | C89: 10 | D89: 4 | E89: 6 | F89: 1 | G89: 1 | H89: 0 | I89: 0 | J89: 0 | K89: 1 | L89: 0 | M89: 0 | N89: 0 | O89: 0 | P89: 0 | Q89: 3 | R89: 0 | S89: 0 | T89: 1 | U89: 0 | V89: 0 | W89: 1 | X89: 0 | Y89: 0 | Z89: 0 | AA89: 0 | AB89: 0 | AC89: 0 | AD89: 0 | AE89: 0 | AF89: 0 | AG89: 0 | AH89: 0 | AI89: 0 | AJ89: 2 | AK89: 0 | AL89: 0 | AM89: 0 | AN89: 10
B90: MATRONA /ÓN | C90: 313 | D90: 92 | E90: 221 | F90: 0 | G90: 0 | H90: 0 | I90: 0 | J90: 0 | K90: 2 | L90: 22 | M90: 20 | N90: 15 | O90: 84 | P90: 12 | Q90: 45 | R90: 3 | S90: 23 | T90: 5 | U90: 14 | V90: 2 | W90: 11 | X90: 3 | Y90: 9 | Z90: 2 | AA90: 1 | AB90: 18 | AC90: 3 | AD90: 2 | AE90: 6 | AF90: 0 | AG90: 0 | AH90: 2 | AI90: 1 | AJ90: 4 | AK90: 2 | AL90: 2 | AM90: 0 | AN90: 310
A91: OTROS PROBLEMAS DE SALUD | B91: MÉDICO | C91: 44760 | D91: 11935 | E91: 32825 | F91: 198 | G91: 180 | H91: 137 | I91: 159 | J91: 156 | K91: 192 | L91: 165 | M91: 258 | N91: 170 | O91: 443 | P91: 189 | Q91: 532 | R91: 218 | S91: 677 | T91: 214 | U91: 860 | V91: 267 | W91: 1157 | X91: 472 | Y91: 1796 | Z91: 849 | AA91: 2772 | AB91: 1257 | AC91: 3601 | AD91: 1322 | AE91: 4230 | AF91: 1542 | AG91: 4182 | AH91: 1653 | AI91: 4232 | AJ91: 1363 | AK91: 3456 | AL91: 1763 | AM91: 4098 | AN91: 41777
B92: ENFERMERA /O | C92: 5730 | D92: 2318 | E92: 3412 | F92: 1 | G92: 0 | H92: 4 | I92: 3 | J92: 6 | K92: 2 | L92: 16 | M92: 7 | N92: 22 | O92: 54 | P92: 5 | Q92: 38 | R92: 44 | S92: 65 | T92: 8 | U92: 73 | V92: 43 | W92: 65 | X92: 132 | Y92: 239 | Z92: 256 | AA92: 366 | AB92: 449 | AC92: 249 | AD92: 213 | AE92: 372 | AF92: 293 | AG92: 440 | AH92: 355 | AI92: 619 | AJ92: 142 | AK92: 436 | AL92: 329 | AM92: 384 | AN92: 5520
B93: MATRONA /ÓN | C93: 151 | D93: 20 | E93: 131 | F93: 14 | G93: 17 | H93: 2 | I93: 3 | J93: 1 | K93: 4 | L93: 0 | M93: 13 | N93: 0 | O93: 28 | P93: 0 | Q93: 17 | R93: 1 | S93: 27 | T93: 1 | U93: 14 | V93: 0 | W93: 1 | X93: 0 | Y93: 0 | Z93: 1 | AA93: 2 | AB93: 0 | AC93: 0 | AD93: 0 | AE93: 2 | AF93: 0 | AG93: 1 | AH93: 0 | AI93: 1 | AJ93: 0 | AK93: 1 | AL93: 0 | AM93: 0 | AN93: 151
B94: NUTRICIONISTA | C94: 8616 | D94: 3171 | E94: 5445 | F94: 1860 | G94: 1693 | H94: 485 | I94: 495 | J94: 121 | K94: 135 | L94: 39 | M94: 192 | N94: 24 | O94: 281 | P94: 21 | Q94: 345 | R94: 34 | S94: 279 | T94: 24 | U94: 234 | V94: 29 | W94: 210 | X94: 37 | Y94: 223 | Z94: 57 | AA94: 238 | AB94: 97 | AC94: 262 | AD94: 69 | AE94: 225 | AF94: 55 | AG94: 193 | AH94: 76 | AI94: 170 | AJ94: 66 | AK94: 133 | AL94: 77 | AM94: 137 | AN94: 8480
B95: TÉCNICO PARAMÉDICO | C95: 2538 | D95: 1410 | E95: 1128 | F95: 49 | G95: 52 | H95: 25 | I95: 79 | J95: 29 | K95: 25 | L95: 23 | M95: 31 | N95: 26 | O95: 66 | P95: 16 | Q95: 18 | R95: 14 | S95: 42 | T95: 14 | U95: 42 | V95: 47 | W95: 21 | X95: 122 | Y95: 125 | Z95: 228 | AA95: 192 | AB95: 228 | AC95: 20 | AD95: 129 | AE95: 123 | AF95: 152 | AG95: 45 | AH95: 166 | AI95: 165 | AJ95: 9 | AK95: 58 | AL95: 133 | AM95: 24 | AN95: 2497
A96: NIÑOS CON NECESIDADES ESPECIALES | B96: MÉDICO | C96: 468 | D96: 316 | E96: 152 | F96: 200 | G96: 78 | H96: 83 | I96: 44 | J96: 20 | K96: 18 | L96: 13 | M96: 10 | N96: 0 | O96: 2 | P96: 0 | Q96: 0 | R96: 0 | S96: 0 | T96: 0 | U96: 0 | V96: 0 | W96: 0 | X96: 0 | Y96: 0 | Z96: 0 | AA96: 0 | AB96: 0 | AC96: 0 | AD96: 0 | AE96: 0 | AF96: 0 | AG96: 0 | AH96: 0 | AI96: 0 | AJ96: 0 | AK96: 0 | AL96: 0 | AM96: 0 | AN96: 340
B97: ENFERMERA /O | C97: 119 | D97: 75 | E97: 44 | F97: 58 | G97: 35 | H97: 13 | I97: 5 | J97: 1 | K97: 3 | L97: 1 | M97: 0 | N97: 2 | O97: 1 | P97: 0 | Q97: 0 | R97: 0 | S97: 0 | T97: 0 | U97: 0 | V97: 0 | W97: 0 | X97: 0 | Y97: 0 | Z97: 0 | AA97: 0 | AB97: 0 | AC97: 0 | AD97: 0 | AE97: 0 | AF97: 0 | AG97: 0 | AH97: 0 | AI97: 0 | AJ97: 0 | AK97: 0 | AL97: 0 | AM97: 0 | AN97: 108
B98: MATRONA /ÓN | C98: 0 | D98: 0 | E98: 0 | F98: 0 | G98: 0 | H98: 0 | I98: 0 | J98: 0 | K98: 0 | L98: 0 | M98: 0 | N98: 0 | O98: 0 | P98: 0 | Q98: 0 | R98: 0 | S98: 0 | T98: 0 | U98: 0 | V98: 0 | W98: 0 | X98: 0 | Y98: 0 | Z98: 0 | AA98: 0 | AB98: 0 | AC98: 0 | AD98: 0 | AE98: 0 | AF98: 0 | AG98: 0 | AH98: 0 | AI98: 0 | AJ98: 0 | AK98: 0 | AL98: 0 | AM98: 0 | AN98: 0
B99: NUTRICIONISTA | C99: 60 | D99: 43 | E99: 17 | F99: 35 | G99: 17 | H99: 6 | I99: 0 | J99: 1 | K99: 0 | L99: 1 | M99: 0 | N99: 0 | O99: 0 | P99: 0 | Q99: 0 | R99: 0 | S99: 0 | T99: 0 | U99: 0 | V99: 0 | W99: 0 | X99: 0 | Y99: 0 | Z99: 0 | AA99: 0 | AB99: 0 | AC99: 0 | AD99: 0 | AE99: 0 | AF99: 0 | AG99: 0 | AH99: 0 | AI99: 0 | AJ99: 0 | AK99: 0 | AL99: 0 | AM99: 0 | AN99: 60
B100: TÉCNICO PARAMÉDICO | C100: 3 | D100: 1 | E100: 2 | F100: 0 | G100: 0 | H100: 0 | I100: 0 | J100: 0 | K100: 0 | L100: 1 | M100: 0 | N100: 0 | O100: 2 | P100: 0 | Q100: 0 | R100: 0 | S100: 0 | T100: 0 | U100: 0 | V100: 0 | W100: 0 | X100: 0 | Y100: 0 | Z100: 0 | AA100: 0 | AB100: 0 | AC100: 0 | AD100: 0 | AE100: 0 | AF100: 0 | AG100: 0 | AH100: 0 | AI100: 0 | AJ100: 0 | AK100: 0 | AL100: 0 | AM100: 0 | AN100: 2
...

Sheet Hoja 21
A1: 2019 [ Enero - Diciembre ]
A2: TIPO DE CONTROL | B2: PROFESIONAL | C2: TOTAL | F2: POR EDAD | AN2: BENEFICIARIOS
F3: 0 - 4 | H3: 45905 | J3: 45944 | L3: 15 - 19 | N3: 20 - 24 | P3: 25 - 29 | R3: 30 - 34 | T3: 35 - 39 | V3: 40 - 44 | X3: 45 - 49 | Z3: 50 - 54 | AB3: 55 - 59 | AD3: 60 - 64 | AF3: 65 - 69 | AH3: 70 - 74 | AJ3: 75 - 79 | AL3: 80 y mas
C4: Ambos Sexos | D4: Hombres | E4: Mujeres | F4: Hombres | G4: Mujeres | H4: Hombres | I4: Mujeres | J4: Hombres | K4: Mujeres | L4: Hombres | M4: Mujeres | N4: Hombres | O4: Mujeres | P4: Hombres | Q4: Mujeres | R4: Hombres | S4: Mujeres | T4: Hombres | U4: Mujeres | V4: Hombres | W4: Mujeres | X4: Hombres | Y4: Mujeres | Z4: Hombres | AA4: Mujeres | AB4: Hombres | AC4: Mujeres | AD4: Hombres | AE4: Mujeres | AF4: Hombres | AG4: Mujeres | AH4: Hombres | AI4: Mujeres | AJ4: Hombres | AK4: Mujeres | AL4: Hombres | AM4: Mujeres
A5: Acumulado Pais
A6: DE SALUD CARDIOVASCULAR | B6: MÉDICO | C6: 5560806 | D6: 2028288 | E6: 3532518 | F6: 0 | G6: 0 | H6: 0 | I6: 0 | J6: 0 | K6: 0 | L6: 3420 | M6: 5474 | N6: 5372 | O6: 11148 | P6: 10606 | Q6: 23416 | R6: 18742 | S6: 40896 | T6: 32792 | U6: 70270 | V6: 58130 | W6: 123432 | X6: 99908 | Y6: 216302 | Z6: 171414 | AA6: 359746 | AB6: 246160 | AC6: 458110 | AD6: 284092 | AE6: 491396 | AF6: 308114 | AG6: 488696 | AH6: 302838 | AI6: 455722 | AJ6: 239446 | AK6: 364440 | AL6: 247242 | AM6: 423482 | AN6: 5514534
B7: ENFERMERA /O | C7: 2552008 | D7: 929456 | E7: 1622538 | F7: 0 | G7: 0 | H7: 0 | I7: 0 | J7: 0 | K7: 0 | L7: 816 | M7: 1124 | N7: 1696 | O7: 3084 | P7: 3412 | Q7: 7360 | R7: 6760 | S7: 14006 | T7: 12328 | U7: 25430 | V7: 22200 | W7: 47916 | X7: 39650 | Y7: 88702 | Z7: 71416 | AA7: 152756 | AB7: 103670 | AC7: 199500 | AD7: 124550 | AE7: 221482 | AF7: 145756 | AG7: 238574 | AH7: 150220 | AI7: 226788 | AJ7: 121274 | AK7: 182332 | AL7: 125710 | AM7: 213494 | AN7: 2527630
B8: NUTRICIONISTA | C8: 2174036 | D8: 747376 | E8: 1426660 | F8: 0 | G8: 0 | H8: 0 | I8: 0 | J8: 0 | K8: 0 | L8: 1460 | M8: 2504 | N8: 2264 | O8: 5538 | P8: 4542 | Q8: 11290 | R8: 7562 | S8: 18468 | T8: 12878 | U8: 31074 | V8: 23062 | W8: 53984 | X8: 38286 | Y8: 93852 | Z8: 65014 | AA8: 152416 | AB8: 90220 | AC8: 190922 | AD8: 103108 | AE8: 200262 | AF8: 112404 | AG8: 197636 | AH8: 112846 | AI8: 182184 | AJ8: 88888 | AK8: 139280 | AL8: 84832 | AM8: 147240 | AN8: 2150452
B9: TÉCNICO PARAMÉDICO | C9: 179088 | D9: 67332 | E9: 111756 | F9: 0 | G9: 0 | H9: 0 | I9: 0 | J9: 0 | K9: 0 | L9: 246 | M9: 314 | N9: 326 | O9: 632 | P9: 572 | Q9: 1150 | R9: 912 | S9: 1884 | T9: 1544 | U9: 2702 | V9: 2044 | W9: 4648 | X9: 3456 | Y9: 7458 | Z9: 5956 | AA9: 12138 | AB9: 7846 | AC9: 14410 | AD9: 8840 | AE9: 14944 | AF9: 9426 | AG9: 15202 | AH9: 10276 | AI9: 13518 | AJ9: 7206 | AK9: 10096 | AL9: 8682 | AM9: 12658 | AN9: 177438
A10: DE TUBERCULOSIS | B10: MÉDICO | C10: 25396 | D10: 14158 | E10: 11238 | F10: 386 | G10: 352 | H10: 384 | I10: 378 | J10: 324 | K10: 256 | L10: 386 | M10: 456 | N10: 1046 | O10: 818 | P10: 1320 | Q10: 1050 | R10: 1278 | S10: 944 | T10: 1230 | U10: 780 | V10: 958 | W10: 704 | X10: 1054 | Y10: 740 | Z10: 1244 | AA10: 866 | AB10: 1086 | AC10: 828 | AD10: 1056 | AE10: 790 | AF10: 758 | AG10: 602 | AH10: 554 | AI10: 588 | AJ10: 534 | AK10: 402 | AL10: 560 | AM10: 684 | AN10: 24424
B11: ENFERMERA /O | C11: 20892 | D11: 11632 | E11: 9260 | F11: 400 | G11: 360 | H11: 316 | I11: 336 | J11: 290 | K11: 418 | L11: 242 | M11: 252 | N11: 766 | O11: 714 | P11: 832 | Q11: 918 | R11: 1332 | S11: 1148 | T11: 1300 | U11: 724 | V11: 730 | W11: 514 | X11: 912 | Y11: 610 | Z11: 1116 | AA11: 728 | AB11: 1046 | AC11: 550 | AD11: 864 | AE11: 304 | AF11: 566 | AG11: 426 | AH11: 320 | AI11: 562 | AJ11: 330 | AK11: 178 | AL11: 270 | AM11: 518 | AN11: 20450
A12: SEGUIMIENTO AUTOVALENTE CON RIESGO | B12: MÉDICO | C12: 6958 | D12: 2932 | E12: 4026 | F12: 0 | G12: 0 | H12: 0 | I12: 0 | J12: 0 | K12: 0 | L12: 0 | M12: 0 | N12: 0 | O12: 0 | P12: 0 | Q12: 0 | R12: 0 | S12: 0 | T12: 0 | U12: 0 | V12: 0 | W12: 0 | X12: 0 | Y12: 0 | Z12: 0 | AA12: 0 | AB12: 0 | AC12: 0 | AD12: 0 | AE12: 0 | AF12: 684 | AG12: 982 | AH12: 822 | AI12: 1046 | AJ12: 640 | AK12: 864 | AL12: 786 | AM12: 1134 | AN12: 6934
B13: ENFERMERA /O | C13: 57010 | D13: 21018 | E13: 36024 | F13: 0 | G13: 0 | H13: 0 | I13: 0 | J13: 0 | K13: 0 | L13: 0 | M13: 0 | N13: 0 | O13: 0 | P13: 0 | Q13: 0 | R13: 0 | S13: 0 | T13: 0 | U13: 0 | V13: 0 | W13: 0 | X13: 0 | Y13: 0 | Z13: 0 | AA13: 0 | AB13: 0 | AC13: 0 | AD13: 0 | AE13: 0 | AF13: 5496 | AG13: 10298 | AH13: 6222 | AI13: 10438 | AJ13: 5112 | AK13: 8188 | AL13: 4156 | AM13: 7100 | AN13: 56536
A14: SEGUIMIENTO RIESGO DEPENDENCIA | B14: MÉDICO | C14: 1808 | D14: 682 | E14: 1126 | F14: 0 | G14: 0 | H14: 0 | I14: 0 | J14: 0 | K14: 0 | L14: 0 | M14: 0 | N14: 0 | O14: 0 | P14: 0 | Q14: 0 | R14: 0 | S14: 0 | T14: 0 | U14: 0 | V14: 0 | W14: 0 | X14: 0 | Y14: 0 | Z14: 0 | AA14: 0 | AB14: 0 | AC14: 0 | AD14: 0 | AE14: 0 | AF14: 110 | AG14: 132 | AH14: 140 | AI14: 184 | AJ14: 110 | AK14: 240 | AL14: 322 | AM14: 570 | AN14: 1796
B15: ENFERMERA /O | C15: 31190 | D15: 11056 | E15: 20134 | F15: 0 | G15: 0 | H15: 0 | I15: 0 | J15: 0 | K15: 0 | L15: 0 | M15: 0 | N15: 0 | O15: 0 | P15: 0 | Q15: 0 | R15: 0 | S15: 0 | T15: 0 | U15: 0 | V15: 0 | W15: 0 | X15: 0 | Y15: 0 | Z15: 0 | AA15: 0 | AB15: 0 | AC15: 0 | AD15: 0 | AE15: 0 | AF15: 1384 | AG15: 2500 | AH15: 2238 | AI15: 3720 | AJ15: 2560 | AK15: 4506 | AL15: 4874 | AM15: 9408 | AN15: 31018
A16: DE INFECCIÓN TRANSMISIÓN SEXUAL | B16: MÉDICO | C16: 5738 | D16: 1990 | E16: 3748 | F16: 58 | G16: 54 | H16: 34 | I16: 38 | J16: 28 | K16: 20 | L16: 96 | M16: 164 | N16: 166 | O16: 304 | P16: 162 | Q16: 234 | R16: 130 | S16: 246 | T16: 112 | U16: 194 | V16: 74 | W16: 180 | X16: 100 | Y16: 212 | Z16: 94 | AA16: 240 | AB16: 194 | AC16: 378 | AD16: 176 | AE16: 354 | AF16: 128 | AG16: 340 | AH16: 186 | AI16: 328 | AJ16: 142 | AK16: 228 | AL16: 110 | AM16: 234 | AN16: 5682
B17: ENFERMERA /O | C17: 1142 | D17: 418 | E17: 724 | F17: 34 | G17: 14 | H17: 4 | I17: 4 | J17: 8 | K17: 14 | L17: 14 | M17: 20 | N17: 2 | O17: 20 | P17: 10 | Q17: 18 | R17: 20 | S17: 20 | T17: 6 | U17: 30 | V17: 24 | W17: 26 | X17: 20 | Y17: 52 | Z17: 28 | AA17: 86 | AB17: 44 | AC17: 74 | AD17: 28 | AE17: 78 | AF17: 54 | AG17: 70 | AH17: 58 | AI17: 72 | AJ17: 30 | AK17: 60 | AL17: 34 | AM17: 66 | AN17: 1132
B18: MATRONA /ÓN | C18: 12438 | D18: 3024 | E18: 9414 | F18: 24 | G18: 82 | H18: 18 | I18: 30 | J18: 18 | K18: 60 | L18: 410 | M18: 1016 | N18: 674 | O18: 1660 | P18: 522 | Q18: 1506 | R18: 278 | S18: 1104 | T18: 172 | U18: 978 | V18: 160 | W18: 676 | X18: 102 | Y18: 614 | Z18: 184 | AA18: 518 | AB18: 102 | AC18: 414 | AD18: 104 | AE18: 228 | AF18: 80 | AG18: 164 | AH18: 68 | AI18: 134 | AJ18: 50 | AK18: 130 | AL18: 58 | AM18: 100 | AN18: 12236
A19: OTROS PROBLEMAS DE SALUD | B19: MÉDICO | C19: 1418278 | D19: 382710 | E19: 1035568 | F19: 15416 | G19: 12468 | H19: 10600 | I19: 8826 | J19: 10206 | K19: 9400 | L19: 9128 | M19: 15408 | N19: 6876 | O19: 19188 | P19: 7712 | Q19: 27516 | R19: 8532 | S19: 32870 | T19: 9546 | U19: 39546 | V19: 11556 | W19: 49384 | X19: 16534 | Y19: 67974 | Z19: 25994 | AA19: 95622 | AB19: 34360 | AC19: 120644 | AD19: 40350 | AE19: 124262 | AF19: 43736 | AG19: 120472 | AH19: 46510 | AI19: 109316 | AJ19: 39754 | AK19: 84386 | AL19: 45914 | AM19: 98272 | AN19: 1402082
B20: ENFERMERA /O | C20: 170578 | D20: 59512 | E20: 111066 | F20: 2488 | G20: 2138 | H20: 990 | I20: 876 | J20: 560 | K20: 542 | L20: 502 | M20: 850 | N20: 798 | O20: 1316 | P20: 732 | Q20: 1834 | R20: 1000 | S20: 2198 | T20: 1178 | U20: 3026 | V20: 1440 | W20: 4042 | X20: 2760 | Y20: 6810 | Z20: 4374 | AA20: 10324 | AB20: 4984 | AC20: 11178 | AD20: 6144 | AE20: 12538 | AF20: 7192 | AG20: 14778 | AH20: 9082 | AI20: 14214 | AJ20: 7058 | AK20: 10546 | AL20: 8230 | AM20: 13856 | AN20: 168012
B21: MATRONA /ÓN | C21: 25018 | D21: 1962 | E21: 23056 | F21: 900 | G21: 900 | H21: 64 | I21: 100 | J21: 114 | K21: 376 | L21: 164 | M21: 1086 | N21: 52 | O21: 1406 | P21: 44 | Q21: 2010 | R21: 68 | S21: 1546 | T21: 96 | U21: 1328 | V21: 34 | W21: 1644 | X21: 40 | Y21: 1886 | Z21: 56 | AA21: 2036 | AB21: 52 | AC21: 2298 | AD21: 58 | AE21: 2282 | AF21: 86 | AG21: 1698 | AH21: 60 | AI21: 1308 | AJ21: 36 | AK21: 742 | AL21: 38 | AM21: 410 | AN21: 24844
B22: NUTRICIONISTA | C22: 229174 | D22: 75734 | E22: 153440 | F22: 30506 | G22: 29254 | H22: 8550 | I22: 9428 | J22: 4066 | K22: 4602 | L22: 1842 | M22: 6428 | N22: 1020 | O22: 7414 | P22: 1164 | Q22: 9352 | R22: 1248 | S22: 8600 | T22: 1248 | U22: 7530 | V22: 1496 | W22: 7366 | X22: 1908 | Y22: 7918 | Z22: 2490 | AA22: 9702 | AB22: 3018 | AC22: 10244 | AD22: 3334 | AE22: 9032 | AF22: 3954 | AG22: 8844 | AH22: 3938 | AI22: 7086 | AJ22: 2786 | AK22: 5108 | AL22: 3166 | AM22: 5532 | AN22: 224632
B23: TÉCNICO PARAMÉDICO | C23: 130332 | D23: 52804 | E23: 77528 | F23: 2342 | G23: 2512 | H23: 1956 | I23: 1950 | J23: 2036 | K23: 2264 | L23: 1506 | M23: 3562 | N23: 1698 | O23: 3822 | P23: 1982 | Q23: 4644 | R23: 1832 | S23: 4594 | T23: 1836 | U23: 4792 | V23: 2330 | W23: 4810 | X23: 3122 | Y23: 5356 | Z23: 4106 | AA23: 6406 | AB23: 4350 | AC23: 6152 | AD23: 4588 | AE23: 5704 | AF23: 4164 | AG23: 5624 | AH23: 5750 | AI23: 4510 | AJ23: 4024 | AK23: 4818 | AL23: 5156 | AM23: 6034 | AN23: 128150
A24: NIÑOS CON NECESIDADES ESPECIALES | B24: MÉDICO | C24: 5360 | D24: 3178 | E24: 2182 | F24: 1974 | G24: 1370 | H24: 706 | I24: 386 | J24: 406 | K24: 304 | L24: 74 | M24: 100 | N24: 18 | O24: 22 | P24: 0 | Q24: 0 | R24: 0 | S24: 0 | T24: 0 | U24: 8 | V24: 0 | W24: 0 | X24: 0 | Y24: 0 | Z24: 0 | AA24: 0 | AB24: 0 | AC24: 0 | AD24: 0 | AE24: 0 | AF24: 0 | AG24: 0 | AH24: 0 | AI24: 0 | AJ24: 0 | AK24: 0 | AL24: 0 | AM24: 0 | AN24: 4994
B25: ENFERMERA /O | C25: 9058 | D25: 5168 | E25: 3890 | F25: 4170 | G25: 3254 | H25: 820 | I25: 486 | J25: 130 | K25: 90 | L25: 28 | M25: 44 | N25: 20 | O25: 16 | P25: 0 | Q25: 0 | R25: 0 | S25: 0 | T25: 0 | U25: 8 | V25: 0 | W25: 0 | X25: 0 | Y25: 0 | Z25: 0 | AA25: 0 | AB25: 0 | AC25: 0 | AD25: 0 | AE25: 0 | AF25: 0 | AG25: 0 | AH25: 0 | AI25: 0 | AJ25: 0 | AK25: 0 | AL25: 0 | AM25: 0 | AN25: 8696
B26: MATRONA /ÓN | C26: 526 | D26: 164 | E26: 362 | F26: 62 | G26: 86 | H26: 10 | I26: 2 | J26: 48 | K26: 86 | L26: 34 | M26: 114 | N26: 10 | O26: 74 | P26: 0 | Q26: 0 | R26: 0 | S26: 0 | T26: 0 | U26: 8 | V26: 0 | W26: 0 | X26: 0 | Y26: 0 | Z26: 0 | AA26: 0 | AB26: 0 | AC26: 0 | AD26: 0 | AE26: 0 | AF26: 0 | AG26: 0 | AH26: 0 | AI26: 0 | AJ26: 0 | AK26: 0 | AL26: 0 | AM26: 0 | AN26: 512
B27: NUTRICIONISTA | C27: 5272 | D27: 2832 | E27: 2440 | F27: 2186 | G27: 1870 | H27: 424 | I27: 312 | J27: 150 | K27: 128 | L27: 46 | M27: 88 | N27: 26 | O27: 42 | P27: 0 | Q27: 0 | R27: 0 | S27: 0 | T27: 0 | U27: 8 | V27: 0 | W27: 0 | X27: 0 | Y27: 0 | Z27: 0 | AA27: 0 | AB27: 0 | AC27: 0 | AD27: 0 | AE27: 0 | AF27: 0 | AG27: 0 | AH27: 0 | AI27: 0 | AJ27: 0 | AK27: 0 | AL27: 0 | AM27: 0 | AN27: 5142
B28: TÉCNICO PARAMÉDICO | C28: 230 | D28: 112 | E28: 118 | F28: 50 | G28: 26 | H28: 24 | I28: 32 | J28: 10 | K28: 32 | L28: 22 | M28: 28 | N28: 6 | O28: 0 | P28: 0 | Q28: 0 | R28: 0 | S28: 0 | T28: 0 | U28: 8 | V28: 0 | W28: 0 | X28: 0 | Y28: 0 | Z28: 0 | AA28: 0 | AB28: 0 | AC28: 0 | AD28: 0 | AE28: 0 | AF28: 0 | AG28: 0 | AH28: 0 | AI28: 0 | AJ28: 0 | AK28: 0 | AL28: 0 | AM28: 0 | AN28: 230
A29: Servicio: Servicio de Salud Arica
A30: DE SALUD CARDIOVASCULAR | B30: MÉDICO | C30: 35780 | D30: 13232 | E30: 22548 | F30: 0 | G30: 0 | H30: 0 | I30: 0 | J30: 0 | K30: 0 | L30: 8 | M30: 30 | N30: 28 | O30: 36 | P30: 46 | Q30: 90 | R30: 112 | S30: 172 | T30: 164 | U30: 366 | V30: 272 | W30: 636 | X30: 558 | Y30: 1034 | Z30: 898 | AA30: 1866 | AB30: 1356 | AC30: 2678 | AD30: 1814 | AE30: 3096 | AF30: 2028 | AG30: 3420 | AH30: 2298 | AI30: 3518 | AJ30: 1864 | AK30: 2632 | AL30: 1786 | AM30: 2974 | AN30: 35742
B31: ENFERMERA /O | C31: 32000 | D31: 12810 | E31: 19190 | F31: 0 | G31: 0 | H31: 0 | I31: 0 | J31: 0 | K31: 0 | L31: 10 | M31: 10 | N31: 34 | O31: 40 | P31: 76 | Q31: 44 | R31: 106 | S31: 178 | T31: 216 | U31: 372 | V31: 308 | W31: 498 | X31: 590 | Y31: 1040 | Z31: 888 | AA31: 1522 | AB31: 1400 | AC31: 2218 | AD31: 1754 | AE31: 2516 | AF31: 1828 | AG31: 2866 | AH31: 2182 | AI31: 2796 | AJ31: 1748 | AK31: 2200 | AL31: 1670 | AM31: 2890 | AN31: 31980
B32: NUTRICIONISTA | C32: 18706 | D32: 6822 | E32: 11884 | F32: 0 | G32: 0 | H32: 0 | I32: 0 | J32: 0 | K32: 0 | L32: 8 | M32: 2 | N32: 24 | O32: 22 | P32: 48 | Q32: 42 | R32: 44 | S32: 78 | T32: 88 | U32: 174 | V32: 136 | W32: 330 | X32: 248 | Y32: 576 | Z32: 520 | AA32: 946 | AB32: 648 | AC32: 1412 | AD32: 854 | AE32: 1590 | AF32: 1024 | AG32: 1740 | AH32: 1258 | AI32: 1844 | AJ32: 998 | AK32: 1484 | AL32: 924 | AM32: 1644 | AN32: 18702
B33: TÉCNICO PARAMÉDICO | C33: 634 | D33: 266 | E33: 368 | F33: 0 | G33: 0 | H33: 0 | I33: 0 | J33: 0 | K33: 0 | L33: 0 | M33: 0 | N33: 2 | O33: 0 | P33: 0 | Q33: 2 | R33: 12 | S33: 4 | T33: 2 | U33: 6 | V33: 8 | W33: 22 | X33: 24 | Y33: 26 | Z33: 22 | AA33: 36 | AB33: 48 | AC33: 28 | AD33: 38 | AE33: 36 | AF33: 16 | AG33: 34 | AH33: 18 | AI33: 90 | AJ33: 72 | AK33: 40 | AL33: 4 | AM33: 44 | AN33: 620
A34: DE TUBERCULOSIS | B34: MÉDICO | C34: 944 | D34: 572 | E34: 372 | F34: 4 | G34: 4 | H34: 2 | I34: 0 | J34: 4 | K34: 6 | L34: 32 | M34: 14 | N34: 46 | O34: 40 | P34: 88 | Q34: 30 | R34: 52 | S34: 36 | T34: 60 | U34: 40 | V34: 48 | W34: 20 | X34: 42 | Y34: 24 | Z34: 58 | AA34: 62 | AB34: 48 | AC34: 18 | AD34: 10 | AE34: 10 | AF34: 56 | AG34: 30 | AH34: 10 | AI34: 4 | AJ34: 8 | AK34: 8 | AL34: 4 | AM34: 26 | AN34: 944
B35: ENFERMERA /O | C35: 540 | D35: 306 | E35: 234 | F35: 4 | G35: 2 | H35: 4 | I35: 4 | J35: 2 | K35: 8 | L35: 6 | M35: 4 | N35: 20 | O35: 10 | P35: 46 | Q35: 20 | R35: 20 | S35: 34 | T35: 26 | U35: 24 | V35: 38 | W35: 10 | X35: 18 | Y35: 22 | Z35: 20 | AA35: 22 | AB35: 24 | AC35: 6 | AD35: 28 | AE35: 22 | AF35: 36 | AG35: 10 | AH35: 6 | AI35: 8 | AJ35: 4 | AK35: 4 | AL35: 4 | AM35: 24 | AN35: 540
A36: SEGUIMIENTO AUTOVALENTE CON RIESGO | B36: MÉDICO | C36: 682 | D36: 282 | E36: 400 | F36: 0 | G36: 0 | H36: 0 | I36: 0 | J36: 0 | K36: 0 | L36: 0 | M36: 0 | N36: 0 | O36: 0 | P36: 0 | Q36: 0 | R36: 0 | S36: 0 | T36: 0 | U36: 0 | V36: 0 | W36: 0 | X36: 0 | Y36: 0 | Z36: 0 | AA36: 0 | AB36: 0 | AC36: 0 | AD36: 0 | AE36: 0 | AF36: 44 | AG36: 96 | AH36: 86 | AI36: 114 | AJ36: 88 | AK36: 88 | AL36: 64 | AM36: 102 | AN36: 680
B37: ENFERMERA /O | C37: 352 | D37: 116 | E37: 236 | F37: 0 | G37: 0 | H37: 0 | I37: 0 | J37: 0 | K37: 0 | L37: 0 | M37: 0 | N37: 0 | O37: 0 | P37: 0 | Q37: 0 | R37: 0 | S37: 0 | T37: 0 | U37: 0 | V37: 0 | W37: 0 | X37: 0 | Y37: 0 | Z37: 0 | AA37: 0 | AB37: 0 | AC37: 0 | AD37: 0 | AE37: 0 | AF37: 18 | AG37: 72 | AH37: 56 | AI37: 64 | AJ37: 24 | AK37: 56 | AL37: 18 | AM37: 44 | AN37: 352
A38: SEGUIMIENTO RIESGO DEPENDENCIA | B38: MÉDICO | C38: 254 | D38: 90 | E38: 164 | F38: 0 | G38: 0 | H38: 0 | I38: 0 | J38: 0 | K38: 0 | L38: 0 | M38: 0 | N38: 0 | O38: 0 | P38: 0 | Q38: 0 | R38: 0 | S38: 0 | T38: 0 | U38: 0 | V38: 0 | W38: 0 | X38: 0 | Y38: 0 | Z38: 0 | AA38: 0 | AB38: 0 | AC38: 0 | AD38: 0 | AE38: 0 | AF38: 12 | AG38: 16 | AH38: 8 | AI38: 22 | AJ38: 16 | AK38: 46 | AL38: 54 | AM38: 80 | AN38: 254
B39: ENFERMERA /O | C39: 308 | D39: 98 | E39: 210 | F39: 0 | G39: 0 | H39: 0 | I39: 0 | J39: 0 | K39: 0 | L39: 0 | M39: 0 | N39: 0 | O39: 0 | P39: 0 | Q39: 0 | R39: 0 | S39: 0 | T39: 0 | U39: 0 | V39: 0 | W39: 0 | X39: 0 | Y39: 0 | Z39: 0 | AA39: 0 | AB39: 0 | AC39: 0 | AD39: 0 | AE39: 0 | AF39: 8 | AG39: 34 | AH39: 20 | AI39: 46 | AJ39: 34 | AK39: 38 | AL39: 36 | AM39: 92 | AN39: 308
A40: DE INFECCIÓN TRANSMISIÓN SEXUAL | B40: MÉDICO | C40: 2 | D40: 2 | E40: 0 | F40: 0 | G40: 0 | H40: 0 | I40: 0 | J40: 0 | K40: 0 | L40: 0 | M40: 0 | N40: 0 | O40: 0 | P40: 0 | Q40: 0 | R40: 2 | S40: 0 | T40: 0 | U40: 0 | V40: 0 | W40: 0 | X40: 0 | Y40: 0 | Z40: 0 | AA40: 0 | AB40: 0 | AC40: 0 | AD40: 0 | AE40: 0 | AF40: 0 | AG40: 0 | AH40: 0 | AI40: 0 | AJ40: 0 | AK40: 0 | AL40: 0 | AM40: 0 | AN40: 2
B41: ENFERMERA /O | C41: 0 | D41: 0 | E41: 0 | F41: 0 | G41: 0 | H41: 0 | I41: 0 | J41: 0 | K41: 0 | L41: 0 | M41: 0 | N41: 0 | O41: 0 | P41: 0 | Q41: 0 | R41: 0 | S41: 0 | T41: 0 | U41: 0 | V41: 0 | W41: 0 | X41: 0 | Y41: 0 | Z41: 0 | AA41: 0 | AB41: 0 | AC41: 0 | AD41: 0 | AE41: 0 | AF41: 0 | AG41: 0 | AH41: 0 | AI41: 0 | AJ41: 0 | AK41: 0 | AL41: 0 | AM41: 0 | AN41: 0
B42: MATRONA /ÓN | C42: 0 | D42: 0 | E42: 0 | F42: 0 | G42: 0 | H42: 0 | I42: 0 | J42: 0 | K42: 0 | L42: 0 | M42: 0 | N42: 0 | O42: 0 | P42: 0 | Q42: 0 | R42: 0 | S42: 0 | T42: 0 | U42: 0 | V42: 0 | W42: 0 | X42: 0 | Y42: 0 | Z42: 0 | AA42: 0 | AB42: 0 | AC42: 0 | AD42: 0 | AE42: 0 | AF42: 0 | AG42: 0 | AH42: 0 | AI42: 0 | AJ42: 0 | AK42: 0 | AL42: 0 | AM42: 0 | AN42: 0
A43: OTROS PROBLEMAS DE SALUD | B43: MÉDICO | C43: 36414 | D43: 11086 | E43: 25328 | F43: 32 | G43: 12 | H43: 256 | I43: 246 | J43: 668 | K43: 762 | L43: 690 | M43: 940 | N43: 506 | O43: 846 | P43: 382 | Q43: 752 | R43: 436 | S43: 934 | T43: 370 | U43: 1018 | V43: 272 | W43: 950 | X43: 394 | Y43: 1418 | Z43: 616 | AA43: 2062 | AB43: 980 | AC43: 2966 | AD43: 1270 | AE43: 2754 | AF43: 1172 | AG43: 2904 | AH43: 1192 | AI43: 2752 | AJ43: 992 | AK43: 2098 | AL43: 858 | AM43: 1914 | AN43: 36380
B44: ENFERMERA /O | C44: 372 | D44: 82 | E44: 290 | F44: 0 | G44: 4 | H44: 2 | I44: 2 | J44: 2 | K44: 0 | L44: 0 | M44: 0 | N44: 0 | O44: 0 | P44: 0 | Q44: 0 | R44: 0 | S44: 0 | T44: 2 | U44: 12 | V44: 0 | W44: 2 | X44: 0 | Y44: 8 | Z44: 6 | AA44: 20 | AB44: 2 | AC44: 16 | AD44: 10 | AE44: 26 | AF44: 4 | AG44: 36 | AH44: 16 | AI44: 58 | AJ44: 14 | AK44: 46 | AL44: 24 | AM44: 60 | AN44: 368
B45: MATRONA /ÓN | C45: 0 | D45: 0 | E45: 0 | F45: 0 | G45: 0 | H45: 0 | I45: 0 | J45: 0 | K45: 0 | L45: 0 | M45: 0 | N45: 0 | O45: 0 | P45: 0 | Q45: 0 | R45: 0 | S45: 0 | T45: 0 | U45: 0 | V45: 0 | W45: 0 | X45: 0 | Y45: 0 | Z45: 0 | AA45: 0 | AB45: 0 | AC45: 0 | AD45: 0 | AE45: 0 | AF45: 0 | AG45: 0 | AH45: 0 | AI45: 0 | AJ45: 0 | AK45: 0 | AL45: 0 | AM45: 0 | AN45: 0
B46: NUTRICIONISTA | C46: 6956 | D46: 2960 | E46: 3996 | F46: 1560 | G46: 1264 | H46: 526 | I46: 510 | J46: 210 | K46: 186 | L46: 122 | M46: 340 | N46: 50 | O46: 208 | P46: 40 | Q46: 194 | R46: 44 | S46: 144 | T46: 36 | U46: 126 | V46: 28 | W46: 124 | X46: 26 | Y46: 154 | Z46: 24 | AA46: 170 | AB46: 54 | AC46: 186 | AD46: 90 | AE46: 162 | AF46: 46 | AG46: 106 | AH46: 64 | AI46: 68 | AJ46: 18 | AK46: 26 | AL46: 22 | AM46: 28 | AN46: 6956
B47: TÉCNICO PARAMÉDICO | C47: 0 | D47: 0 | E47: 0 | F47: 0 | G47: 0 | H47: 0 | I47: 0 | J47: 0 | K47: 0 | L47: 0 | M47: 0 | N47: 0 | O47: 0 | P47: 0 | Q47: 0 | R47: 0 | S47: 0 | T47: 0 | U47: 0 | V47: 0 | W47: 0 | X47: 0 | Y47: 0 | Z47: 0 | AA47: 0 | AB47: 0 | AC47: 0 | AD47: 0 | AE47: 0 | AF47: 0 | AG47: 0 | AH47: 0 | AI47: 0 | AJ47: 0 | AK47: 0 | AL47: 0 | AM47: 0 | AN47: 0
A48: NIÑOS CON NECESIDADES ESPECIALES | B48: MÉDICO | C48: 0 | D48: 0 | E48: 0 | F48: 0 | G48: 0 | H48: 0 | I48: 0 | J48: 0 | K48: 0 | L48: 0 | M48: 0 | N48: 0 | O48: 0 | P48: 0 | Q48: 0 | R48: 0 | S48: 0 | T48: 0 | U48: 0 | V48: 0 | W48: 0 | X48: 0 | Y48: 0 | Z48: 0 | AA48: 0 | AB48: 0 | AC48: 0 | AD48: 0 | AE48: 0 | AF48: 0 | AG48: 0 | AH48: 0 | AI48: 0 | AJ48: 0 | AK48: 0 | AL48: 0 | AM48: 0 | AN48: 0
B49: ENFERMERA /O | C49: 750 | D49: 430 | E49: 320 | F49: 410 | G49: 308 | H49: 20 | I49: 12 | J49: 0 | K49: 0 | L49: 0 | M49: 0 | N49: 0 | O49: 0 | P49: 0 | Q49: 0 | R49: 0 | S49: 0 | T49: 0 | U49: 0 | V49: 0 | W49: 0 | X49: 0 | Y49: 0 | Z49: 0 | AA49: 0 | AB49: 0 | AC49: 0 | AD49: 0 | AE49: 0 | AF49: 0 | AG49: 0 | AH49: 0 | AI49: 0 | AJ49: 0 | AK49: 0 | AL49: 0 | AM49: 0 | AN49: 750
B50: MATRONA /ÓN | C50: 0 | D50: 0 | E50: 0 | F50: 0 | G50: 0 | H50: 0 | I50: 0 | J50: 0 | K50: 0 | L50: 0 | M50: 0 | N50: 0 | O50: 0 | P50: 0 | Q50: 0 | R50: 0 | S50: 0 | T50: 0 | U50: 0 | V50: 0 | W50: 0 | X50: 0 | Y50: 0 | Z50: 0 | AA50: 0 | AB50: 0 | AC50: 0 | AD50: 0 | AE50: 0 | AF50: 0 | AG50: 0 | AH50: 0 | AI50: 0 | AJ50: 0 | AK50: 0 | AL50: 0 | AM50: 0 | AN50: 0
B51: NUTRICIONISTA | C51: 64 | D51: 46 | E51: 18 | F51: 46 | G51: 18 | H51: 0 | I51: 0 | J51: 0 | K51: 0 | L51: 0 | M51: 0 | N51: 0 | O51: 0 | P51: 0 | Q51: 0 | R51: 0 | S51: 0 | T51: 0 | U51: 0 | V51: 0 | W51: 0 | X51: 0 | Y51: 0 | Z51: 0 | AA51: 0 | AB51: 0 | AC51: 0 | AD51: 0 | AE51: 0 | AF51: 0 | AG51: 0 | AH51: 0 | AI51: 0 | AJ51: 0 | AK51: 0 | AL51: 0 | AM51: 0 | AN51: 64
B52: TÉCNICO PARAMÉDICO | C52: 0 | D52: 0 | E52: 0 | F52: 0 | G52: 0 | H52: 0 | I52: 0 | J52: 0 | K52: 0 | L52: 0 | M52: 0 | N52: 0 | O52: 0 | P52: 0 | Q52: 0 | R52: 0 | S52: 0 | T52: 0 | U52: 0 | V52: 0 | W52: 0 | X52: 0 | Y52: 0 | Z52: 0 | AA52: 0 | AB52: 0 | AC52: 0 | AD52: 0 | AE52: 0 | AF52: 0 | AG52: 0 | AH52: 0 | AI52: 0 | AJ52: 0 | AK52: 0 | AL52: 0 | AM52: 0 | AN52: 0
A53: Servicio: Servicio de Salud Iquique
A54: DE SALUD CARDIOVASCULAR | B54: MÉDICO | C54: 104696 | D54: 38020 | E54: 66676 | F54: 0 | G54: 0 | H54: 0 | I54: 0 | J54: 0 | K54: 0 | L54: 44 | M54: 76 | N54: 62 | O54: 254 | P54: 188 | Q54: 446 | R54: 330 | S54: 630 | T54: 510 | U54: 1286 | V54: 1050 | W54: 1968 | X54: 1804 | Y54: 3618 | Z54: 2728 | AA54: 6278 | AB54: 4840 | AC54: 9164 | AD54: 5952 | AE54: 10378 | AF54: 6818 | AG54: 10640 | AH54: 5932 | AI54: 8844 | AJ54: 4124 | AK54: 6324 | AL54: 3638 | AM54: 6770 | AN54: 100912
B55: ENFERMERA /O | C55: 22652 | D55: 8152 | E55: 14500 | F55: 0 | G55: 0 | H55: 0 | I55: 0 | J55: 0 | K55: 0 | L55: 4 | M55: 20 | N55: 8 | O55: 48 | P55: 20 | Q55: 86 | R55: 66 | S55: 108 | T55: 130 | U55: 336 | V55: 256 | W55: 456 | X55: 352 | Y55: 774 | Z55: 588 | AA55: 1476 | AB55: 892 | AC55: 1926 | AD55: 1158 | AE55: 2122 | AF55: 1316 | AG55: 2198 | AH55: 1426 | AI55: 1876 | AJ55: 954 | AK55: 1522 | AL55: 982 | AM55: 1552 | AN55: 22458
B56: NUTRICIONISTA | C56: 21616 | D56: 7406 | E56: 14210 | F56: 0 | G56: 0 | H56: 0 | I56: 0 | J56: 0 | K56: 0 | L56: 10 | M56: 16 | N56: 34 | O56: 80 | P56: 66 | Q56: 168 | R56: 100 | S56: 236 | T56: 142 | U56: 396 | V56: 314 | W56: 532 | X56: 448 | Y56: 912 | Z56: 610 | AA56: 1466 | AB56: 940 | AC56: 2054 | AD56: 1240 | AE56: 2254 | AF56: 1078 | AG56: 2184 | AH56: 1062 | AI56: 1688 | AJ56: 696 | AK56: 1150 | AL56: 666 | AM56: 1074 | AN56: 20682
B57: TÉCNICO PARAMÉDICO | C57: 524 | D57: 214 | E57: 310 | F57: 0 | G57: 0 | H57: 0 | I57: 0 | J57: 0 | K57: 0 | L57: 0 | M57: 0 | N57: 8 | O57: 0 | P57: 0 | Q57: 0 | R57: 8 | S57: 0 | T57: 0 | U57: 0 | V57: 4 | W57: 4 | X57: 6 | Y57: 14 | Z57: 18 | AA57: 12 | AB57: 30 | AC57: 14 | AD57: 10 | AE57: 30 | AF57: 10 | AG57: 168 | AH57: 26 | AI57: 18 | AJ57: 50 | AK57: 4 | AL57: 44 | AM57: 46 | AN57: 488
A58: DE TUBERCULOSIS | B58: MÉDICO | C58: 762 | D58: 444 | E58: 318 | F58: 8 | G58: 2 | H58: 6 | I58: 6 | J58: 6 | K58: 14 | L58: 22 | M58: 18 | N58: 24 | O58: 26 | P58: 34 | Q58: 52 | R58: 30 | S58: 42 | T58: 40 | U58: 28 | V58: 50 | W58: 20 | X58: 18 | Y58: 44 | Z58: 28 | AA58: 12 | AB58: 66 | AC58: 20 | AD58: 34 | AE58: 6 | AF58: 22 | AG58: 14 | AH58: 16 | AI58: 14 | AJ58: 16 | AK58: 0 | AL58: 24 | AM58: 0 | AN58: 760
B59: ENFERMERA /O | C59: 4958 | D59: 2518 | E59: 2440 | F59: 22 | G59: 10 | H59: 4 | I59: 10 | J59: 6 | K59: 42 | L59: 12 | M59: 24 | N59: 242 | O59: 132 | P59: 58 | Q59: 412 | R59: 240 | S59: 500 | T59: 214 | U59: 270 | V59: 82 | W59: 210 | X59: 164 | Y59: 148 | Z59: 418 | AA59: 290 | AB59: 336 | AC59: 96 | AD59: 334 | AE59: 30 | AF59: 230 | AG59: 86 | AH59: 22 | AI59: 168 | AJ59: 120 | AK59: 8 | AL59: 14 | AM59: 4 | AN59: 4972
A60: SEGUIMIENTO AUTOVALENTE CON RIESGO | B60: MÉDICO | C60: 14 | D60: 8 | E60: 6 | F60: 0 | G60: 0 | H60: 0 | I60: 0 | J60: 0 | K60: 0 | L60: 0 | M60: 0 | N60: 0 | O60: 0 | P60: 0 | Q60: 0 | R60: 0 | S60: 0 | T60: 0 | U60: 0 | V60: 0 | W60: 0 | X60: 0 | Y60: 0 | Z60: 0 | AA60: 0 | AB60: 0 | AC60: 0 | AD60: 0 | AE60: 0 | AF60: 6 | AG60: 4 | AH60: 0 | AI60: 0 | AJ60: 0 | AK60: 2 | AL60: 2 | AM60: 0 | AN60: 14
B61: ENFERMERA /O | C61: 1346 | D61: 524 | E61: 822 | F61: 0 | G61: 0 | H61: 0 | I61: 0 | J61: 0 | K61: 0 | L61: 0 | M61: 0 | N61: 0 | O61: 0 | P61: 0 | Q61: 0 | R61: 0 | S61: 0 | T61: 0 | U61: 0 | V61: 0 | W61: 0 | X61: 0 | Y61: 0 | Z61: 0 | AA61: 0 | AB61: 0 | AC61: 0 | AD61: 0 | AE61: 0 | AF61: 100 | AG61: 226 | AH61: 178 | AI61: 246 | AJ61: 132 | AK61: 194 | AL61: 114 | AM61: 156 | AN61: 1216
A62: SEGUIMIENTO RIESGO DEPENDENCIA | B62: MÉDICO | C62: 12 | D62: 0 | E62: 12 | F62: 0 | G62: 0 | H62: 0 | I62: 0 | J62: 0 | K62: 0 | L62: 0 | M62: 0 | N62: 0 | O62: 0 | P62: 0 | Q62: 0 | R62: 0 | S62: 0 | T62: 0 | U62: 0 | V62: 0 | W62: 0 | X62: 0 | Y62: 0 | Z62: 0 | AA62: 0 | AB62: 0 | AC62: 0 | AD62: 0 | AE62: 0 | AF62: 0 | AG62: 0 | AH62: 0 | AI62: 8 | AJ62: 0 | AK62: 2 | AL62: 0 | AM62: 2 | AN62: 12
B63: ENFERMERA /O | C63: 1112 | D63: 360 | E63: 752 | F63: 0 | G63: 0 | H63: 0 | I63: 0 | J63: 0 | K63: 0 | L63: 0 | M63: 0 | N63: 0 | O63: 0 | P63: 0 | Q63: 0 | R63: 0 | S63: 0 | T63: 0 | U63: 0 | V63: 0 | W63: 0 | X63: 0 | Y63: 0 | Z63: 0 | AA63: 0 | AB63: 0 | AC63: 0 | AD63: 0 | AE63: 0 | AF63: 40 | AG63: 76 | AH63: 60 | AI63: 130 | AJ63: 48 | AK63: 118 | AL63: 212 | AM63: 428 | AN63: 1096
A64: DE INFECCIÓN TRANSMISIÓN SEXUAL | B64: MÉDICO | C64: 6 | D64: 0 | E64: 6 | F64: 0 | G64: 0 | H64: 0 | I64: 0 | J64: 0 | K64: 0 | L64: 0 | M64: 0 | N64: 0 | O64: 0 | P64: 0 | Q64: 0 | R64: 0 | S64: 0 | T64: 0 | U64: 0 | V64: 0 | W64: 0 | X64: 0 | Y64: 0 | Z64: 0 | AA64: 2 | AB64: 0 | AC64: 0 | AD64: 0 | AE64: 0 | AF64: 0 | AG64: 0 | AH64: 0 | AI64: 2 | AJ64: 0 | AK64: 0 | AL64: 0 | AM64: 2 | AN64: 6
B65: ENFERMERA /O | C65: 44 | D65: 16 | E65: 28 | F65: 0 | G65: 2 | H65: 0 | I65: 0 | J65: 0 | K65: 0 | L65: 0 | M65: 0 | N65: 0 | O65: 0 | P65: 0 | Q65: 0 | R65: 0 | S65: 0 | T65: 0 | U65: 0 | V65: 4 | W65: 0 | X65: 2 | Y65: 0 | Z65: 4 | AA65: 16 | AB65: 4 | AC65: 8 | AD65: 2 | AE65: 0 | AF65: 0 | AG65: 0 | AH65: 0 | AI65: 2 | AJ65: 0 | AK65: 0 | AL65: 0 | AM65: 0 | AN65: 42
B66: MATRONA /ÓN | C66: 76 | D66: 4 | E66: 72 | F66: 0 | G66: 28 | H66: 0 | I66: 0 | J66: 0 | K66: 0 | L66: 0 | M66: 6 | N66: 0 | O66: 10 | P66: 4 | Q66: 14 | R66: 0 | S66: 4 | T66: 0 | U66: 6 | V66: 0 | W66: 0 | X66: 0 | Y66: 2 | Z66: 0 | AA66: 0 | AB66: 0 | AC66: 0 | AD66: 0 | AE66: 0 | AF66: 0 | AG66: 0 | AH66: 0 | AI66: 2 | AJ66: 0 | AK66: 0 | AL66: 0 | AM66: 0 | AN66: 48
A67: OTROS PROBLEMAS DE SALUD | B67: MÉDICO | C67: 44468 | D67: 10252 | E67: 34216 | F67: 304 | G67: 368 | H67: 138 | I67: 136 | J67: 94 | K67: 134 | L67: 162 | M67: 310 | N67: 138 | O67: 542 | P67: 180 | Q67: 910 | R67: 248 | S67: 918 | T67: 276 | U67: 1088 | V67: 284 | W67: 1194 | X67: 356 | Y67: 1626 | Z67: 498 | AA67: 2364 | AB67: 800 | AC67: 3858 | AD67: 1252 | AE67: 4466 | AF67: 1350 | AG67: 5134 | AH67: 1512 | AI67: 4272 | AJ67: 1236 | AK67: 3316 | AL67: 1424 | AM67: 3580 | AN67: 43836
B68: ENFERMERA /O | C68: 4874 | D68: 1400 | E68: 3474 | F68: 264 | G68: 280 | H68: 60 | I68: 80 | J68: 60 | K68: 28 | L68: 20 | M68: 52 | N68: 30 | O68: 88 | P68: 20 | Q68: 148 | R68: 34 | S68: 146 | T68: 6 | U68: 122 | V68: 36 | W68: 186 | X68: 98 | Y68: 222 | Z68: 88 | AA68: 282 | AB68: 88 | AC68: 404 | AD68: 108 | AE68: 370 | AF68: 126 | AG68: 314 | AH68: 110 | AI68: 288 | AJ68: 94 | AK68: 184 | AL68: 158 | AM68: 280 | AN68: 4716
B69: MATRONA /ÓN | C69: 1488 | D69: 516 | E69: 972 | F69: 492 | G69: 486 | H69: 0 | I69: 2 | J69: 0 | K69: 2 | L69: 0 | M69: 12 | N69: 0 | O69: 54 | P69: 0 | Q69: 58 | R69: 0 | S69: 40 | T69: 0 | U69: 22 | V69: 0 | W69: 52 | X69: 2 | Y69: 44 | Z69: 0 | AA69: 46 | AB69: 4 | AC69: 36 | AD69: 2 | AE69: 36 | AF69: 8 | AG69: 44 | AH69: 6 | AI69: 28 | AJ69: 2 | AK69: 8 | AL69: 0 | AM69: 2 | AN69: 1488
B70: NUTRICIONISTA | C70: 7090 | D70: 1982 | E70: 5108 | F70: 246 | G70: 294 | H70: 90 | I70: 100 | J70: 62 | K70: 66 | L70: 42 | M70: 140 | N70: 44 | O70: 218 | P70: 54 | Q70: 266 | R70: 38 | S70: 204 | T70: 40 | U70: 242 | V70: 80 | W70: 214 | X70: 96 | Y70: 280 | Z70: 92 | AA70: 366 | AB70: 132 | AC70: 488 | AD70: 216 | AE70: 538 | AF70: 232 | AG70: 616 | AH70: 222 | AI70: 466 | AJ70: 144 | AK70: 290 | AL70: 152 | AM70: 320 | AN70: 6692
B71: TÉCNICO PARAMÉDICO | C71: 2310 | D71: 994 | E71: 1316 | F71: 40 | G71: 48 | H71: 22 | I71: 34 | J71: 20 | K71: 66 | L71: 34 | M71: 24 | N71: 24 | O71: 14 | P71: 56 | Q71: 46 | R71: 54 | S71: 60 | T71: 44 | U71: 104 | V71: 44 | W71: 28 | X71: 94 | Y71: 56 | Z71: 62 | AA71: 74 | AB71: 24 | AC71: 84 | AD71: 82 | AE71: 74 | AF71: 66 | AG71: 166 | AH71: 94 | AI71: 162 | AJ71: 68 | AK71: 82 | AL71: 166 | AM71: 194 | AN71: 2214
A72: NIÑOS CON NECESIDADES ESPECIALES | B72: MÉDICO | C72: 32 | D72: 16 | E72: 16 | F72: 16 | G72: 16 | H72: 0 | I72: 0 | J72: 0 | K72: 0 | L72: 0 | M72: 0 | N72: 0 | O72: 0 | P72: 0 | Q72: 0 | R72: 0 | S72: 0 | T72: 0 | U72: 0 | V72: 0 | W72: 0 | X72: 0 | Y72: 0 | Z72: 0 | AA72: 0 | AB72: 0 | AC72: 0 | AD72: 0 | AE72: 0 | AF72: 0 | AG72: 0 | AH72: 0 | AI72: 0 | AJ72: 0 | AK72: 0 | AL72: 0 | AM72: 0 | AN72: 32
B73: ENFERMERA /O | C73: 238 | D73: 126 | E73: 112 | F73: 110 | G73: 96 | H73: 14 | I73: 16 | J73: 2 | K73: 0 | L73: 0 | M73: 0 | N73: 0 | O73: 0 | P73: 0 | Q73: 0 | R73: 0 | S73: 0 | T73: 0 | U73: 0 | V73: 0 | W73: 0 | X73: 0 | Y73: 0 | Z73: 0 | AA73: 0 | AB73: 0 | AC73: 0 | AD73: 0 | AE73: 0 | AF73: 0 | AG73: 0 | AH73: 0 | AI73: 0 | AJ73: 0 | AK73: 0 | AL73: 0 | AM73: 0 | AN73: 224
B74: MATRONA /ÓN | C74: 2 | D74: 0 | E74: 2 | F74: 0 | G74: 2 | H74: 0 | I74: 0 | J74: 0 | K74: 0 | L74: 0 | M74: 0 | N74: 0 | O74: 0 | P74: 0 | Q74: 0 | R74: 0 | S74: 0 | T74: 0 | U74: 0 | V74: 0 | W74: 0 | X74: 0 | Y74: 0 | Z74: 0 | AA74: 0 | AB74: 0 | AC74: 0 | AD74: 0 | AE74: 0 | AF74: 0 | AG74: 0 | AH74: 0 | AI74: 0 | AJ74: 0 | AK74: 0 | AL74: 0 | AM74: 0 | AN74: 2
B75: NUTRICIONISTA | C75: 260 | D75: 156 | E75: 104 | F75: 112 | G75: 90 | H75: 42 | I75: 12 | J75: 0 | K75: 0 | L75: 0 | M75: 2 | N75: 2 | O75: 0 | P75: 0 | Q75: 0 | R75: 0 | S75: 0 | T75: 0 | U75: 0 | V75: 0 | W75: 0 | X75: 0 | Y75: 0 | Z75: 0 | AA75: 0 | AB75: 0 | AC75: 0 | AD75: 0 | AE75: 0 | AF75: 0 | AG75: 0 | AH75: 0 | AI75: 0 | AJ75: 0 | AK75: 0 | AL75: 0 | AM75: 0 | AN75: 232
B76: TÉCNICO PARAMÉDICO | C76: 0 | D76: 0 | E76: 0 | F76: 0 | G76: 0 | H76: 0 | I76: 0 | J76: 0 | K76: 0 | L76: 0 | M76: 0 | N76: 0 | O76: 0 | P76: 0 | Q76: 0 | R76: 0 | S76: 0 | T76: 0 | U76: 0 | V76: 0 | W76: 0 | X76: 0 | Y76: 0 | Z76: 0 | AA76: 0 | AB76: 0 | AC76: 0 | AD76: 0 | AE76: 0 | AF76: 0 | AG76: 0 | AH76: 0 | AI76: 0 | AJ76: 0 | AK76: 0 | AL76: 0 | AM76: 0 | AN76: 0
A77: Servicio: Servicio de Salud Antofagasta
A78: DE SALUD CARDIOVASCULAR | B78: MÉDICO | C78: 152040 | D78: 50740 | E78: 101300 | F78: 0 | G78: 0 | H78: 0 | I78: 0 | J78: 0 | K78: 0 | L78: 78 | M78: 112 | N78: 132 | O78: 270 | P78: 194 | Q78: 516 | R78: 378 | S78: 932 | T78: 666 | U78: 1818 | V78: 1178 | W78: 3114 | X78: 2296 | Y78: 5682 | Z78: 4102 | AA78: 9752 | AB78: 6334 | AC78: 13422 | AD78: 7710 | AE78: 14706 | AF78: 8050 | AG78: 14682 | AH78: 7590 | AI78: 13472 | AJ78: 5758 | AK78: 10480 | AL78: 6274 | AM78: 12342 | AN78: 150036
B79: ENFERMERA /O | C79: 45628 | D79: 15978 | E79: 29650 | F79: 0 | G79: 0 | H79: 0 | I79: 0 | J79: 0 | K79: 0 | L79: 14 | M79: 22 | N79: 46 | O79: 20 | P79: 72 | Q79: 122 | R79: 110 | S79: 278 | T79: 152 | U79: 436 | V79: 308 | W79: 736 | X79: 534 | Y79: 1402 | Z79: 1142 | AA79: 2578 | AB79: 1518 | AC79: 3026 | AD79: 1932 | AE79: 3630 | AF79: 2744 | AG79: 4866 | AH79: 2888 | AI79: 4652 | AJ79: 2242 | AK79: 3730 | AL79: 2276 | AM79: 4152 | AN79: 45034
B80: NUTRICIONISTA | C80: 32826 | D80: 10072 | E80: 22754 | F80: 0 | G80: 0 | H80: 0 | I80: 0 | J80: 0 | K80: 0 | L80: 14 | M80: 30 | N80: 50 | O80: 124 | P80: 68 | Q80: 214 | R80: 102 | S80: 364 | T80: 152 | U80: 638 | V80: 320 | W80: 910 | X80: 474 | Y80: 1594 | Z80: 924 | AA80: 2512 | AB80: 1282 | AC80: 3202 | AD80: 1396 | AE80: 3034 | AF80: 1550 | AG80: 3192 | AH80: 1494 | AI80: 2616 | AJ80: 1092 | AK80: 1996 | AL80: 1154 | AM80: 2328 | AN80: 32372
B81: TÉCNICO PARAMÉDICO | C81: 106 | D81: 50 | E81: 56 | F81: 0 | G81: 0 | H81: 0 | I81: 0 | J81: 0 | K81: 0 | L81: 0 | M81: 0 | N81: 0 | O81: 0 | P81: 0 | Q81: 0 | R81: 0 | S81: 0 | T81: 2 | U81: 0 | V81: 2 | W81: 6 | X81: 6 | Y81: 2 | Z81: 2 | AA81: 2 | AB81: 0 | AC81: 0 | AD81: 4 | AE81: 12 | AF81: 6 | AG81: 4 | AH81: 10 | AI81: 12 | AJ81: 4 | AK81: 0 | AL81: 14 | AM81: 18 | AN81: 82
A82: DE TUBERCULOSIS | B82: MÉDICO | C82: 1250 | D82: 686 | E82: 564 | F82: 12 | G82: 18 | H82: 28 | I82: 26 | J82: 14 | K82: 14 | L82: 30 | M82: 48 | N82: 72 | O82: 48 | P82: 90 | Q82: 56 | R82: 60 | S82: 36 | T82: 58 | U82: 50 | V82: 72 | W82: 48 | X82: 28 | Y82: 28 | Z82: 58 | AA82: 54 | AB82: 48 | AC82: 60 | AD82: 74 | AE82: 24 | AF82: 12 | AG82: 10 | AH82: 12 | AI82: 22 | AJ82: 14 | AK82: 16 | AL82: 4 | AM82: 6 | AN82: 1224
B83: ENFERMERA /O | C83: 578 | D83: 334 | E83: 244 | F83: 0 | G83: 4 | H83: 2 | I83: 10 | J83: 6 | K83: 12 | L83: 28 | M83: 6 | N83: 20 | O83: 16 | P83: 60 | Q83: 20 | R83: 44 | S83: 24 | T83: 34 | U83: 20 | V83: 32 | W83: 8 | X83: 28 | Y83: 20 | Z83: 22 | AA83: 32 | AB83: 12 | AC83: 14 | AD83: 22 | AE83: 6 | AF83: 2 | AG83: 8 | AH83: 12 | AI83: 34 | AJ83: 8 | AK83: 8 | AL83: 2 | AM83: 2 | AN83: 560
A84: SEGUIMIENTO AUTOVALENTE CON RIESGO | B84: MÉDICO | C84: 262 | D84: 118 | E84: 144 | F84: 0 | G84: 0 | H84: 0 | I84: 0 | J84: 0 | K84: 0 | L84: 0 | M84: 0 | N84: 0 | O84: 0 | P84: 0 | Q84: 0 | R84: 0 | S84: 0 | T84: 0 | U84: 0 | V84: 0 | W84: 0 | X84: 0 | Y84: 0 | Z84: 0 | AA84: 0 | AB84: 0 | AC84: 0 | AD84: 0 | AE84: 0 | AF84: 30 | AG84: 44 | AH84: 28 | AI84: 38 | AJ84: 26 | AK84: 40 | AL84: 34 | AM84: 22 | AN84: 260
B85: ENFERMERA /O | C85: 4236 | D85: 1412 | E85: 2824 | F85: 0 | G85: 0 | H85: 0 | I85: 0 | J85: 0 | K85: 0 | L85: 0 | M85: 0 | N85: 0 | O85: 0 | P85: 0 | Q85: 0 | R85: 0 | S85: 0 | T85: 0 | U85: 0 | V85: 0 | W85: 0 | X85: 0 | Y85: 0 | Z85: 0 | AA85: 0 | AB85: 0 | AC85: 0 | AD85: 0 | AE85: 0 | AF85: 334 | AG85: 734 | AH85: 406 | AI85: 836 | AJ85: 366 | AK85: 630 | AL85: 306 | AM85: 624 | AN85: 4190
A86: SEGUIMIENTO RIESGO DEPENDENCIA | B86: MÉDICO | C86: 104 | D86: 48 | E86: 56 | F86: 0 | G86: 0 | H86: 0 | I86: 0 | J86: 0 | K86: 0 | L86: 0 | M86: 0 | N86: 0 | O86: 0 | P86: 0 | Q86: 0 | R86: 0 | S86: 0 | T86: 0 | U86: 0 | V86: 0 | W86: 0 | X86: 0 | Y86: 0 | Z86: 0 | AA86: 0 | AB86: 0 | AC86: 0 | AD86: 0 | AE86: 0 | AF86: 8 | AG86: 6 | AH86: 12 | AI86: 18 | AJ86: 8 | AK86: 12 | AL86: 20 | AM86: 20 | AN86: 104
B87: ENFERMERA /O | C87: 2148 | D87: 662 | E87: 1486 | F87: 0 | G87: 0 | H87: 0 | I87: 0 | J87: 0 | K87: 0 | L87: 0 | M87: 0 | N87: 0 | O87: 0 | P87: 0 | Q87: 0 | R87: 0 | S87: 0 | T87: 0 | U87: 0 | V87: 0 | W87: 0 | X87: 0 | Y87: 0 | Z87: 0 | AA87: 0 | AB87: 0 | AC87: 0 | AD87: 0 | AE87: 0 | AF87: 64 | AG87: 164 | AH87: 134 | AI87: 230 | AJ87: 118 | AK87: 274 | AL87: 346 | AM87: 818 | AN87: 2100
A88: DE INFECCIÓN TRANSMISIÓN SEXUAL | B88: MÉDICO | C88: 36 | D88: 18 | E88: 18 | F88: 0 | G88: 0 | H88: 0 | I88: 0 | J88: 0 | K88: 0 | L88: 4 | M88: 0 | N88: 4 | O88: 8 | P88: 4 | Q88: 4 | R88: 2 | S88: 2 | T88: 0 | U88: 0 | V88: 0 | W88: 0 | X88: 0 | Y88: 0 | Z88: 2 | AA88: 2 | AB88: 0 | AC88: 2 | AD88: 2 | AE88: 0 | AF88: 0 | AG88: 0 | AH88: 0 | AI88: 0 | AJ88: 0 | AK88: 0 | AL88: 0 | AM88: 0 | AN88: 36
B89: ENFERMERA /O | C89: 0 | D89: 0 | E89: 0 | F89: 0 | G89: 0 | H89: 0 | I89: 0 | J89: 0 | K89: 0 | L89: 0 | M89: 0 | N89: 0 | O89: 0 | P89: 0 | Q89: 0 | R89: 0 | S89: 0 | T89: 0 | U89: 0 | V89: 0 | W89: 0 | X89: 0 | Y89: 0 | Z89: 0 | AA89: 0 | AB89: 0 | AC89: 0 | AD89: 0 | AE89: 0 | AF89: 0 | AG89: 0 | AH89: 0 | AI89: 0 | AJ89: 0 | AK89: 0 | AL89: 0 | AM89: 0 | AN89: 0
B90: MATRONA /ÓN | C90: 520 | D90: 150 | E90: 370 | F90: 0 | G90: 0 | H90: 0 | I90: 0 | J90: 0 | K90: 2 | L90: 44 | M90: 106 | N90: 30 | O90: 88 | P90: 12 | Q90: 48 | R90: 12 | S90: 48 | T90: 10 | U90: 28 | V90: 6 | W90: 12 | X90: 6 | Y90: 14 | Z90: 4 | AA90: 4 | AB90: 2 | AC90: 12 | AD90: 16 | AE90: 2 | AF90: 8 | AG90: 0 | AH90: 0 | AI90: 0 | AJ90: 0 | AK90: 0 | AL90: 0 | AM90: 6 | AN90: 482
A91: OTROS PROBLEMAS DE SALUD | B91: MÉDICO | C91: 80754 | D91: 22708 | E91: 58046 | F91: 382 | G91: 378 | H91: 272 | I91: 224 | J91: 172 | K91: 264 | L91: 258 | M91: 460 | N91: 254 | O91: 720 | P91: 282 | Q91: 894 | R91: 304 | S91: 1292 | T91: 264 | U91: 1596 | V91: 412 | W91: 1978 | X91: 958 | Y91: 3274 | Z91: 1572 | AA91: 5252 | AB91: 2034 | AC91: 6602 | AD91: 2872 | AE91: 7112 | AF91: 2382 | AG91: 7442 | AH91: 3966 | AI91: 7068 | AJ91: 2676 | AK91: 6100 | AL91: 3648 | AM91: 7390 | AN91: 79386
B92: ENFERMERA /O | C92: 13518 | D92: 5834 | E92: 7684 | F92: 12 | G92: 10 | H92: 12 | I92: 0 | J92: 36 | K92: 22 | L92: 40 | M92: 28 | N92: 8 | O92: 22 | P92: 10 | Q92: 38 | R92: 18 | S92: 136 | T92: 8 | U92: 172 | V92: 40 | W92: 114 | X92: 412 | Y92: 468 | Z92: 682 | AA92: 1396 | AB92: 568 | AC92: 934 | AD92: 1022 | AE92: 670 | AF92: 302 | AG92: 1114 | AH92: 1410 | AI92: 826 | AJ92: 470 | AK92: 990 | AL92: 784 | AM92: 744 | AN92: 13236
B93: MATRONA /ÓN | C93: 308 | D93: 28 | E93: 280 | F93: 6 | G93: 6 | H93: 0 | I93: 2 | J93: 2 | K93: 6 | L93: 0 | M93: 12 | N93: 0 | O93: 24 | P93: 4 | Q93: 54 | R93: 0 | S93: 14 | T93: 0 | U93: 10 | V93: 0 | W93: 24 | X93: 0 | Y93: 24 | Z93: 4 | AA93: 16 | AB93: 0 | AC93: 20 | AD93: 0 | AE93: 4 | AF93: 4 | AG93: 26 | AH93: 0 | AI93: 20 | AJ93: 6 | AK93: 6 | AL93: 2 | AM93: 12 | AN93: 306
B94: NUTRICIONISTA | C94: 12130 | D94: 3758 | E94: 8372 | F94: 1688 | G94: 1680 | H94: 470 | I94: 470 | J94: 194 | K94: 188 | L94: 48 | M94: 200 | N94: 28 | O94: 394 | P94: 40 | Q94: 568 | R94: 42 | S94: 482 | T94: 52 | U94: 388 | V94: 70 | W94: 360 | X94: 68 | Y94: 472 | Z94: 108 | AA94: 634 | AB94: 100 | AC94: 674 | AD94: 148 | AE94: 480 | AF94: 134 | AG94: 538 | AH94: 244 | AI94: 374 | AJ94: 148 | AK94: 236 | AL94: 176 | AM94: 234 | AN94: 11956
B95: TÉCNICO PARAMÉDICO | C95: 7710 | D95: 4334 | E95: 3376 | F95: 40 | G95: 40 | H95: 26 | I95: 80 | J95: 22 | K95: 10 | L95: 12 | M95: 22 | N95: 8 | O95: 26 | P95: 22 | Q95: 36 | R95: 12 | S95: 94 | T95: 18 | U95: 206 | V95: 42 | W95: 44 | X95: 402 | Y95: 304 | Z95: 602 | AA95: 1118 | AB95: 466 | AC95: 560 | AD95: 882 | AE95: 206 | AF95: 10 | AG95: 302 | AH95: 1050 | AI95: 8 | AJ95: 220 | AK95: 248 | AL95: 500 | AM95: 72 | AN95: 7582
A96: NIÑOS CON NECESIDADES ESPECIALES | B96: MÉDICO | C96: 1476 | D96: 888 | E96: 588 | F96: 614 | G96: 362 | H96: 182 | I96: 134 | J96: 78 | K96: 70 | L96: 14 | M96: 16 | N96: 0 | O96: 6 | P96: 0 | Q96: 0 | R96: 0 | S96: 0 | T96: 0 | U96: 0 | V96: 0 | W96: 0 | X96: 0 | Y96: 0 | Z96: 0 | AA96: 0 | AB96: 0 | AC96: 0 | AD96: 0 | AE96: 0 | AF96: 0 | AG96: 0 | AH96: 0 | AI96: 0 | AJ96: 0 | AK96: 0 | AL96: 0 | AM96: 0 | AN96: 1328
B97: ENFERMERA /O | C97: 490 | D97: 302 | E97: 188 | F97: 228 | G97: 156 | H97: 62 | I97: 30 | J97: 6 | K97: 0 | L97: 4 | M97: 0 | N97: 2 | O97: 2 | P97: 0 | Q97: 0 | R97: 0 | S97: 0 | T97: 0 | U97: 0 | V97: 0 | W97: 0 | X97: 0 | Y97: 0 | Z97: 0 | AA97: 0 | AB97: 0 | AC97: 0 | AD97: 0 | AE97: 0 | AF97: 0 | AG97: 0 | AH97: 0 | AI97: 0 | AJ97: 0 | AK97: 0 | AL97: 0 | AM97: 0 | AN97: 472
B98: MATRONA /ÓN | C98: 6 | D98: 6 | E98: 0 | F98: 6 | G98: 0 | H98: 0 | I98: 0 | J98: 0 | K98: 0 | L98: 0 | M98: 0 | N98: 0 | O98: 0 | P98: 0 | Q98: 0 | R98: 0 | S98: 0 | T98: 0 | U98: 0 | V98: 0 | W98: 0 | X98: 0 | Y98: 0 | Z98: 0 | AA98: 0 | AB98: 0 | AC98: 0 | AD98: 0 | AE98: 0 | AF98: 0 | AG98: 0 | AH98: 0 | AI98: 0 | AJ98: 0 | AK98: 0 | AL98: 0 | AM98: 0 | AN98: 2
B99: NUTRICIONISTA | C99: 184 | D99: 114 | E99: 70 | F99: 98 | G99: 60 | H99: 14 | I99: 4 | J99: 2 | K99: 0 | L99: 0 | M99: 4 | N99: 0 | O99: 2 | P99: 0 | Q99: 0 | R99: 0 | S99: 0 | T99: 0 | U99: 0 | V99: 0 | W99: 0 | X99: 0 | Y99: 0 | Z99: 0 | AA99: 0 | AB99: 0 | AC99: 0 | AD99: 0 | AE99: 0 | AF99: 0 | AG99: 0 | AH99: 0 | AI99: 0 | AJ99: 0 | AK99: 0 | AL99: 0 | AM99: 0 | AN99: 174
B100: TÉCNICO PARAMÉDICO | C100: 0 | D100: 0 | E100: 0 | F100: 0 | G100: 0 | H100: 0 | I100: 0 | J100: 0 | K100: 0 | L100: 0 | M100: 0 | N100: 0 | O100: 0 | P100: 0 | Q100: 0 | R100: 0 | S100: 0 | T100: 0 | U100: 0 | V100: 0 | W100: 0 | X100: 0 | Y100: 0 | Z100: 0 | AA100: 0 | AB100: 0 | AC100: 0 | AD100: 0 | AE100: 0 | AF100: 0 | AG100: 0 | AH100: 0 | AI100: 0 | AJ100: 0 | AK100: 0 | AL100: 0 | AM100: 0 | AN100: 0
...

Sheet Hoja 22
A1: 2020 [ Enero - Diciembre ]
A2: TIPO DE CONTROL | B2: PROFESIONAL | C2: TOTAL | F2: POR EDAD | AN2: BENEFICIARIOS
F3: 0 - 4 | H3: 45905 | J3: 45944 | L3: 15 - 19 | N3: 20 - 24 | P3: 25 - 29 | R3: 30 - 34 | T3: 35 - 39 | V3: 40 - 44 | X3: 45 - 49 | Z3: 50 - 54 | AB3: 55 - 59 | AD3: 60 - 64 | AF3: 65 - 69 | AH3: 70 - 74 | AJ3: 75 - 79 | AL3: 80 y mas
C4: Ambos Sexos | D4: Hombres | E4: Mujeres | F4: Hombres | G4: Mujeres | H4: Hombres | I4: Mujeres | J4: Hombres | K4: Mujeres | L4: Hombres | M4: Mujeres | N4: Hombres | O4: Mujeres | P4: Hombres | Q4: Mujeres | R4: Hombres | S4: Mujeres | T4: Hombres | U4: Mujeres | V4: Hombres | W4: Mujeres | X4: Hombres | Y4: Mujeres | Z4: Hombres | AA4: Mujeres | AB4: Hombres | AC4: Mujeres | AD4: Hombres | AE4: Mujeres | AF4: Hombres | AG4: Mujeres | AH4: Hombres | AI4: Mujeres | AJ4: Hombres | AK4: Mujeres | AL4: Hombres | AM4: Mujeres
A5: Acumulado Pais
A6: DE SALUD CARDIOVASCULAR | B6: MÉDICO | C6: 2539374 | D6: 956450 | E6: 1584302 | F6: 0 | G6: 0 | H6: 0 | I6: 0 | J6: 0 | K6: 0 | L6: 1628 | M6: 2426 | N6: 2572 | O6: 5424 | P6: 5118 | Q6: 11374 | R6: 10144 | S6: 20946 | T6: 17230 | U6: 34808 | V6: 29680 | W6: 57958 | X6: 49806 | Y6: 99854 | Z6: 81472 | AA6: 158704 | AB6: 118866 | AC6: 208240 | AD6: 136798 | AE6: 223172 | AF6: 143662 | AG6: 217526 | AH6: 137166 | AI6: 198368 | AJ6: 108184 | AK6: 157450 | AL6: 114160 | AM6: 188134 | AN6: 2501836
B7: ENFERMERA /O | C7: 877790 | D7: 325074 | E7: 551862 | F7: 0 | G7: 0 | H7: 0 | I7: 0 | J7: 0 | K7: 0 | L7: 284 | M7: 420 | N7: 560 | O7: 1082 | P7: 1398 | Q7: 2770 | R7: 2526 | S7: 5502 | T7: 4754 | U7: 9286 | V7: 8184 | W7: 17224 | X7: 14588 | Y7: 31358 | Z7: 25596 | AA7: 52168 | AB7: 37924 | AC7: 69952 | AD7: 44850 | AE7: 76654 | AF7: 50218 | AG7: 78630 | AH7: 49118 | AI7: 73850 | AJ7: 42002 | AK7: 59978 | AL7: 43066 | AM7: 72992 | AN7: 865600
B8: NUTRICIONISTA | C8: 718782 | D8: 255050 | E8: 463426 | F8: 0 | G8: 0 | H8: 0 | I8: 2 | J8: 2 | K8: 0 | L8: 536 | M8: 890 | N8: 904 | O8: 2000 | P8: 1706 | Q8: 4318 | R8: 3190 | S8: 7394 | T8: 5146 | U8: 11294 | V8: 8868 | W8: 18644 | X8: 14170 | Y8: 31976 | Z8: 22570 | AA8: 50122 | AB8: 32188 | AC8: 62964 | AD8: 36674 | AE8: 66298 | AF8: 38198 | AG8: 63486 | AH8: 36384 | AI8: 56834 | AJ8: 27672 | AK8: 42300 | AL8: 26770 | AM8: 44766 | AN8: 707606
B9: TÉCNICO PARAMÉDICO | C9: 119840 | D9: 44718 | E9: 74912 | F9: 0 | G9: 0 | H9: 0 | I9: 0 | J9: 0 | K9: 0 | L9: 82 | M9: 166 | N9: 156 | O9: 258 | P9: 360 | Q9: 748 | R9: 562 | S9: 1348 | T9: 854 | U9: 1800 | V9: 1418 | W9: 2948 | X9: 2052 | Y9: 4992 | Z9: 3874 | AA9: 8050 | AB9: 5390 | AC9: 9838 | AD9: 6324 | AE9: 10080 | AF9: 5744 | AG9: 10012 | AH9: 6762 | AI9: 8866 | AJ9: 4894 | AK9: 7144 | AL9: 6228 | AM9: 8680 | AN9: 115644
A10: DE TUBERCULOSIS | B10: MÉDICO | C10: 19326 | D10: 10804 | E10: 8532 | F10: 252 | G10: 316 | H10: 198 | I10: 226 | J10: 248 | K10: 252 | L10: 354 | M10: 328 | N10: 850 | O10: 652 | P10: 1014 | Q10: 942 | R10: 1120 | S10: 874 | T10: 1106 | U10: 572 | V10: 748 | W10: 474 | X10: 884 | Y10: 576 | Z10: 876 | AA10: 698 | AB10: 842 | AC10: 632 | AD10: 798 | AE10: 592 | AF10: 522 | AG10: 396 | AH10: 472 | AI10: 456 | AJ10: 216 | AK10: 220 | AL10: 304 | AM10: 326 | AN10: 18554
B11: ENFERMERA /O | C11: 17492 | D11: 9762 | E11: 7724 | F11: 262 | G11: 414 | H11: 396 | I11: 294 | J11: 246 | K11: 238 | L11: 362 | M11: 376 | N11: 638 | O11: 512 | P11: 930 | Q11: 946 | R11: 1016 | S11: 678 | T11: 780 | U11: 734 | V11: 762 | W11: 474 | X11: 796 | Y11: 580 | Z11: 778 | AA11: 508 | AB11: 758 | AC11: 390 | AD11: 900 | AE11: 422 | AF11: 440 | AG11: 354 | AH11: 308 | AI11: 256 | AJ11: 170 | AK11: 136 | AL11: 220 | AM11: 412 | AN11: 16756
A12: SEGUIMIENTO AUTOVALENTE CON RIESGO | B12: MÉDICO | C12: 2234 | D12: 1006 | E12: 1248 | F12: 0 | G12: 0 | H12: 0 | I12: 0 | J12: 0 | K12: 0 | L12: 0 | M12: 0 | N12: 0 | O12: 0 | P12: 0 | Q12: 0 | R12: 0 | S12: 0 | T12: 0 | U12: 0 | V12: 0 | W12: 0 | X12: 0 | Y12: 0 | Z12: 0 | AA12: 0 | AB12: 0 | AC12: 0 | AD12: 0 | AE12: 0 | AF12: 174 | AG12: 272 | AH12: 248 | AI12: 336 | AJ12: 232 | AK12: 278 | AL12: 352 | AM12: 362 | AN12: 2224
B13: ENFERMERA /O | C13: 13406 | D13: 4834 | E13: 8588 | F13: 0 | G13: 0 | H13: 0 | I13: 0 | J13: 0 | K13: 0 | L13: 0 | M13: 0 | N13: 0 | O13: 0 | P13: 0 | Q13: 0 | R13: 0 | S13: 0 | T13: 0 | U13: 0 | V13: 0 | W13: 0 | X13: 0 | Y13: 0 | Z13: 0 | AA13: 0 | AB13: 0 | AC13: 0 | AD13: 0 | AE13: 0 | AF13: 1200 | AG13: 2256 | AH13: 1466 | AI13: 2530 | AJ13: 1168 | AK13: 2022 | AL13: 998 | AM13: 1782 | AN13: 12840
A14: SEGUIMIENTO RIESGO DEPENDENCIA | B14: MÉDICO | C14: 676 | D14: 262 | E14: 374 | F14: 0 | G14: 0 | H14: 0 | I14: 0 | J14: 0 | K14: 0 | L14: 0 | M14: 0 | N14: 0 | O14: 0 | P14: 0 | Q14: 0 | R14: 0 | S14: 0 | T14: 0 | U14: 0 | V14: 0 | W14: 0 | X14: 0 | Y14: 0 | Z14: 0 | AA14: 0 | AB14: 0 | AC14: 0 | AD14: 0 | AE14: 0 | AF14: 30 | AG14: 38 | AH14: 34 | AI14: 70 | AJ14: 76 | AK14: 68 | AL14: 122 | AM14: 198 | AN14: 628
B15: ENFERMERA /O | C15: 8134 | D15: 2920 | E15: 5228 | F15: 0 | G15: 0 | H15: 0 | I15: 0 | J15: 0 | K15: 0 | L15: 0 | M15: 0 | N15: 0 | O15: 0 | P15: 0 | Q15: 0 | R15: 0 | S15: 0 | T15: 0 | U15: 0 | V15: 0 | W15: 0 | X15: 0 | Y15: 0 | Z15: 0 | AA15: 0 | AB15: 0 | AC15: 0 | AD15: 0 | AE15: 0 | AF15: 392 | AG15: 596 | AH15: 534 | AI15: 950 | AJ15: 678 | AK15: 1124 | AL15: 1318 | AM15: 2556 | AN15: 7768
A16: DE INFECCIÓN TRANSMISIÓN SEXUAL | B16: MÉDICO | C16: 2554 | D16: 864 | E16: 1676 | F16: 12 | G16: 10 | H16: 0 | I16: 0 | J16: 2 | K16: 12 | L16: 32 | M16: 84 | N16: 176 | O16: 314 | P16: 128 | Q16: 180 | R16: 68 | S16: 146 | T16: 78 | U16: 74 | V16: 48 | W16: 78 | X16: 26 | Y16: 122 | Z16: 46 | AA16: 160 | AB16: 32 | AC16: 142 | AD16: 46 | AE16: 74 | AF16: 20 | AG16: 96 | AH16: 48 | AI16: 62 | AJ16: 30 | AK16: 42 | AL16: 72 | AM16: 80 | AN16: 2518
B17: ENFERMERA /O | C17: 720 | D17: 314 | E17: 406 | F17: 6 | G17: 26 | H17: 0 | I17: 0 | J17: 0 | K17: 2 | L17: 18 | M17: 20 | N17: 38 | O17: 42 | P17: 62 | Q17: 52 | R17: 18 | S17: 36 | T17: 18 | U17: 32 | V17: 18 | W17: 16 | X17: 14 | Y17: 28 | Z17: 22 | AA17: 28 | AB17: 18 | AC17: 14 | AD17: 12 | AE17: 22 | AF17: 20 | AG17: 32 | AH17: 14 | AI17: 16 | AJ17: 18 | AK17: 12 | AL17: 18 | AM17: 28 | AN17: 712
B18: MATRONA /ÓN | C18: 6512 | D18: 1666 | E18: 4860 | F18: 14 | G18: 6 | H18: 8 | I18: 4 | J18: 2 | K18: 52 | L18: 188 | M18: 610 | N18: 378 | O18: 1102 | P18: 294 | Q18: 770 | R18: 230 | S18: 630 | T18: 106 | U18: 446 | V18: 80 | W18: 348 | X18: 66 | Y18: 334 | Z18: 72 | AA18: 212 | AB18: 70 | AC18: 124 | AD18: 44 | AE18: 90 | AF18: 30 | AG18: 36 | AH18: 50 | AI18: 38 | AJ18: 16 | AK18: 12 | AL18: 18 | AM18: 46 | AN18: 6374
A19: OTROS PROBLEMAS DE SALUD | B19: MÉDICO | C19: 610680 | D19: 176570 | E19: 434692 | F19: 6128 | G19: 5178 | H19: 3464 | I19: 3028 | J19: 3298 | K19: 3410 | L19: 3388 | M19: 5984 | N19: 3658 | O19: 9286 | P19: 4440 | Q19: 13998 | R19: 4554 | S19: 16588 | T19: 4668 | U19: 17846 | V19: 5792 | W19: 21446 | X19: 7510 | Y19: 28574 | Z19: 10966 | AA19: 37586 | AB19: 15114 | AC19: 48656 | AD19: 19000 | AE19: 50712 | AF19: 19384 | AG19: 48228 | AH19: 21714 | AI19: 43804 | AJ19: 18918 | AK19: 34622 | AL19: 24570 | AM19: 45786 | AN19: 597972
B20: ENFERMERA /O | C20: 81068 | D20: 32882 | E20: 47658 | F20: 992 | G20: 910 | H20: 390 | I20: 404 | J20: 192 | K20: 238 | L20: 226 | M20: 380 | N20: 298 | O20: 524 | P20: 404 | Q20: 754 | R20: 658 | S20: 1610 | T20: 744 | U20: 1280 | V20: 858 | W20: 1564 | X20: 1460 | Y20: 3080 | Z20: 2380 | AA20: 5110 | AB20: 3326 | AC20: 4794 | AD20: 4090 | AE20: 5458 | AF20: 3634 | AG20: 5454 | AH20: 3990 | AI20: 5428 | AJ20: 4390 | AK20: 4604 | AL20: 4850 | AM20: 6066 | AN20: 78426
B21: MATRONA /ÓN | C21: 12260 | D21: 1144 | E21: 11042 | F21: 658 | G21: 496 | H21: 44 | I21: 58 | J21: 20 | K21: 122 | L21: 46 | M21: 528 | N21: 40 | O21: 1052 | P21: 56 | Q21: 1208 | R21: 36 | S21: 938 | T21: 16 | U21: 918 | V21: 18 | W21: 782 | X21: 18 | Y21: 914 | Z21: 24 | AA21: 936 | AB21: 22 | AC21: 834 | AD21: 34 | AE21: 880 | AF21: 40 | AG21: 588 | AH21: 30 | AI21: 392 | AJ21: 24 | AK21: 226 | AL21: 18 | AM21: 170 | AN21: 12086
B22: NUTRICIONISTA | C22: 71728 | D22: 22806 | E22: 48946 | F22: 9360 | G22: 9550 | H22: 2062 | I22: 2154 | J22: 1076 | K22: 1272 | L22: 562 | M22: 2018 | N22: 446 | O22: 2704 | P22: 494 | Q22: 3466 | R22: 504 | S22: 3392 | T22: 518 | U22: 2742 | V22: 518 | W22: 2122 | X22: 558 | Y22: 2452 | Z22: 730 | AA22: 2716 | AB22: 924 | AC22: 2930 | AD22: 1056 | AE22: 2844 | AF22: 1072 | AG22: 2628 | AH22: 964 | AI22: 2520 | AJ22: 834 | AK22: 1414 | AL22: 1128 | AM22: 2022 | AN22: 69478
B23: TÉCNICO PARAMÉDICO | C23: 93126 | D23: 37148 | E23: 55954 | F23: 1364 | G23: 1784 | H23: 960 | I23: 882 | J23: 984 | K23: 1004 | L23: 1070 | M23: 2622 | N23: 1176 | O23: 3038 | P23: 1138 | Q23: 3470 | R23: 1212 | S23: 4058 | T23: 1402 | U23: 3224 | V23: 1680 | W23: 3326 | X23: 2294 | Y23: 4200 | Z23: 2860 | AA23: 4286 | AB23: 3356 | AC23: 4386 | AD23: 3788 | AE23: 4478 | AF23: 3564 | AG23: 4166 | AH23: 3774 | AI23: 3524 | AJ23: 2834 | AK23: 3380 | AL23: 3702 | AM23: 4118 | AN23: 89744
A24: NIÑOS CON NECESIDADES ESPECIALES | B24: MÉDICO | C24: 2702 | D24: 1618 | E24: 1084 | F24: 1260 | G24: 870 | H24: 250 | I24: 148 | J24: 72 | K24: 36 | L24: 34 | M24: 22 | N24: 2 | O24: 8 | P24: 0 | Q24: 0 | R24: 0 | S24: 0 | T24: 0 | U24: 0 | V24: 0 | W24: 0 | X24: 0 | Y24: 0 | Z24: 0 | AA24: 0 | AB24: 2 | AC24: 2 | AD24: 2 | AE24: 2 | AF24: 0 | AG24: 2 | AH24: 0 | AI24: 0 | AJ24: 0 | AK24: 0 | AL24: 0 | AM24: 0 | AN24: 2496
B25: ENFERMERA /O | C25: 6508 | D25: 3532 | E25: 2976 | F25: 3074 | G25: 2688 | H25: 370 | I25: 236 | J25: 66 | K25: 18 | L25: 18 | M25: 16 | N25: 4 | O25: 18 | P25: 0 | Q25: 0 | R25: 0 | S25: 0 | T25: 0 | U25: 0 | V25: 0 | W25: 0 | X25: 0 | Y25: 0 | Z25: 0 | AA25: 0 | AB25: 0 | AC25: 0 | AD25: 0 | AE25: 0 | AF25: 0 | AG25: 0 | AH25: 0 | AI25: 0 | AJ25: 0 | AK25: 0 | AL25: 0 | AM25: 0 | AN25: 5976
B26: MATRONA /ÓN | C26: 252 | D26: 130 | E26: 122 | F26: 98 | G26: 60 | H26: 16 | I26: 12 | J26: 6 | K26: 22 | L26: 8 | M26: 24 | N26: 2 | O26: 4 | P26: 0 | Q26: 0 | R26: 0 | S26: 0 | T26: 0 | U26: 0 | V26: 0 | W26: 0 | X26: 0 | Y26: 0 | Z26: 0 | AA26: 0 | AB26: 0 | AC26: 0 | AD26: 0 | AE26: 0 | AF26: 0 | AG26: 0 | AH26: 0 | AI26: 0 | AJ26: 0 | AK26: 0 | AL26: 0 | AM26: 0 | AN26: 222
B27: NUTRICIONISTA | C27: 2764 | D27: 1454 | E27: 1310 | F27: 1184 | G27: 1052 | H27: 170 | I27: 128 | J27: 64 | K27: 54 | L27: 26 | M27: 40 | N27: 10 | O27: 36 | P27: 2 | Q27: 0 | R27: 0 | S27: 0 | T27: 0 | U27: 0 | V27: 0 | W27: 0 | X27: 0 | Y27: 0 | Z27: 0 | AA27: 0 | AB27: 0 | AC27: 0 | AD27: 0 | AE27: 0 | AF27: 0 | AG27: 0 | AH27: 0 | AI27: 0 | AJ27: 0 | AK27: 0 | AL27: 0 | AM27: 0 | AN27: 2552
B28: TÉCNICO PARAMÉDICO | C28: 112 | D28: 72 | E28: 40 | F28: 54 | G28: 10 | H28: 12 | I28: 16 | J28: 0 | K28: 6 | L28: 6 | M28: 8 | N28: 0 | O28: 0 | P28: 0 | Q28: 0 | R28: 0 | S28: 0 | T28: 0 | U28: 0 | V28: 0 | W28: 0 | X28: 0 | Y28: 0 | Z28: 0 | AA28: 0 | AB28: 0 | AC28: 0 | AD28: 0 | AE28: 0 | AF28: 0 | AG28: 0 | AH28: 0 | AI28: 0 | AJ28: 0 | AK28: 0 | AL28: 0 | AM28: 0 | AN28: 100
A29: Servicio: Servicio de Salud Arica
A30: DE SALUD CARDIOVASCULAR | B30: MÉDICO | C30: 21746 | D30: 8324 | E30: 13422 | F30: 0 | G30: 0 | H30: 0 | I30: 0 | J30: 0 | K30: 0 | L30: 4 | M30: 16 | N30: 28 | O30: 50 | P30: 42 | Q30: 54 | R30: 86 | S30: 108 | T30: 162 | U30: 248 | V30: 218 | W30: 380 | X30: 386 | Y30: 732 | Z30: 642 | AA30: 1166 | AB30: 1012 | AC30: 1640 | AD30: 992 | AE30: 1864 | AF30: 1326 | AG30: 2000 | AH30: 1350 | AI30: 1770 | AJ30: 1080 | AK30: 1532 | AL30: 996 | AM30: 1862 | AN30: 21654
B31: ENFERMERA /O | C31: 21810 | D31: 8758 | E31: 13052 | F31: 0 | G31: 0 | H31: 0 | I31: 0 | J31: 0 | K31: 0 | L31: 8 | M31: 8 | N31: 22 | O31: 34 | P31: 54 | Q31: 56 | R31: 92 | S31: 138 | T31: 200 | U31: 198 | V31: 280 | W31: 456 | X31: 502 | Y31: 794 | Z31: 764 | AA31: 1226 | AB31: 992 | AC31: 1694 | AD31: 1098 | AE31: 1780 | AF31: 1368 | AG31: 1830 | AH31: 1282 | AI31: 1714 | AJ31: 994 | AK31: 1312 | AL31: 1102 | AM31: 1812 | AN31: 21792
B32: NUTRICIONISTA | C32: 7456 | D32: 2708 | E32: 4748 | F32: 0 | G32: 0 | H32: 0 | I32: 0 | J32: 0 | K32: 0 | L32: 0 | M32: 6 | N32: 10 | O32: 16 | P32: 20 | Q32: 22 | R32: 42 | S32: 56 | T32: 64 | U32: 102 | V32: 82 | W32: 138 | X32: 160 | Y32: 344 | Z32: 200 | AA32: 434 | AB32: 318 | AC32: 632 | AD32: 378 | AE32: 672 | AF32: 420 | AG32: 730 | AH32: 440 | AI32: 652 | AJ32: 310 | AK32: 462 | AL32: 264 | AM32: 482 | AN32: 7454
B33: TÉCNICO PARAMÉDICO | C33: 610 | D33: 284 | E33: 326 | F33: 0 | G33: 0 | H33: 0 | I33: 0 | J33: 0 | K33: 0 | L33: 0 | M33: 0 | N33: 0 | O33: 0 | P33: 2 | Q33: 0 | R33: 8 | S33: 14 | T33: 8 | U33: 6 | V33: 4 | W33: 12 | X33: 16 | Y33: 14 | Z33: 32 | AA33: 46 | AB33: 54 | AC33: 38 | AD33: 60 | AE33: 20 | AF33: 10 | AG33: 30 | AH33: 26 | AI33: 82 | AJ33: 58 | AK33: 32 | AL33: 6 | AM33: 32 | AN33: 584
A34: DE TUBERCULOSIS | B34: MÉDICO | C34: 740 | D34: 430 | E34: 310 | F34: 2 | G34: 2 | H34: 2 | I34: 0 | J34: 2 | K34: 14 | L34: 14 | M34: 0 | N34: 44 | O34: 32 | P34: 62 | Q34: 8 | R34: 24 | S34: 36 | T34: 22 | U34: 18 | V34: 18 | W34: 26 | X34: 64 | Y34: 18 | Z34: 34 | AA34: 44 | AB34: 30 | AC34: 32 | AD34: 22 | AE34: 22 | AF34: 18 | AG34: 30 | AH34: 24 | AI34: 16 | AJ34: 6 | AK34: 4 | AL34: 42 | AM34: 8 | AN34: 712
B35: ENFERMERA /O | C35: 388 | D35: 242 | E35: 146 | F35: 6 | G35: 0 | H35: 2 | I35: 4 | J35: 0 | K35: 0 | L35: 6 | M35: 2 | N35: 28 | O35: 16 | P35: 34 | Q35: 2 | R35: 10 | S35: 12 | T35: 10 | U35: 6 | V35: 14 | W35: 14 | X35: 12 | Y35: 2 | Z35: 6 | AA35: 24 | AB35: 26 | AC35: 16 | AD35: 24 | AE35: 4 | AF35: 14 | AG35: 20 | AH35: 12 | AI35: 6 | AJ35: 8 | AK35: 8 | AL35: 30 | AM35: 10 | AN35: 388
A36: SEGUIMIENTO AUTOVALENTE CON RIESGO | B36: MÉDICO | C36: 348 | D36: 138 | E36: 210 | F36: 0 | G36: 0 | H36: 0 | I36: 0 | J36: 0 | K36: 0 | L36: 0 | M36: 0 | N36: 0 | O36: 0 | P36: 0 | Q36: 0 | R36: 0 | S36: 0 | T36: 0 | U36: 0 | V36: 0 | W36: 0 | X36: 0 | Y36: 0 | Z36: 0 | AA36: 0 | AB36: 0 | AC36: 0 | AD36: 0 | AE36: 0 | AF36: 32 | AG36: 54 | AH36: 40 | AI36: 54 | AJ36: 16 | AK36: 50 | AL36: 50 | AM36: 52 | AN36: 342
B37: ENFERMERA /O | C37: 162 | D37: 62 | E37: 100 | F37: 0 | G37: 0 | H37: 0 | I37: 0 | J37: 0 | K37: 0 | L37: 0 | M37: 0 | N37: 0 | O37: 0 | P37: 0 | Q37: 0 | R37: 0 | S37: 0 | T37: 0 | U37: 0 | V37: 0 | W37: 0 | X37: 0 | Y37: 0 | Z37: 0 | AA37: 0 | AB37: 0 | AC37: 0 | AD37: 0 | AE37: 0 | AF37: 8 | AG37: 30 | AH37: 30 | AI37: 42 | AJ37: 14 | AK37: 20 | AL37: 10 | AM37: 8 | AN37: 162
A38: SEGUIMIENTO RIESGO DEPENDENCIA | B38: MÉDICO | C38: 96 | D38: 30 | E38: 66 | F38: 0 | G38: 0 | H38: 0 | I38: 0 | J38: 0 | K38: 0 | L38: 0 | M38: 0 | N38: 0 | O38: 0 | P38: 0 | Q38: 0 | R38: 0 | S38: 0 | T38: 0 | U38: 0 | V38: 0 | W38: 0 | X38: 0 | Y38: 0 | Z38: 0 | AA38: 0 | AB38: 0 | AC38: 0 | AD38: 0 | AE38: 0 | AF38: 4 | AG38: 10 | AH38: 2 | AI38: 12 | AJ38: 12 | AK38: 18 | AL38: 12 | AM38: 26 | AN38: 94
B39: ENFERMERA /O | C39: 104 | D39: 34 | E39: 70 | F39: 0 | G39: 0 | H39: 0 | I39: 0 | J39: 0 | K39: 0 | L39: 0 | M39: 0 | N39: 0 | O39: 0 | P39: 0 | Q39: 0 | R39: 0 | S39: 0 | T39: 0 | U39: 0 | V39: 0 | W39: 0 | X39: 0 | Y39: 0 | Z39: 0 | AA39: 0 | AB39: 0 | AC39: 0 | AD39: 0 | AE39: 0 | AF39: 4 | AG39: 8 | AH39: 2 | AI39: 18 | AJ39: 6 | AK39: 14 | AL39: 22 | AM39: 30 | AN39: 104
A40: DE INFECCIÓN TRANSMISIÓN SEXUAL | B40: MÉDICO | C40: 0 | D40: 0 | E40: 0 | F40: 0 | G40: 0 | H40: 0 | I40: 0 | J40: 0 | K40: 0 | L40: 0 | M40: 0 | N40: 0 | O40: 0 | P40: 0 | Q40: 0 | R40: 0 | S40: 0 | T40: 0 | U40: 0 | V40: 0 | W40: 0 | X40: 0 | Y40: 0 | Z40: 0 | AA40: 0 | AB40: 0 | AC40: 0 | AD40: 0 | AE40: 0 | AF40: 0 | AG40: 0 | AH40: 0 | AI40: 0 | AJ40: 0 | AK40: 0 | AL40: 0 | AM40: 0 | AN40: 0
B41: ENFERMERA /O | C41: 0 | D41: 0 | E41: 0 | F41: 0 | G41: 0 | H41: 0 | I41: 0 | J41: 0 | K41: 0 | L41: 0 | M41: 0 | N41: 0 | O41: 0 | P41: 0 | Q41: 0 | R41: 0 | S41: 0 | T41: 0 | U41: 0 | V41: 0 | W41: 0 | X41: 0 | Y41: 0 | Z41: 0 | AA41: 0 | AB41: 0 | AC41: 0 | AD41: 0 | AE41: 0 | AF41: 0 | AG41: 0 | AH41: 0 | AI41: 0 | AJ41: 0 | AK41: 0 | AL41: 0 | AM41: 0 | AN41: 0
B42: MATRONA /ÓN | C42: 0 | D42: 0 | E42: 0 | F42: 0 | G42: 0 | H42: 0 | I42: 0 | J42: 0 | K42: 0 | L42: 0 | M42: 0 | N42: 0 | O42: 0 | P42: 0 | Q42: 0 | R42: 0 | S42: 0 | T42: 0 | U42: 0 | V42: 0 | W42: 0 | X42: 0 | Y42: 0 | Z42: 0 | AA42: 0 | AB42: 0 | AC42: 0 | AD42: 0 | AE42: 0 | AF42: 0 | AG42: 0 | AH42: 0 | AI42: 0 | AJ42: 0 | AK42: 0 | AL42: 0 | AM42: 0 | AN42: 0
A43: OTROS PROBLEMAS DE SALUD | B43: MÉDICO | C43: 9040 | D43: 2174 | E43: 6866 | F43: 18 | G43: 14 | H43: 12 | I43: 8 | J43: 4 | K43: 8 | L43: 20 | M43: 54 | N43: 16 | O43: 106 | P43: 26 | Q43: 102 | R43: 18 | S43: 138 | T43: 30 | U43: 170 | V43: 34 | W43: 220 | X43: 70 | Y43: 334 | Z43: 88 | AA43: 496 | AB43: 168 | AC43: 630 | AD43: 148 | AE43: 728 | AF43: 278 | AG43: 910 | AH43: 398 | AI43: 1046 | AJ43: 354 | AK43: 852 | AL43: 492 | AM43: 1050 | AN43: 9006
B44: ENFERMERA /O | C44: 582 | D44: 150 | E44: 432 | F44: 4 | G44: 4 | H44: 0 | I44: 0 | J44: 4 | K44: 2 | L44: 0 | M44: 0 | N44: 0 | O44: 0 | P44: 2 | Q44: 4 | R44: 0 | S44: 2 | T44: 2 | U44: 2 | V44: 0 | W44: 8 | X44: 0 | Y44: 20 | Z44: 4 | AA44: 24 | AB44: 0 | AC44: 24 | AD44: 10 | AE44: 46 | AF44: 12 | AG44: 70 | AH44: 36 | AI44: 68 | AJ44: 22 | AK44: 44 | AL44: 54 | AM44: 114 | AN44: 580
B45: MATRONA /ÓN | C45: 0 | D45: 0 | E45: 0 | F45: 0 | G45: 0 | H45: 0 | I45: 0 | J45: 0 | K45: 0 | L45: 0 | M45: 0 | N45: 0 | O45: 0 | P45: 0 | Q45: 0 | R45: 0 | S45: 0 | T45: 0 | U45: 0 | V45: 0 | W45: 0 | X45: 0 | Y45: 0 | Z45: 0 | AA45: 0 | AB45: 0 | AC45: 0 | AD45: 0 | AE45: 0 | AF45: 0 | AG45: 0 | AH45: 0 | AI45: 0 | AJ45: 0 | AK45: 0 | AL45: 0 | AM45: 0 | AN45: 0
B46: NUTRICIONISTA | C46: 134 | D46: 24 | E46: 110 | F46: 20 | G46: 30 | H46: 0 | I46: 4 | J46: 0 | K46: 0 | L46: 0 | M46: 12 | N46: 0 | O46: 14 | P46: 0 | Q46: 18 | R46: 0 | S46: 14 | T46: 0 | U46: 10 | V46: 0 | W46: 2 | X46: 0 | Y46: 2 | Z46: 0 | AA46: 0 | AB46: 0 | AC46: 2 | AD46: 0 | AE46: 0 | AF46: 0 | AG46: 0 | AH46: 0 | AI46: 0 | AJ46: 2 | AK46: 2 | AL46: 2 | AM46: 0 | AN46: 134
B47: TÉCNICO PARAMÉDICO | C47: 34 | D47: 8 | E47: 26 | F47: 0 | G47: 0 | H47: 0 | I47: 0 | J47: 0 | K47: 0 | L47: 0 | M47: 0 | N47: 0 | O47: 2 | P47: 0 | Q47: 0 | R47: 0 | S47: 0 | T47: 0 | U47: 0 | V47: 0 | W47: 0 | X47: 0 | Y47: 0 | Z47: 0 | AA47: 6 | AB47: 0 | AC47: 2 | AD47: 2 | AE47: 4 | AF47: 4 | AG47: 2 | AH47: 0 | AI47: 0 | AJ47: 0 | AK47: 4 | AL47: 2 | AM47: 6 | AN47: 34
A48: NIÑOS CON NECESIDADES ESPECIALES | B48: MÉDICO | C48: 12 | D48: 4 | E48: 8 | F48: 4 | G48: 8 | H48: 0 | I48: 0 | J48: 0 | K48: 0 | L48: 0 | M48: 0 | N48: 0 | O48: 0 | P48: 0 | Q48: 0 | R48: 0 | S48: 0 | T48: 0 | U48: 0 | V48: 0 | W48: 0 | X48: 0 | Y48: 0 | Z48: 0 | AA48: 0 | AB48: 0 | AC48: 0 | AD48: 0 | AE48: 0 | AF48: 0 | AG48: 0 | AH48: 0 | AI48: 0 | AJ48: 0 | AK48: 0 | AL48: 0 | AM48: 0 | AN48: 12
B49: ENFERMERA /O | C49: 490 | D49: 294 | E49: 196 | F49: 286 | G49: 192 | H49: 8 | I49: 4 | J49: 0 | K49: 0 | L49: 0 | M49: 0 | N49: 0 | O49: 0 | P49: 0 | Q49: 0 | R49: 0 | S49: 0 | T49: 0 | U49: 0 | V49: 0 | W49: 0 | X49: 0 | Y49: 0 | Z49: 0 | AA49: 0 | AB49: 0 | AC49: 0 | AD49: 0 | AE49: 0 | AF49: 0 | AG49: 0 | AH49: 0 | AI49: 0 | AJ49: 0 | AK49: 0 | AL49: 0 | AM49: 0 | AN49: 484
B50: MATRONA /ÓN | C50: 4 | D50: 0 | E50: 4 | F50: 0 | G50: 4 | H50: 0 | I50: 0 | J50: 0 | K50: 0 | L50: 0 | M50: 0 | N50: 0 | O50: 0 | P50: 0 | Q50: 0 | R50: 0 | S50: 0 | T50: 0 | U50: 0 | V50: 0 | W50: 0 | X50: 0 | Y50: 0 | Z50: 0 | AA50: 0 | AB50: 0 | AC50: 0 | AD50: 0 | AE50: 0 | AF50: 0 | AG50: 0 | AH50: 0 | AI50: 0 | AJ50: 0 | AK50: 0 | AL50: 0 | AM50: 0 | AN50: 4
B51: NUTRICIONISTA | C51: 46 | D51: 36 | E51: 10 | F51: 36 | G51: 10 | H51: 0 | I51: 0 | J51: 0 | K51: 0 | L51: 0 | M51: 0 | N51: 0 | O51: 0 | P51: 0 | Q51: 0 | R51: 0 | S51: 0 | T51: 0 | U51: 0 | V51: 0 | W51: 0 | X51: 0 | Y51: 0 | Z51: 0 | AA51: 0 | AB51: 0 | AC51: 0 | AD51: 0 | AE51: 0 | AF51: 0 | AG51: 0 | AH51: 0 | AI51: 0 | AJ51: 0 | AK51: 0 | AL51: 0 | AM51: 0 | AN51: 46
B52: TÉCNICO PARAMÉDICO | C52: 0 | D52: 0 | E52: 0 | F52: 0 | G52: 0 | H52: 0 | I52: 0 | J52: 0 | K52: 0 | L52: 0 | M52: 0 | N52: 0 | O52: 0 | P52: 0 | Q52: 0 | R52: 0 | S52: 0 | T52: 0 | U52: 0 | V52: 0 | W52: 0 | X52: 0 | Y52: 0 | Z52: 0 | AA52: 0 | AB52: 0 | AC52: 0 | AD52: 0 | AE52: 0 | AF52: 0 | AG52: 0 | AH52: 0 | AI52: 0 | AJ52: 0 | AK52: 0 | AL52: 0 | AM52: 0 | AN52: 0
A53: Servicio: Servicio de Salud Iquique
A54: DE SALUD CARDIOVASCULAR | B54: MÉDICO | C54: 52072 | D54: 20128 | E54: 31944 | F54: 0 | G54: 0 | H54: 0 | I54: 0 | J54: 0 | K54: 0 | L54: 26 | M54: 36 | N54: 40 | O54: 106 | P54: 88 | Q54: 244 | R54: 190 | S54: 428 | T54: 308 | U54: 606 | V54: 618 | W54: 1062 | X54: 960 | Y54: 1756 | Z54: 1542 | AA54: 3024 | AB54: 2536 | AC54: 4274 | AD54: 2990 | AE54: 4934 | AF54: 3626 | AG54: 5232 | AH54: 3310 | AI54: 4320 | AJ54: 2070 | AK54: 2814 | AL54: 1824 | AM54: 3104 | AN54: 50214
B55: ENFERMERA /O | C55: 11528 | D55: 4930 | E55: 6598 | F55: 0 | G55: 0 | H55: 0 | I55: 0 | J55: 0 | K55: 0 | L55: 2 | M55: 6 | N55: 6 | O55: 8 | P55: 16 | Q55: 40 | R55: 24 | S55: 52 | T55: 68 | U55: 108 | V55: 78 | W55: 128 | X55: 164 | Y55: 220 | Z55: 258 | AA55: 370 | AB55: 294 | AC55: 590 | AD55: 410 | AE55: 670 | AF55: 554 | AG55: 866 | AH55: 614 | AI55: 788 | AJ55: 1188 | AK55: 1278 | AL55: 1254 | AM55: 1474 | AN55: 11002
B56: NUTRICIONISTA | C56: 7668 | D56: 2908 | E56: 4796 | F56: 0 | G56: 0 | H56: 0 | I56: 0 | J56: 0 | K56: 0 | L56: 10 | M56: 12 | N56: 12 | O56: 26 | P56: 36 | Q56: 64 | R56: 42 | S56: 108 | T56: 64 | U56: 122 | V56: 148 | W56: 220 | X56: 150 | Y56: 312 | Z56: 256 | AA56: 544 | AB56: 424 | AC56: 654 | AD56: 408 | AE56: 752 | AF56: 438 | AG56: 752 | AH56: 448 | AI56: 540 | AJ56: 232 | AK56: 368 | AL56: 204 | AM56: 322 | AN56: 6684
B57: TÉCNICO PARAMÉDICO | C57: 460 | D57: 228 | E57: 232 | F57: 0 | G57: 0 | H57: 0 | I57: 0 | J57: 0 | K57: 0 | L57: 0 | M57: 2 | N57: 2 | O57: 0 | P57: 0 | Q57: 0 | R57: 2 | S57: 0 | T57: 2 | U57: 2 | V57: 2 | W57: 4 | X57: 12 | Y57: 4 | Z57: 16 | AA57: 14 | AB57: 22 | AC57: 16 | AD57: 14 | AE57: 26 | AF57: 18 | AG57: 82 | AH57: 38 | AI57: 16 | AJ57: 54 | AK57: 18 | AL57: 46 | AM57: 48 | AN57: 456
A58: DE TUBERCULOSIS | B58: MÉDICO | C58: 2792 | D58: 1492 | E58: 1300 | F58: 14 | G58: 34 | H58: 18 | I58: 30 | J58: 30 | K58: 20 | L58: 62 | M58: 32 | N58: 102 | O58: 76 | P58: 124 | Q58: 162 | R58: 196 | S58: 160 | T58: 154 | U58: 134 | V58: 152 | W58: 68 | X58: 82 | Y58: 100 | Z58: 178 | AA58: 118 | AB58: 104 | AC58: 86 | AD58: 84 | AE58: 90 | AF58: 94 | AG58: 56 | AH58: 58 | AI58: 56 | AJ58: 28 | AK58: 32 | AL58: 12 | AM58: 46 | AN58: 2732
B59: ENFERMERA /O | C59: 6098 | D59: 3234 | E59: 2864 | F59: 12 | G59: 72 | H59: 48 | I59: 74 | J59: 34 | K59: 26 | L59: 126 | M59: 24 | N59: 192 | O59: 142 | P59: 354 | Q59: 590 | R59: 418 | S59: 330 | T59: 244 | U59: 428 | V59: 348 | W59: 196 | X59: 246 | Y59: 274 | Z59: 380 | AA59: 176 | AB59: 334 | AC59: 100 | AD59: 236 | AE59: 158 | AF59: 112 | AG59: 112 | AH59: 38 | AI59: 36 | AJ59: 80 | AK59: 34 | AL59: 32 | AM59: 92 | AN59: 5772
A60: SEGUIMIENTO AUTOVALENTE CON RIESGO | B60: MÉDICO | C60: 10 | D60: 4 | E60: 6 | F60: 0 | G60: 0 | H60: 0 | I60: 0 | J60: 0 | K60: 0 | L60: 0 | M60: 0 | N60: 0 | O60: 0 | P60: 0 | Q60: 0 | R60: 0 | S60: 0 | T60: 0 | U60: 0 | V60: 0 | W60: 0 | X60: 0 | Y60: 0 | Z60: 0 | AA60: 0 | AB60: 0 | AC60: 0 | AD60: 0 | AE60: 0 | AF60: 0 | AG60: 2 | AH60: 0 | AI60: 0 | AJ60: 0 | AK60: 2 | AL60: 4 | AM60: 2 | AN60: 8
B61: ENFERMERA /O | C61: 322 | D61: 108 | E61: 214 | F61: 0 | G61: 0 | H61: 0 | I61: 0 | J61: 0 | K61: 0 | L61: 0 | M61: 0 | N61: 0 | O61: 0 | P61: 0 | Q61: 0 | R61: 0 | S61: 0 | T61: 0 | U61: 0 | V61: 0 | W61: 0 | X61: 0 | Y61: 0 | Z61: 0 | AA61: 0 | AB61: 0 | AC61: 0 | AD61: 0 | AE61: 0 | AF61: 30 | AG61: 46 | AH61: 22 | AI61: 76 | AJ61: 16 | AK61: 42 | AL61: 38 | AM61: 52 | AN61: 322
A62: SEGUIMIENTO RIESGO DEPENDENCIA | B62: MÉDICO | C62: 14 | D62: 8 | E62: 6 | F62: 0 | G62: 0 | H62: 0 | I62: 0 | J62: 0 | K62: 0 | L62: 0 | M62: 0 | N62: 0 | O62: 0 | P62: 0 | Q62: 0 | R62: 0 | S62: 0 | T62: 0 | U62: 0 | V62: 0 | W62: 0 | X62: 0 | Y62: 0 | Z62: 0 | AA62: 0 | AB62: 0 | AC62: 0 | AD62: 0 | AE62: 0 | AF62: 0 | AG62: 2 | AH62: 0 | AI62: 2 | AJ62: 2 | AK62: 0 | AL62: 6 | AM62: 2 | AN62: 8
B63: ENFERMERA /O | C63: 314 | D63: 138 | E63: 176 | F63: 0 | G63: 0 | H63: 0 | I63: 0 | J63: 0 | K63: 0 | L63: 0 | M63: 0 | N63: 0 | O63: 0 | P63: 0 | Q63: 0 | R63: 0 | S63: 0 | T63: 0 | U63: 0 | V63: 0 | W63: 0 | X63: 0 | Y63: 0 | Z63: 0 | AA63: 0 | AB63: 0 | AC63: 0 | AD63: 0 | AE63: 0 | AF63: 32 | AG63: 22 | AH63: 18 | AI63: 24 | AJ63: 26 | AK63: 28 | AL63: 64 | AM63: 100 | AN63: 312
A64: DE INFECCIÓN TRANSMISIÓN SEXUAL | B64: MÉDICO | C64: 0 | D64: 0 | E64: 0 | F64: 0 | G64: 0 | H64: 0 | I64: 0 | J64: 0 | K64: 0 | L64: 0 | M64: 0 | N64: 0 | O64: 0 | P64: 0 | Q64: 0 | R64: 0 | S64: 0 | T64: 0 | U64: 0 | V64: 0 | W64: 0 | X64: 0 | Y64: 0 | Z64: 0 | AA64: 0 | AB64: 0 | AC64: 0 | AD64: 0 | AE64: 0 | AF64: 0 | AG64: 0 | AH64: 0 | AI64: 0 | AJ64: 0 | AK64: 0 | AL64: 0 | AM64: 0 | AN64: 0
B65: ENFERMERA /O | C65: 0 | D65: 0 | E65: 0 | F65: 0 | G65: 0 | H65: 0 | I65: 0 | J65: 0 | K65: 0 | L65: 0 | M65: 0 | N65: 0 | O65: 0 | P65: 0 | Q65: 0 | R65: 0 | S65: 0 | T65: 0 | U65: 0 | V65: 0 | W65: 0 | X65: 0 | Y65: 0 | Z65: 0 | AA65: 0 | AB65: 0 | AC65: 0 | AD65: 0 | AE65: 0 | AF65: 0 | AG65: 0 | AH65: 0 | AI65: 0 | AJ65: 0 | AK65: 0 | AL65: 0 | AM65: 0 | AN65: 0
B66: MATRONA /ÓN | C66: 6 | D66: 0 | E66: 6 | F66: 0 | G66: 0 | H66: 0 | I66: 0 | J66: 0 | K66: 0 | L66: 0 | M66: 0 | N66: 0 | O66: 0 | P66: 0 | Q66: 2 | R66: 0 | S66: 4 | T66: 0 | U66: 0 | V66: 0 | W66: 0 | X66: 0 | Y66: 0 | Z66: 0 | AA66: 0 | AB66: 0 | AC66: 0 | AD66: 0 | AE66: 0 | AF66: 0 | AG66: 0 | AH66: 0 | AI66: 0 | AJ66: 0 | AK66: 0 | AL66: 0 | AM66: 0 | AN66: 6
A67: OTROS PROBLEMAS DE SALUD | B67: MÉDICO | C67: 20226 | D67: 4748 | E67: 15478 | F67: 62 | G67: 58 | H67: 74 | I67: 54 | J67: 50 | K67: 60 | L67: 82 | M67: 150 | N67: 44 | O67: 326 | P67: 102 | Q67: 514 | R67: 112 | S67: 580 | T67: 80 | U67: 492 | V67: 110 | W67: 530 | X67: 166 | Y67: 706 | Z67: 200 | AA67: 1004 | AB67: 442 | AC67: 1708 | AD67: 664 | AE67: 1970 | AF67: 674 | AG67: 2324 | AH67: 708 | AI67: 1828 | AJ67: 548 | AK67: 1396 | AL67: 630 | AM67: 1770 | AN67: 17950
B68: ENFERMERA /O | C68: 1582 | D68: 496 | E68: 1086 | F68: 26 | G68: 8 | H68: 8 | I68: 8 | J68: 4 | K68: 2 | L68: 8 | M68: 20 | N68: 10 | O68: 38 | P68: 8 | Q68: 38 | R68: 16 | S68: 44 | T68: 10 | U68: 46 | V68: 24 | W68: 58 | X68: 38 | Y68: 62 | Z68: 34 | AA68: 122 | AB68: 62 | AC68: 142 | AD68: 40 | AE68: 102 | AF68: 42 | AG68: 106 | AH68: 54 | AI68: 100 | AJ68: 36 | AK68: 54 | AL68: 76 | AM68: 136 | AN68: 1494
B69: MATRONA /ÓN | C69: 582 | D69: 330 | E69: 252 | F69: 328 | G69: 232 | H69: 0 | I69: 0 | J69: 0 | K69: 0 | L69: 0 | M69: 10 | N69: 0 | O69: 6 | P69: 0 | Q69: 0 | R69: 0 | S69: 2 | T69: 0 | U69: 0 | V69: 2 | W69: 0 | X69: 0 | Y69: 2 | Z69: 0 | AA69: 0 | AB69: 0 | AC69: 0 | AD69: 0 | AE69: 0 | AF69: 0 | AG69: 0 | AH69: 0 | AI69: 0 | AJ69: 0 | AK69: 0 | AL69: 0 | AM69: 0 | AN69: 576
B70: NUTRICIONISTA | C70: 2446 | D70: 596 | E70: 1850 | F70: 132 | G70: 86 | H70: 14 | I70: 22 | J70: 14 | K70: 24 | L70: 8 | M70: 82 | N70: 6 | O70: 78 | P70: 22 | Q70: 112 | R70: 18 | S70: 130 | T70: 26 | U70: 94 | V70: 18 | W70: 86 | X70: 16 | Y70: 90 | Z70: 34 | AA70: 136 | AB70: 36 | AC70: 176 | AD70: 44 | AE70: 196 | AF70: 60 | AG70: 210 | AH70: 66 | AI70: 168 | AJ70: 30 | AK70: 82 | AL70: 52 | AM70: 78 | AN70: 2150
B71: TÉCNICO PARAMÉDICO | C71: 2634 | D71: 1518 | E71: 1116 | F71: 78 | G71: 48 | H71: 42 | I71: 46 | J71: 28 | K71: 36 | L71: 18 | M71: 30 | N71: 46 | O71: 36 | P71: 4 | Q71: 10 | R71: 6 | S71: 36 | T71: 12 | U71: 32 | V71: 20 | W71: 38 | X71: 78 | Y71: 54 | Z71: 36 | AA71: 18 | AB71: 40 | AC71: 40 | AD71: 36 | AE71: 62 | AF71: 708 | AG71: 240 | AH71: 150 | AI71: 134 | AJ71: 62 | AK71: 96 | AL71: 154 | AM71: 160 | AN71: 2500
A72: NIÑOS CON NECESIDADES ESPECIALES | B72: MÉDICO | C72: 444 | D72: 314 | E72: 130 | F72: 190 | G72: 90 | H72: 100 | I72: 40 | J72: 8 | K72: 0 | L72: 16 | M72: 0 | N72: 0 | O72: 0 | P72: 0 | Q72: 0 | R72: 0 | S72: 0 | T72: 0 | U72: 0 | V72: 0 | W72: 0 | X72: 0 | Y72: 0 | Z72: 0 | AA72: 0 | AB72: 0 | AC72: 0 | AD72: 0 | AE72: 0 | AF72: 0 | AG72: 0 | AH72: 0 | AI72: 0 | AJ72: 0 | AK72: 0 | AL72: 0 | AM72: 0 | AN72: 444
B73: ENFERMERA /O | C73: 154 | D73: 72 | E73: 82 | F73: 68 | G73: 78 | H73: 4 | I73: 4 | J73: 0 | K73: 0 | L73: 0 | M73: 0 | N73: 0 | O73: 0 | P73: 0 | Q73: 0 | R73: 0 | S73: 0 | T73: 0 | U73: 0 | V73: 0 | W73: 0 | X73: 0 | Y73: 0 | Z73: 0 | AA73: 0 | AB73: 0 | AC73: 0 | AD73: 0 | AE73: 0 | AF73: 0 | AG73: 0 | AH73: 0 | AI73: 0 | AJ73: 0 | AK73: 0 | AL73: 0 | AM73: 0 | AN73: 142
B74: MATRONA /ÓN | C74: 4 | D74: 4 | E74: 0 | F74: 4 | G74: 0 | H74: 0 | I74: 0 | J74: 0 | K74: 0 | L74: 0 | M74: 0 | N74: 0 | O74: 0 | P74: 0 | Q74: 0 | R74: 0 | S74: 0 | T74: 0 | U74: 0 | V74: 0 | W74: 0 | X74: 0 | Y74: 0 | Z74: 0 | AA74: 0 | AB74: 0 | AC74: 0 | AD74: 0 | AE74: 0 | AF74: 0 | AG74: 0 | AH74: 0 | AI74: 0 | AJ74: 0 | AK74: 0 | AL74: 0 | AM74: 0 | AN74: 4
B75: NUTRICIONISTA | C75: 164 | D75: 106 | E75: 58 | F75: 90 | G75: 44 | H75: 12 | I75: 6 | J75: 2 | K75: 6 | L75: 2 | M75: 2 | N75: 0 | O75: 0 | P75: 0 | Q75: 0 | R75: 0 | S75: 0 | T75: 0 | U75: 0 | V75: 0 | W75: 0 | X75: 0 | Y75: 0 | Z75: 0 | AA75: 0 | AB75: 0 | AC75: 0 | AD75: 0 | AE75: 0 | AF75: 0 | AG75: 0 | AH75: 0 | AI75: 0 | AJ75: 0 | AK75: 0 | AL75: 0 | AM75: 0 | AN75: 136
B76: TÉCNICO PARAMÉDICO | C76: 0 | D76: 0 | E76: 0 | F76: 0 | G76: 0 | H76: 0 | I76: 0 | J76: 0 | K76: 0 | L76: 0 | M76: 0 | N76: 0 | O76: 0 | P76: 0 | Q76: 0 | R76: 0 | S76: 0 | T76: 0 | U76: 0 | V76: 0 | W76: 0 | X76: 0 | Y76: 0 | Z76: 0 | AA76: 0 | AB76: 0 | AC76: 0 | AD76: 0 | AE76: 0 | AF76: 0 | AG76: 0 | AH76: 0 | AI76: 0 | AJ76: 0 | AK76: 0 | AL76: 0 | AM76: 0 | AN76: 0
A77: Servicio: Servicio de Salud Antofagasta
A78: DE SALUD CARDIOVASCULAR | B78: MÉDICO | C78: 67002 | D78: 23234 | E78: 43768 | F78: 0 | G78: 0 | H78: 0 | I78: 0 | J78: 0 | K78: 0 | L78: 38 | M78: 52 | N78: 62 | O78: 112 | P78: 92 | Q78: 222 | R78: 160 | S78: 386 | T78: 300 | U78: 824 | V78: 558 | W78: 1440 | X78: 1132 | Y78: 2790 | Z78: 1828 | AA78: 4056 | AB78: 3052 | AC78: 6084 | AD78: 3628 | AE78: 6684 | AF78: 3978 | AG78: 6302 | AH78: 3422 | AI78: 5524 | AJ78: 2396 | AK78: 4202 | AL78: 2588 | AM78: 5090 | AN78: 64460
B79: ENFERMERA /O | C79: 18332 | D79: 6340 | E79: 11992 | F79: 0 | G79: 0 | H79: 0 | I79: 0 | J79: 0 | K79: 0 | L79: 6 | M79: 20 | N79: 8 | O79: 22 | P79: 22 | Q79: 62 | R79: 54 | S79: 130 | T79: 64 | U79: 152 | V79: 116 | W79: 374 | X79: 224 | Y79: 738 | Z79: 458 | AA79: 1042 | AB79: 726 | AC79: 1396 | AD79: 894 | AE79: 1500 | AF79: 1068 | AG79: 1904 | AH79: 1040 | AI79: 1798 | AJ79: 866 | AK79: 1248 | AL79: 794 | AM79: 1606 | AN79: 17986
B80: NUTRICIONISTA | C80: 11272 | D80: 3710 | E80: 7562 | F80: 0 | G80: 0 | H80: 0 | I80: 0 | J80: 0 | K80: 0 | L80: 8 | M80: 28 | N80: 18 | O80: 26 | P80: 26 | Q80: 82 | R80: 46 | S80: 148 | T80: 94 | U80: 264 | V80: 142 | W80: 320 | X80: 224 | Y80: 684 | Z80: 328 | AA80: 914 | AB80: 538 | AC80: 1272 | AD80: 664 | AE80: 1048 | AF80: 574 | AG80: 960 | AH80: 454 | AI80: 752 | AJ80: 304 | AK80: 602 | AL80: 290 | AM80: 462 | AN80: 11090
B81: TÉCNICO PARAMÉDICO | C81: 146 | D81: 62 | E81: 84 | F81: 0 | G81: 0 | H81: 0 | I81: 0 | J81: 0 | K81: 0 | L81: 0 | M81: 0 | N81: 0 | O81: 0 | P81: 0 | Q81: 0 | R81: 0 | S81: 6 | T81: 8 | U81: 0 | V81: 0 | W81: 2 | X81: 0 | Y81: 4 | Z81: 12 | AA81: 14 | AB81: 2 | AC81: 2 | AD81: 4 | AE81: 10 | AF81: 6 | AG81: 10 | AH81: 12 | AI81: 22 | AJ81: 2 | AK81: 4 | AL81: 16 | AM81: 10 | AN81: 146
A82: DE TUBERCULOSIS | B82: MÉDICO | C82: 976 | D82: 472 | E82: 504 | F82: 4 | G82: 4 | H82: 2 | I82: 10 | J82: 2 | K82: 12 | L82: 14 | M82: 16 | N82: 56 | O82: 28 | P82: 74 | Q82: 120 | R82: 52 | S82: 78 | T82: 48 | U82: 46 | V82: 50 | W82: 26 | X82: 34 | Y82: 24 | Z82: 26 | AA82: 14 | AB82: 22 | AC82: 38 | AD82: 60 | AE82: 26 | AF82: 0 | AG82: 14 | AH82: 8 | AI82: 38 | AJ82: 14 | AK82: 4 | AL82: 6 | AM82: 6 | AN82: 882
B83: ENFERMERA /O | C83: 442 | D83: 230 | E83: 212 | F83: 2 | G83: 22 | H83: 2 | I83: 6 | J83: 6 | K83: 4 | L83: 2 | M83: 6 | N83: 22 | O83: 6 | P83: 28 | Q83: 44 | R83: 18 | S83: 20 | T83: 22 | U83: 24 | V83: 16 | W83: 14 | X83: 18 | Y83: 28 | Z83: 34 | AA83: 4 | AB83: 10 | AC83: 6 | AD83: 22 | AE83: 6 | AF83: 2 | AG83: 2 | AH83: 18 | AI83: 18 | AJ83: 2 | AK83: 0 | AL83: 6 | AM83: 2 | AN83: 406
A84: SEGUIMIENTO AUTOVALENTE CON RIESGO | B84: MÉDICO | C84: 76 | D84: 26 | E84: 50 | F84: 0 | G84: 0 | H84: 0 | I84: 0 | J84: 0 | K84: 0 | L84: 0 | M84: 0 | N84: 0 | O84: 0 | P84: 0 | Q84: 0 | R84: 0 | S84: 0 | T84: 0 | U84: 0 | V84: 0 | W84: 0 | X84: 0 | Y84: 0 | Z84: 0 | AA84: 0 | AB84: 0 | AC84: 0 | AD84: 0 | AE84: 0 | AF84: 6 | AG84: 10 | AH84: 2 | AI84: 12 | AJ84: 12 | AK84: 16 | AL84: 6 | AM84: 12 | AN84: 78
B85: ENFERMERA /O | C85: 1618 | D85: 524 | E85: 1094 | F85: 0 | G85: 0 | H85: 0 | I85: 0 | J85: 0 | K85: 0 | L85: 0 | M85: 0 | N85: 0 | O85: 0 | P85: 0 | Q85: 0 | R85: 0 | S85: 0 | T85: 0 | U85: 0 | V85: 0 | W85: 0 | X85: 0 | Y85: 0 | Z85: 0 | AA85: 0 | AB85: 0 | AC85: 0 | AD85: 0 | AE85: 0 | AF85: 104 | AG85: 258 | AH85: 156 | AI85: 294 | AJ85: 142 | AK85: 278 | AL85: 122 | AM85: 264 | AN85: 1370
A86: SEGUIMIENTO RIESGO DEPENDENCIA | B86: MÉDICO | C86: 30 | D86: 12 | E86: 18 | F86: 0 | G86: 0 | H86: 0 | I86: 0 | J86: 0 | K86: 0 | L86: 0 | M86: 0 | N86: 0 | O86: 0 | P86: 0 | Q86: 0 | R86: 0 | S86: 0 | T86: 0 | U86: 0 | V86: 0 | W86: 0 | X86: 0 | Y86: 0 | Z86: 0 | AA86: 0 | AB86: 0 | AC86: 0 | AD86: 0 | AE86: 0 | AF86: 2 | AG86: 2 | AH86: 0 | AI86: 0 | AJ86: 4 | AK86: 2 | AL86: 6 | AM86: 14 | AN86: 30
B87: ENFERMERA /O | C87: 936 | D87: 328 | E87: 608 | F87: 0 | G87: 0 | H87: 0 | I87: 0 | J87: 0 | K87: 0 | L87: 0 | M87: 0 | N87: 0 | O87: 0 | P87: 0 | Q87: 0 | R87: 0 | S87: 0 | T87: 0 | U87: 0 | V87: 0 | W87: 0 | X87: 0 | Y87: 0 | Z87: 0 | AA87: 0 | AB87: 0 | AC87: 0 | AD87: 0 | AE87: 0 | AF87: 38 | AG87: 56 | AH87: 54 | AI87: 70 | AJ87: 46 | AK87: 108 | AL87: 190 | AM87: 374 | AN87: 814
A88: DE INFECCIÓN TRANSMISIÓN SEXUAL | B88: MÉDICO | C88: 8 | D88: 8 | E88: 0 | F88: 0 | G88: 0 | H88: 0 | I88: 0 | J88: 0 | K88: 0 | L88: 0 | M88: 0 | N88: 2 | O88: 0 | P88: 0 | Q88: 0 | R88: 4 | S88: 0 | T88: 0 | U88: 0 | V88: 0 | W88: 0 | X88: 0 | Y88: 0 | Z88: 2 | AA88: 0 | AB88: 0 | AC88: 0 | AD88: 0 | AE88: 0 | AF88: 0 | AG88: 0 | AH88: 0 | AI88: 0 | AJ88: 0 | AK88: 0 | AL88: 0 | AM88: 0 | AN88: 8
B89: ENFERMERA /O | C89: 0 | D89: 0 | E89: 0 | F89: 0 | G89: 0 | H89: 0 | I89: 0 | J89: 0 | K89: 0 | L89: 0 | M89: 0 | N89: 0 | O89: 0 | P89: 0 | Q89: 0 | R89: 0 | S89: 0 | T89: 0 | U89: 0 | V89: 0 | W89: 0 | X89: 0 | Y89: 0 | Z89: 0 | AA89: 0 | AB89: 0 | AC89: 0 | AD89: 0 | AE89: 0 | AF89: 0 | AG89: 0 | AH89: 0 | AI89: 0 | AJ89: 0 | AK89: 0 | AL89: 0 | AM89: 0 | AN89: 0
B90: MATRONA /ÓN | C90: 428 | D90: 130 | E90: 298 | F90: 0 | G90: 0 | H90: 0 | I90: 0 | J90: 0 | K90: 4 | L90: 0 | M90: 26 | N90: 44 | O90: 56 | P90: 10 | Q90: 38 | R90: 6 | S90: 28 | T90: 12 | U90: 8 | V90: 2 | W90: 14 | X90: 12 | Y90: 50 | Z90: 4 | AA90: 10 | AB90: 8 | AC90: 12 | AD90: 4 | AE90: 14 | AF90: 8 | AG90: 10 | AH90: 12 | AI90: 6 | AJ90: 2 | AK90: 10 | AL90: 6 | AM90: 12 | AN90: 412
A91: OTROS PROBLEMAS DE SALUD | B91: MÉDICO | C91: 34498 | D91: 10798 | E91: 23700 | F91: 70 | G91: 66 | H91: 56 | I91: 22 | J91: 50 | K91: 56 | L91: 66 | M91: 106 | N91: 100 | O91: 212 | P91: 82 | Q91: 264 | R91: 60 | S91: 834 | T91: 112 | U91: 502 | V91: 142 | W91: 622 | X91: 484 | Y91: 1586 | Z91: 786 | AA91: 2178 | AB91: 1294 | AC91: 3060 | AD91: 1832 | AE91: 3240 | AF91: 1140 | AG91: 2900 | AH91: 1714 | AI91: 2694 | AJ91: 1122 | AK91: 2388 | AL91: 1688 | AM91: 2970 | AN91: 31962
B92: ENFERMERA /O | C92: 10550 | D92: 4442 | E92: 6108 | F92: 10 | G92: 6 | H92: 4 | I92: 2 | J92: 0 | K92: 0 | L92: 2 | M92: 4 | N92: 24 | O92: 0 | P92: 6 | Q92: 6 | R92: 22 | S92: 508 | T92: 8 | U92: 92 | V92: 4 | W92: 68 | X92: 376 | Y92: 740 | Z92: 522 | AA92: 978 | AB92: 750 | AC92: 1048 | AD92: 1014 | AE92: 818 | AF92: 146 | AG92: 538 | AH92: 614 | AI92: 428 | AJ92: 342 | AK92: 618 | AL92: 598 | AM92: 254 | AN92: 10344
B93: MATRONA /ÓN | C93: 294 | D93: 14 | E93: 280 | F93: 0 | G93: 0 | H93: 0 | I93: 0 | J93: 2 | K93: 4 | L93: 4 | M93: 26 | N93: 0 | O93: 38 | P93: 0 | Q93: 34 | R93: 0 | S93: 30 | T93: 0 | U93: 36 | V93: 0 | W93: 30 | X93: 0 | Y93: 10 | Z93: 2 | AA93: 12 | AB93: 2 | AC93: 4 | AD93: 0 | AE93: 40 | AF93: 4 | AG93: 2 | AH93: 0 | AI93: 2 | AJ93: 0 | AK93: 6 | AL93: 0 | AM93: 6 | AN93: 292
B94: NUTRICIONISTA | C94: 3034 | D94: 732 | E94: 2302 | F94: 238 | G94: 296 | H94: 88 | I94: 146 | J94: 30 | K94: 34 | L94: 12 | M94: 58 | N94: 12 | O94: 88 | P94: 6 | Q94: 134 | R94: 12 | S94: 142 | T94: 18 | U94: 138 | V94: 20 | W94: 110 | X94: 20 | Y94: 156 | Z94: 22 | AA94: 178 | AB94: 38 | AC94: 196 | AD94: 42 | AE94: 176 | AF94: 36 | AG94: 148 | AH94: 54 | AI94: 130 | AJ94: 38 | AK94: 104 | AL94: 46 | AM94: 68 | AN94: 3022
B95: TÉCNICO PARAMÉDICO | C95: 8200 | D95: 3710 | E95: 4490 | F95: 24 | G95: 20 | H95: 4 | I95: 4 | J95: 4 | K95: 2 | L95: 0 | M95: 0 | N95: 22 | O95: 0 | P95: 0 | Q95: 0 | R95: 0 | S95: 490 | T95: 0 | U95: 52 | V95: 2 | W95: 14 | X95: 354 | Y95: 676 | Z95: 478 | AA95: 842 | AB95: 702 | AC95: 848 | AD95: 938 | AE95: 650 | AF95: 20 | AG95: 272 | AH95: 456 | AI95: 172 | AJ95: 238 | AK95: 420 | AL95: 468 | AM95: 28 | AN95: 8008
A96: NIÑOS CON NECESIDADES ESPECIALES | B96: MÉDICO | C96: 456 | D96: 300 | E96: 156 | F96: 230 | G96: 124 | H96: 50 | I96: 12 | J96: 20 | K96: 12 | L96: 0 | M96: 8 | N96: 0 | O96: 0 | P96: 0 | Q96: 0 | R96: 0 | S96: 0 | T96: 0 | U96: 0 | V96: 0 | W96: 0 | X96: 0 | Y96: 0 | Z96: 0 | AA96: 0 | AB96: 0 | AC96: 0 | AD96: 0 | AE96: 0 | AF96: 0 | AG96: 0 | AH96: 0 | AI96: 0 | AJ96: 0 | AK96: 0 | AL96: 0 | AM96: 0 | AN96: 410
B97: ENFERMERA /O | C97: 278 | D97: 152 | E97: 126 | F97: 126 | G97: 104 | H97: 14 | I97: 16 | J97: 6 | K97: 4 | L97: 6 | M97: 0 | N97: 0 | O97: 2 | P97: 0 | Q97: 0 | R97: 0 | S97: 0 | T97: 0 | U97: 0 | V97: 0 | W97: 0 | X97: 0 | Y97: 0 | Z97: 0 | AA97: 0 | AB97: 0 | AC97: 0 | AD97: 0 | AE97: 0 | AF97: 0 | AG97: 0 | AH97: 0 | AI97: 0 | AJ97: 0 | AK97: 0 | AL97: 0 | AM97: 0 | AN97: 252
B98: MATRONA /ÓN | C98: 6 | D98: 0 | E98: 6 | F98: 0 | G98: 2 | H98: 0 | I98: 2 | J98: 0 | K98: 2 | L98: 0 | M98: 0 | N98: 0 | O98: 0 | P98: 0 | Q98: 0 | R98: 0 | S98: 0 | T98: 0 | U98: 0 | V98: 0 | W98: 0 | X98: 0 | Y98: 0 | Z98: 0 | AA98: 0 | AB98: 0 | AC98: 0 | AD98: 0 | AE98: 0 | AF98: 0 | AG98: 0 | AH98: 0 | AI98: 0 | AJ98: 0 | AK98: 0 | AL98: 0 | AM98: 0 | AN98: 8
B99: NUTRICIONISTA | C99: 118 | D99: 66 | E99: 52 | F99: 54 | G99: 50 | H99: 10 | I99: 0 | J99: 2 | K99: 2 | L99: 0 | M99: 0 | N99: 0 | O99: 0 | P99: 0 | Q99: 0 | R99: 0 | S99: 0 | T99: 0 | U99: 0 | V99: 0 | W99: 0 | X99: 0 | Y99: 0 | Z99: 0 | AA99: 0 | AB99: 0 | AC99: 0 | AD99: 0 | AE99: 0 | AF99: 0 | AG99: 0 | AH99: 0 | AI99: 0 | AJ99: 0 | AK99: 0 | AL99: 0 | AM99: 0 | AN99: 104
B100: TÉCNICO PARAMÉDICO | C100: 0 | D100: 0 | E100: 0 | F100: 0 | G100: 0 | H100: 0 | I100: 0 | J100: 0 | K100: 0 | L100: 0 | M100: 0 | N100: 0 | O100: 0 | P100: 0 | Q100: 0 | R100: 0 | S100: 0 | T100: 0 | U100: 0 | V100: 0 | W100: 0 | X100: 0 | Y100: 0 | Z100: 0 | AA100: 0 | AB100: 0 | AC100: 0 | AD100: 0 | AE100: 0 | AF100: 0 | AG100: 0 | AH100: 0 | AI100: 0 | AJ100: 0 | AK100: 0 | AL100: 0 | AM100: 0 | AN100: 0
...

Sheet Salud1(Mex)
A2: Egresos hospitalarios por año (SSA y SESAS)
A4: Entidad Federativa | B4: 2017 | C4: 2018 | D4: 2019 | E4: 2020 | F4: 2021 | G4: 2022 | H4: 2023 | I4: 2024 | J4: 2025
A5: AGS | B5: 43976 | C5: 39160 | D5: 37825 | E5: 31486 | F5: 33526 | G5: 34923 | H5: 35167 | I5: 35936 | J5: 25687
A6: BC | B6: 38449 | C6: 40627 | D6: 37499 | E6: 26697 | F6: 33584 | G6: 37977 | H6: 40959 | I6: 43610 | J6: 31368
A7: BCS | B7: 19721 | C7: 19639 | D7: 22636 | E7: 17080 | F7: 24323 | G7: 27126 | H7: 31728 | I7: 32455 | J7: 24143
A8: CAMP | B8: 26668 | C8: 24245 | D8: 23075 | E8: 16834 | F8: 18217 | G8: 19500 | H8: 22091 | I8: 21408 | J8: 17982
A9: COAH | B9: 41680 | C9: 39205 | D9: 36817 | E9: 29006 | F9: 32428 | G9: 32065 | H9: 31522 | I9: 31107 | J9: 24206
A10: COL | B10: 18983 | C10: 19049 | D10: 20795 | E10: 15952 | F10: 14551 | G10: 15774 | H10: 18672 | I10: 17706 | J10: 11701
A11: CHIS | B11: 113046 | C11: 108258 | D11: 114798 | E11: 79558 | F11: 97022 | G11: 120604 | H11: 124852 | I11: 125628 | J11: 105481
A12: CHI | B12: 75903 | C12: 81911 | D12: 78937 | E12: 59790 | F12: 60667 | G12: 69114 | H12: 65958 | I12: 66591 | J12: 55790
A13: CDMX | B13: 235581 | C13: 249752 | D13: 219172 | E13: 171663 | F13: 189816 | G13: 216538 | H13: 228731 | I13: 242649 | J13: 170624
A14: DGO | B14: 49616 | C14: 48582 | D14: 53790 | E14: 41804 | F14: 40200 | G14: 43789 | H14: 54898 | I14: 55882 | J14: 37339
A15: GTO | B15: 161800 | C15: 158514 | D15: 166531 | E15: 129901 | F15: 136248 | G15: 150414 | H15: 164111 | I15: 161359 | J15: 131935
... A37: Nacional | B37: 2715624 | C37: 2623379 | D37: 2629434 | E37: 1937344 | F37: 2088779 | G37: 2292018 | H37: 2404015 | I37: 2477749 | J37: 1915503

Sheet Salud2(Mex)
A1: Nacimientos/por año
A3: Entidad Federativa | B3: 2008 | C3: 2009 | D3: 2010 | E3: 2011 | F3: 2012 | G3: 2013 | H3: 2014 | I3: 2015 | J3: 2016 | K3: 2017 | L3: 2018 | M3: 2019 | N3: 2020 | O3: 2021 | P3: 2022 | Q3: 2023 | R3: 2024
A4: AGS | B4: 25783 | C4: 26065 | D4: 25830 | E4: 26983 | F4: 27280 | G4: 27200 | H4: 27207 | I4: 27104 | J4: 27020 | K4: 27149 | L4: 25398 | M4: 24690 | N4: 21456 | O4: 21050 | P4: 19701 | Q4: 18962 | R4: 12065
A5: BC | B5: 46834 | C5: 57642 | D5: 55716 | E5: 56655 | F5: 58135 | G5: 56694 | H5: 55404 | I5: 53813 | J5: 52752 | K5: 53280 | L5: 50497 | M5: 48102 | N5: 46622 | O5: 45075 | P5: 43651 | Q5: 40654 | R5: 31536
A6: BCS | B6: 11240 | C6: 12149 | D6: 12711 | E6: 12622 | F6: 12885 | G6: 12457 | H6: 12602 | I6: 12347 | J6: 12033 | K6: 11985 | L6: 11885 | M6: 11400 | N6: 11039 | O6: 9867 | P6: 10539 | Q6: 10098 | R6: 7771
A7: CAMP | B7: 13891 | C7: 14977 | D7: 15648 | E7: 15838 | F7: 16337 | G7: 16820 | H7: 16689 | I7: 17197 | J7: 15872 | K7: 14730 | L7: 13419 | M7: 13870 | N7: 13552 | O7: 12365 | P7: 12284 | Q7: 11472 | R7: 8903
A8: COAH | B8: 54570 | C8: 54465 | D8: 53725 | E8: 55705 | F8: 58151 | G8: 59245 | H8: 59530 | I8: 60064 | J8: 58552 | K8: 56932 | L8: 54153 | M8: 51663 | N8: 47930 | O8: 44410 | P8: 43172 | Q8: 40790 | R8: 32872
A9: COL | B9: 11345 | C9: 12162 | D9: 11912 | E9: 12713 | F9: 12728 | G9: 12291 | H9: 12368 | I9: 11755 | J9: 11251 | K9: 11073 | L9: 10774 | M9: 10291 | N9: 9345 | O9: 9099 | P9: 8706 | Q9: 8256 | R9: 6194
A10: CHIS | B10: 65470 | C10: 75815 | D10: 77007 | E10: 85226 | F10: 88385 | G10: 91189 | H10: 93992 | I10: 94731 | J10: 89008 | K10: 93099 | L10: 77559 | M10: 85475 | N10: 78663 | O10: 89194 | P10: 87692 | Q10: 78470 | R10: 56353
A11: CHI | B11: 54022 | C11: 59679 | D11: 62096 | E11: 62889 | F11: 63068 | G11: 61812 | H11: 60896 | I11: 62109 | J11: 61396 | K11: 61319 | L11: 57347 | M11: 53294 | N11: 51684 | O11: 48119 | P11: 47348 | Q11: 45290 | R11: 35691
A12: CDMX | B12: 119403 | C12: 127439 | D12: 130460 | E12: 137315 | F12: 139491 | G12: 135962 | H12: 133765 | I12: 126319 | J12: 120016 | K12: 113157 | L12: 101463 | M12: 96916 | N12: 87005 | O12: 77476 | P12: 80892 | Q12: 78032 | R12: 61237
A13: DGO | B13: 29959 | C13: 33889 | D13: 35237 | E13: 36189 | F13: 36180 | G13: 36371 | H13: 35102 | I13: 35320 | J13: 34949 | K13: 34266 | L13: 31814 | M13: 30006 | N13: 28285 | O13: 27611 | P13: 27020 | Q13: 24623 | R13: 19277
A14: GTO | B14: 116814 | C14: 116462 | D14: 118769 | E14: 120082 | F14: 120609 | G14: 117425 | H14: 115638 | I14: 115405 | J14: 114312 | K14: 115837 | L14: 110821 | M14: 105027 | N14: 97201 | O14: 90320 | P14: 88531 | Q14: 82942 | R14: 65651
... A36: Nacional | B36: 1962142 | C36: 2047450 | D36: 2063020 | E36: 2157702 | F36: 2199066 | G36: 2190258 | H36: 2171869 | I36: 2139889 | J36: 2074338 | K36: 2059158 | L36: 1935165 | M36: 1863432 | N36: 1744277 | O36: 1636698 | P36: 1620613 | Q36: 1519738 | R36: 1156181

Sheet Salud3(Mex)
A1: DIFUNCIONES POR AÑO
A2: Entidad Federativa | B2: 1998 | C2: 1999 | D2: 2000 | E2: 2001 | F2: 2002 | G2: 2003 | H2: 2004 | I2: 2005 | J2: 2006 | K2: 2007 | L2: 2008 | M2: 2009 | N2: 2010 | O2: 2011 | P2: 2012 | Q2: 2013 | R2: 2014 | S2: 2015 | T2: 2016 | U2: 2017 | V2: 2018 | W2: 2019 | X2: 2020 | Y2: 2021 | Z2: 2022 | AA2: 2023
A3: AGS | B3: 3783 | C3: 3917 | D3: 3728 | E3: 3826 | F3: 4301 | G3: 4293 | H3: 4242 | I3: 4431 | J3: 4488 | K3: 4694 | L3: 4955 | M3: 4987 | N3: 5177 | O3: 4934 | P3: 5267 | Q3: 5522 | R3: 5567 | S3: 5636 | T3: 5910 | U3: 6158 | V3: 6226 | W3: 6768 | X3: 9548 | Y3: 9712 | Z3: 8081 | AA3: 7343
A4: BC | B4: 10910 | C4: 11301 | D4: 11364 | E4: 11090 | F4: 11365 | G4: 11918 | H4: 12422 | I4: 12695 | J4: 12696 | K4: 13069 | L4: 14052 | M4: 15232 | N4: 15400 | O4: 14922 | P4: 14756 | Q4: 15947 | R4: 16198 | S4: 17152 | T4: 18253 | U4: 19073 | V4: 20501 | W4: 20924 | X4: 32662 | Y4: 28596 | Z4: 24693 | AA4: 22497
A5: BCS | B5: 1553 | C5: 1665 | D5: 1697 | E5: 1782 | F5: 1785 | G5: 1925 | H5: 1911 | I5: 2092 | J5: 2171 | K5: 2353 | L5: 2385 | M5: 2476 | N5: 2434 | O5: 2602 | P5: 2739 | Q5: 2757 | R5: 2826 | S5: 3175 | T5: 3183 | U5: 3826 | V5: 3447 | W5: 3556 | X5: 4867 | Y5: 5925 | Z5: 4302 | AA5: 4020
A6: CAMP | B6: 2709 | C6: 2544 | D6: 2526 | E6: 2493 | F6: 2750 | G6: 2827 | H6: 2946 | I6: 3019 | J6: 3084 | K6: 3186 | L6: 3516 | M6: 3651 | N6: 3820 | O6: 3736 | P6: 3964 | Q6: 4139 | R6: 4249 | S6: 4714 | T6: 4932 | U6: 4631 | V6: 4835 | W6: 5121 | X6: 7549 | Y6: 7509 | Z6: 5687 | AA6: 5589
A7: COAH | B7: 10202 | C7: 9706 | D7: 10229 | E7: 10748 | F7: 11030 | G7: 11458 | H7: 11044 | I7: 12377 | J7: 11955 | K7: 12626 | L7: 12981 | M7: 13792 | N7: 14593 | O7: 14640 | P7: 15200 | Q7: 15716 | R7: 16466 | S7: 16167 | T7: 16605 | U7: 16660 | V7: 17013 | W7: 17794 | X7: 28190 | Y7: 23814 | Z7: 21209 | AA7: 19540
A8: COL | B8: 2370 | C8: 2351 | D8: 2412 | E8: 2449 | F8: 2512 | G8: 2442 | H8: 2594 | I8: 2759 | J8: 2831 | K8: 2866 | L8: 3052 | M8: 3107 | N8: 3223 | O8: 3514 | P8: 3717 | Q8: 3790 | R8: 3790 | S8: 4408 | T8: 4486 | U8: 4593 | V8: 4533 | W8: 4566 | X8: 6057 | Y8: 7121 | Z8: 5683 | AA8: 5594
A9: CHIS | B9: 16413 | C9: 15204 | D9: 15253 | E9: 15815 | F9: 16424 | G9: 16889 | H9: 16692 | I9: 17411 | J9: 18287 | K9: 18767 | L9: 19570 | M9: 20378 | N9: 21721 | O9: 21199 | P9: 22411 | Q9: 23121 | R9: 24568 | S9: 26519 | T9: 26691 | U9: 26986 | V9: 27263 | W9: 28317 | X9: 38908 | Y9: 39865 | Z9: 31706 | AA9: 30742
A10: CHI | B10: 15386 | C10: 15517 | D10: 15358 | E10: 15905 | F10: 16494 | G10: 17033 | H10: 16277 | I10: 17239 | J10: 17963 | K10: 18064 | L10: 21066 | M10: 22255 | N10: 25809 | O10: 24121 | P10: 22187 | Q10: 22314 | R10: 22163 | S10: 22416 | T10: 23400 | U10: 23802 | V10: 23836 | W10: 24964 | X10: 39246 | Y10: 31716 | Z10: 28824 | AA10: 27341
A11: CDMX | B11: 46773 | C11: 46601 | D11: 46029 | E11: 46627 | F11: 46984 | G11: 48586 | H11: 48950 | I11: 49882 | J11: 49894 | K11: 51465 | L11: 52404 | M11: 53801 | N11: 55106 | O11: 54629 | P11: 55995 | Q11: 57142 | R11: 58870 | S11: 59484 | T11: 62230 | U11: 61984 | V11: 63213 | W11: 63334 | X11: 107292 | Y11: 100363 | Z11: 69455 | AA11: 65291
A12: DGO | B12: 6106 | C12: 6004 | D12: 5699 | E12: 5902 | F12: 6308 | G12: 6564 | H12: 6463 | I12: 7440 | J12: 7388 | K12: 7686 | L12: 8628 | M12: 9718 | N12: 9221 | O12: 9274 | P12: 8884 | Q12: 9089 | R12: 8950 | S12: 8975 | T12: 9570 | U12: 9449 | V12: 9311 | W12: 10128 | X12: 13945 | Y12: 13750 | Z12: 11710 | AA12: 10193
A13: GTO | B13: 21759 | C13: 21753 | D13: 21401 | E13: 20375 | F13: 22285 | G13: 22493 | H13: 22237 | I13: 23402 | J13: 22973 | K13: 23664 | L13: 25104 | M13: 25422 | N13: 27132 | O13: 26550 | P13: 27454 | Q13: 28657 | R13: 29474 | S13: 30170 | T13: 32202 | U13: 34794 | V13: 35880 | W13: 37347 | X13: 51677 | Y13: 56302 | Z13: 42867 | AA13: 40090
... A35: Nacional | B35: 442466 | C35: 441647 | D35: 435486 | E35: 441004 | F35: 457680 | G35: 470692 | H35: 472273 | I35: 493957 | J35: 493296 | K35: 513122 | L35: 538288 | M35: 563516 | N35: 590886 | O35: 589646 | P35: 601259 | Q35: 622495 | R35: 632587 | S35: 654593 | T35: 684437 | U35: 693848 | V35: 704803 | W35: 734001 | X35: 1073330 | Y35: 1110122 | Z35: 835433 | AA35: 788830

Sheet Turismo1 (ch)
A1: Datos de Chile
A2: Descripción series | B2: 2005 | C2: 2006 | D2: 2007 | E2: 2008 | F2: 2009 | G2: 2010 | H2: 2011 | I2: 2012 | J2: 2013 | K2: 2014 | L2: 2015 | M2: 2016 | N2: 2017 | O2: 2018 | P2: 2019 | Q2: 2020 | R2: 2021 | S2: 2022 | T2: 2023 | U2: 2024
A3: Llegada de turistas extranjeros | I3: 3468475 | J3: 3576204 | K3: 3674391 | L3: 4478336 | M3: 5640700 | N3: 6449883 | O3: 5722928 | P3: 4517962 | Q3: 1119094 | R3: 190022 | S3: 2030479 | T3: 3730507 | U3: 5239233
A4: Llegada de turistas nacionales
A5: Excursionistas | S5: 238677 | T5: 524527 | U5: 598976
A6: Divisas | S6: 1237037274 | T6: 2374757429 | U6: 3118441197
A7: Ingresos por turismo netas en uf | B7: ='Turismo2 (ch)'!B12 -> 287827169 | C7: ='Turismo2 (ch)'!C12 -> 328000840 | D7: ='Turismo2 (ch)'!D12 -> 328041734 | E7: ='Turismo2 (ch)'!E12 -> 323008958 | F7: ='Turismo2 (ch)'!F12 -> 381527383 | G7: ='Turismo2 (ch)'!G12 -> 343302761 | H7: ='Turismo2 (ch)'!H12 -> 435512879 | I7: ='Turismo2 (ch)'!I12 -> 413230817 | ... Q7: ='Turismo2 (ch)'!Q12
A8: Gasto promedio
A9: Ocupacion hotelera
B13: Año | C13: Llegadas de turistas | D13: Var. interanual
B14: 2025 | C14: 3169082 | D14: =+32.6% -> 0.326
B15: 2024 | C15: 5239233 | D15: =+40.4% -> 0.404
B16: 2023 | C16: 3730507 | D16: =+83.7% -> 0.837
B17: 2022 | C17: 2030479 | D17: =+968.5% -> 9.685
B18: 2021 | C18: 190022 | D18: -0.83
B19: 2020 | C19: 1119094 | D19: -0.752
B20: 2019 | C20: 4517962 | D20: -0.211
B21: 2018 | C21: 5722928 | D21: -0.113
B22: 2017 | C22: 6449883 | D22: =+14.3% -> 0.143
B23: 2016 | C23: 5640700 | D23: =+26% -> 0.26
B24: 2015 | C24: 4478336 | D24: =+21.9% -> 0.219
B25: 2014 | C25: 3674391 | D25: =+2.7% -> 0.027
B26: 2013 | C26: 3576204 | D26: -

Sheet Turismo2 (ch)
A2: CHILE: Ventas netas (UF) de empresas según actividad característica del turismo, por tamaño de empresa, total nacional, período 2005-2019
A4: ACT / Tamaño empresa | B4: Ventas netas (UF)
B5: 2005 | C5: 2006 | D5: 2007 | E5: 2008 | F5: 2009 | G5: 2010 | H5: 2011 | I5: 2012 | J5: 2013 | K5: 2014 | L5: 2015 | M5: 2016 | N5: 2017 | O5: 2018 | P5: 2019
A7: Sin Ventas/Sin Información | B7: 0 | C7: 0 | D7: 0 | E7: 0 | F7: 0 | G7: 0 | H7: 0 | I7: 0 | J7: 0 | K7: 0 | L7: 0 | M7: 0 | N7: 0 | O7: 0 | P7: 0
A8: Micro | B8: 25824702 | C8: 27637757 | D8: 27998900 | E8: 29021691 | F8: 29577620 | G8: 30826631 | H8: 32896940 | I8: 34997832 | J8: 37061506 | K8: 39240693 | L8: 41493250 | M8: 43355515 | N8: 45507568 | O8: 56513030 | P8: 59024895
A9: Pequeña | B9: 61531486 | C9: 66237337 | D9: 69021351 | E9: 72054768 | F9: 74916935 | G9: 82819072 | H9: 92684114 | I9: 96305252 | J9: 105322189 | K9: 113711025 | L9: 120716435 | M9: 127984741 | N9: 124020584 | O9: 154743600 | P9: 162817085
A10: Mediana | B10: 52826051 | C10: 60598758 | D10: 63087490 | E10: 66940314 | F10: 68346866 | G10: 73759447 | H10: 77342875 | I10: 84922750 | J10: 88327167 | K10: 95301710 | L10: 99992247 | M10: 106226888 | N10: 92116054 | O10: 119794325 | P10: 128487226
